Workbook
Name Slicer_Country: #N/A
Name Slicer_Month: #N/A
Name Slicer_NewChannel: #N/A
Name Slicer_NewSalesperson: #N/A
Name Slicer_ProductCategory: #N/A
Name Slicer_Region: #N/A

Sheet CohotAnalysis
A3: Row Labels | B3: Sum of GrossRevenue
A4: 01-2023 | B4: 10090676
A5: Brazil | B5: 1037852
A6: Canada | B6: 882622.98
A7: China | B7: 899054.11
A8: France | B8: 758280.92
A9: Germany | B9: 929424.89
A10: India | B10: 1092333.4
A11: Kenya | B11: 947364.87
A12: Nigeria | B12: 881838.68
A13: South Africa | B13: 779927.34
A14: United Kingdom | B14: 1113282.1
A15: USA | B15: 768694.59
... A18: Grand Total | B18: 10945749

Sheet SKUAnalysis
A3: Sum of GrossRevenue | B3: Column Labels
A4: Row Labels | B4: A | C4: B | D4: C | E4: Grand Total
A5: ACC-1021 | D5: 1446.9507 | E5: 1446.9507
A6: ACC-1028 | C6: 10693.885 | E6: 10693.885
A7: ACC-1060 | D7: 5610.0924 | E7: 5610.0924
A8: ACC-1075 | C8: 10893.623 | E8: 10893.623
A9: ACC-1238 | B9: 27465.648 | E9: 27465.648
A10: ACC-1249 | B10: 14431.738 | E10: 14431.738
A11: ACC-1375 | B11: 31513.085 | E11: 31513.085
A12: ACC-1492 | C12: 7382.145 | E12: 7382.145
A13: ACC-1596 | C13: 7507.4515 | E13: 7507.4515
A14: ACC-1604 | C14: 12040.644 | E14: 12040.644
A15: ACC-1659 | B15: 28386.016 | E15: 28386.016
A16: ACC-1663 | C16: 7578.84 | E16: 7578.84
A17: ACC-1731 | B17: 22620.86 | E17: 22620.86
A18: ACC-1770 | D18: 272.986 | E18: 272.986
A19: ACC-1882 | B19: 17964.404 | E19: 17964.404
A20: ACC-2252 | D20: 4569.8508 | E20: 4569.8508
A21: ACC-2364 | C21: 9829.0483 | E21: 9829.0483
A22: ACC-2386 | D22: 5960.334 | E22: 5960.334
A23: ACC-2735 | B23: 14549.029 | E23: 14549.029
A24: ACC-2761 | C24: 10647.727 | E24: 10647.727
A25: ACC-2867 | C25: 8644.6696 | E25: 8644.6696
A26: ACC-2902 | C26: 7969.4615 | E26: 7969.4615
A27: ACC-2903 | C27: 11283.401 | E27: 11283.401
A28: ACC-2988 | B28: 53034.364 | E28: 53034.364
A29: ACC-2990 | D29: 1547.35 | E29: 1547.35
A30: ACC-3068 | C30: 7105.3528 | E30: 7105.3528
A31: ACC-3103 | B31: 23195.018 | E31: 23195.018
A32: ACC-3349 | D32: 1010.3759 | E32: 1010.3759
A33: ACC-3385 | C33: 10388.43 | E33: 10388.43
A34: ACC-3415 | B34: 15530.93 | E34: 15530.93
A35: ACC-3551 | D35: 908.037 | E35: 908.037
A36: ACC-3567 | C36: 7568.9632 | E36: 7568.9632
A37: ACC-3645 | B37: 19628.477 | E37: 19628.477
A38: ACC-3721 | B38: 22526.66 | E38: 22526.66
A39: ACC-3833 | C39: 6732.4334 | E39: 6732.4334
A40: ACC-3951 | C40: 7235.2135 | E40: 7235.2135
A41: ACC-3961 | C41: 10936.992 | E41: 10936.992
A42: ACC-3989 | C42: 10382.659 | E42: 10382.659
A43: ACC-4056 | D43: 4417.8334 | E43: 4417.8334
A44: ACC-4124 | C44: 11015.51 | E44: 11015.51
A45: ACC-4483 | B45: 19066.045 | E45: 19066.045
A46: ACC-4490 | B46: 35396.278 | E46: 35396.278
A47: ACC-4511 | D47: 2117.4835 | E47: 2117.4835
A48: ACC-4587 | D48: 4577.148 | E48: 4577.148
A49: ACC-4631 | B49: 26759.288 | E49: 26759.288
A50: ACC-4766 | D50: 1030.7574 | E50: 1030.7574
A51: ACC-4815 | C51: 9022.35 | E51: 9022.35
A52: ACC-5079 | D52: 5533.623 | E52: 5533.623
A53: ACC-5144 | B53: 15860.782 | E53: 15860.782
A54: ACC-5150 | B54: 20163.409 | E54: 20163.409
A55: ACC-5177 | B55: 34139.16 | E55: 34139.16
A56: ACC-5206 | D56: 930.17574 | E56: 930.17574
A57: ACC-5260 | C57: 7854.6694 | E57: 7854.6694
A58: ACC-5334 | B58: 26552.603 | E58: 26552.603
A59: ACC-5422 | C59: 12699.28 | E59: 12699.28
A60: ACC-5780 | D60: 4790.1068 | E60: 4790.1068
A61: ACC-6223 | B61: 26765.04 | E61: 26765.04
A62: ACC-6348 | B62: 14894.904 | E62: 14894.904
A63: ACC-6543 | C63: 13321.14 | E63: 13321.14
A64: ACC-6594 | B64: 24278.849 | E64: 24278.849
A65: ACC-6626 | B65: 79082.507 | E65: 79082.507
A66: ACC-7047 | D66: 4071.8 | E66: 4071.8
A67: ACC-7078 | B67: 32086.376 | E67: 32086.376
A68: ACC-7240 | C68: 11859.695 | E68: 11859.695
A69: ACC-7354 | C69: 13108.786 | E69: 13108.786
A70: ACC-7671 | D70: 2719.8567 | E70: 2719.8567
A71: ACC-7713 | B71: 13856.524 | E71: 13856.524
A72: ACC-7838 | B72: 35167.745 | E72: 35167.745
A73: ACC-7906 | C73: 8366.02 | E73: 8366.02
A74: ACC-7938 | B74: 16006.143 | E74: 16006.143
A75: ACC-8094 | D75: 6066.5465 | E75: 6066.5465
A76: ACC-8098 | B76: 38096.184 | E76: 38096.184
A77: ACC-8178 | D77: 3021.5016 | E77: 3021.5016
A78: ACC-8242 | D78: 4737.2198 | E78: 4737.2198
A79: ACC-8557 | B79: 23375.594 | E79: 23375.594
A80: ACC-8620 | B80: 14752.706 | E80: 14752.706
A81: ACC-8683 | C81: 8596.2906 | E81: 8596.2906
A82: ACC-8999 | B82: 17847.907 | E82: 17847.907
A83: ACC-9038 | B83: 20079.344 | E83: 20079.344
A84: ACC-9150 | B84: 16013.682 | E84: 16013.682
A85: ACC-9162 | B85: 33062.236 | E85: 33062.236
A86: ACC-9283 | B86: 46450.26 | E86: 46450.26
A87: ACC-9445 | B87: 20430.772 | E87: 20430.772
A88: ACC-9533 | B88: 43084.872 | E88: 43084.872
A89: ACC-9591 | C89: 7689.456 | E89: 7689.456
A90: ACC-9644 | B90: 23668.56 | E90: 23668.56
A91: ACC-9820 | D91: 549.8001 | E91: 549.8001
A92: CMP-1009 | C92: 6874.4829 | E92: 6874.4829
A93: CMP-1072 | D93: 2316.2622 | E93: 2316.2622
A94: CMP-1156 | B94: 33308.55 | E94: 33308.55
A95: CMP-1220 | B95: 15374.563 | E95: 15374.563
A96: CMP-1223 | D96: 6137.802 | E96: 6137.802
A97: CMP-1470 | D97: 2077.46 | E97: 2077.46
A98: CMP-1555 | B98: 13983.753 | E98: 13983.753
A99: CMP-1559 | B99: 27331.83 | E99: 27331.83
A100: CMP-1632 | D100: 97.0154 | E100: 97.0154
A101: CMP-1940 | B101: 40476.013 | E101: 40476.013
A102: CMP-2015 | B102: 16946.092 | E102: 16946.092
...

Sheet Cannibalization
A3: Sum of GrossRevenue | B3: Column Labels
A4: Row Labels | B4: Direct | C4: Distributor | D4: Marketplace | E4: Online | F4: Retail | G4: Grand Total
A5: Africa | B5: 0.042229772 | C5: 0.060964173 | D5: 0.048189289 | E5: 0.039595858 | F5: 0.047390235 | G5: 0.23836933
A6: Americas | B6: 0.069536141 | C6: 0.051971172 | D6: 0.033471983 | E6: 0.063033735 | F6: 0.027668602 | G6: 0.24568163
A7: Asia | B7: 0.058721723 | C7: 0.046540332 | D7: 0.053672492 | E7: 0.037791978 | F7: 0.063325193 | G7: 0.26005172
A8: Europe | B8: 0.076980975 | C8: 0.029561121 | D8: 0.052045458 | E8: 0.053482563 | F8: 0.043827206 | G8: 0.25589732
A9: Grand Total | B9: 0.24746861 | C9: 0.1890368 | D9: 0.18737922 | E9: 0.19390413 | F9: 0.18221124 | G9: 1

Sheet Top3RevperOrder
A3: Row Labels | B3: Sum of GrossRevenue | C3: Sum of GrossProfit
A4: B. Chen | B4: 893735.66 | C4: 359716.93
A5: K. Singh | B5: 883348.13 | C5: 297798.44
A6: M. Rossi | B6: 976696.7 | C6: 363428.29
A7: Grand Total | B7: 2753780.5 | C7: 1020943.7

Sheet Bottom3RevperOrder
A3: Row Labels | B3: Sum of GrossRevenue | C3: Sum of GrossProfit
A4: A. Patel | B4: 979572.27 | C4: 375845.12
A5: B. Chen | B5: 933252.47 | C5: 380805.21
A6: C. Otieno | B6: 689776.36 | C6: 237357.22
A7: D. Smith | B7: 576820.19 | C7: 203186.69
A8: E. Garcia | B8: 543846.44 | C8: 219222.23
A9: F. Müller | B9: 812637.17 | C9: 292994.34
A10: G. Dubois | B10: 510653.71 | C10: 173517.26
A11: H. Kim | B11: 749851.6 | C11: 336984.24
A12: I. Johnson | B12: 541165.67 | C12: 198714.78
A13: J. Njeri | B13: 802384.66 | C13: 333460.55
A14: K. Singh | B14: 913477.32 | C14: 305380.91
A15: L. Okafor | B15: 853458.04 | C15: 289448.3
... A19: Grand Total | B19: 10945749 | C19: 4058529.3

Sheet RevenueByMonth
A3: Row Labels | B3: Sum of GrossRevenue
A4: Jan | B4: 701241.31
A5: Feb | B5: 963301
A6: Mar | B6: 799192.62
A7: Apr | B7: 947246.58
A8: May | B8: 1262901.9
A9: Jun | B9: 1252974.2
A10: Jul | B10: 1323460
A11: Aug | B11: 1090009.6
A12: Sep | B12: 661140.77
A13: Oct | B13: 663847.32
A14: Nov | B14: 543953.69
A15: Dec | B15: 736480.3
A16: Grand Total | B16: 10945749

Sheet ProfitByReg&Chanel
A3: Sum of GrossProfit | B3: Column Labels
A4: Row Labels | B4: Africa | C4: Americas | D4: Asia | E4: Europe | F4: Grand Total
A5: Direct | B5: 187203.7 | C5: 260636.72 | D5: 256155.81 | E5: 301850.55 | F5: 1005846.8
A6: Distributor | B6: 232409.49 | C6: 230034.23 | D6: 172459.12 | E6: 119311.2 | F6: 754214.03
A7: Marketplace | B7: 186864.8 | C7: 115566.17 | D7: 199689.53 | E7: 270217.14 | F7: 772337.64
A8: Online | B8: 180839.19 | C8: 265252.12 | D8: 152920.54 | E8: 219741.99 | F8: 818753.84
A9: Retail | B9: 190525.56 | C9: 87507.989 | D9: 223965.87 | E9: 205377.6 | F9: 707377.02
A10: Grand Total | B10: 977842.74 | C10: 958997.23 | D10: 1005190.9 | E10: 1116498.5 | F10: 4058529.3

Sheet Top10SKUbyRev
A3: Row Labels | B3: Sum of GrossRevenue
A4: NET-5987 | B4: 82141.34
A5: NET-5523 | B5: 79548.756
A6: NET-2365 | B6: 109244
A7: MON-6962 | B7: 92715.25
A8: MON-6699 | B8: 85637.74
A9: MON-2266 | B9: 87404.93
A10: LAP-8910 | B10: 102122.94
A11: LAP-3904 | B11: 82514.712
A12: CMP-8851 | B12: 139277.83
A13: CMP-3938 | B13: 84136.12
A14: Grand Total | B14: 944743.62

Sheet LeadTimeDays
A3: Average of MetTarget | B3: Column Labels
A4: Row Labels | B4: Brazil | C4: Canada | D4: China | E4: France | F4: Germany | G4: India | H4: Japan | I4: Kenya | J4: Nigeria | K4: South Africa | L4: United Kingdom | M4: USA | N4: Grand Total
A5: Accessories | B5: 0.4 | C5: 0.33333333 | D5: 0.75 | E5: 0.14285714 | F5: 0.44444444 | G5: 0.25 | H5: 0.2 | I5: 0.4 | J5: 0.46153846 | K5: 0.5 | L5: 0.125 | M5: 0.5 | N5: 0.36363636
A6: Components | B6: 0.14285714 | C6: 0.5 | D6: 0 | E6: 0.3 | F6: 0.33333333 | G6: 0.2 | H6: 0.375 | I6: 0.2 | J6: 0.33333333 | K6: 0.45454545 | L6: 0.28571429 | M6: 0.4 | N6: 0.28571429
A7: Laptops | B7: 0.2 | C7: 0.33333333 | D7: 0.2 | E7: 0.33333333 | F7: 0.28571429 | G7: 0.11111111 | H7: 0.42857143 | I7: 0.7 | J7: 0.5 | K7: 0.28571429 | L7: 0.44444444 | M7: 0.2 | N7: 0.35365854
A8: Monitors | B8: 0.25 | C8: 0 | D8: 0.16666667 | E8: 0.3 | F8: 0.1 | G8: 0.16666667 | H8: 0.28571429 | I8: 0 | J8: 0.6 | K8: 0.14285714 | L8: 0.28571429 | M8: 0.11111111 | N8: 0.20212766
A9: Networking | B9: 0.16666667 | C9: 0 | D9: 0.5 | E9: 0.33333333 | F9: 0.25 | G9: 0.14285714 | H9: 0.083333333 | I9: 0.33333333 | J9: 0.5 | K9: 0.28571429 | L9: 0.22222222 | M9: 0.5 | N9: 0.26744186
A10: Phones | B10: 0.55555556 | C10: 0 | D10: 0.14285714 | E10: 0 | F10: 0.14285714 | G10: 0.22222222 | H10: 0.090909091 | I10: 0.13333333 | J10: 0.16666667 | K10: 0.5 | L10: 0.25 | M10: 0.1 | N10: 0.19318182
A11: Printers | B11: 0.28571429 | C11: 0.15384615 | D11: 0 | E11: 0.16666667 | F11: 0.125 | G11: 0.33333333 | H11: 0.33333333 | I11: 0.125 | J11: 0.5 | K11: 0.2 | L11: 0.3 | M11: 0.75 | N11: 0.25242718
A12: Grand Total | B12: 0.29032258 | C12: 0.20454545 | D12: 0.19607843 | E12: 0.24074074 | F12: 0.23529412 | G12: 0.19672131 | H12: 0.23728814 | I12: 0.30357143 | J12: 0.43181818 | K12: 0.33333333 | L12: 0.27777778 | M12: 0.35294118 | N12: 0.2721519

Sheet OutliersbySalespersonandRegion
B3: Column Labels
B4: Africa | D4: Americas | F4: Asia | H4: Europe | J4: Total Average of HighestDscnt | K4: Total Count of OrderID
A5: Row Labels | B5: Average of HighestDscnt | C5: Count of OrderID | D5: Average of HighestDscnt | E5: Count of OrderID | F5: Average of HighestDscnt | G5: Count of OrderID | H5: Average of HighestDscnt | I5: Count of OrderID
A6: A. Patel | B6: 0.17647059 | C6: 17 | D6: 0.5 | E6: 10 | F6: 0 | G6: 10 | H6: 0.1 | I6: 10 | J6: 0.19148936 | K6: 47
A7: B. Chen | B7: 0 | C7: 8 | D7: 0.125 | E7: 8 | F7: 0.11764706 | G7: 17 | H7: 0.125 | I7: 16 | J7: 0.10204082 | K7: 49
A8: C. Otieno | B8: 0.25 | C8: 8 | D8: 0.14285714 | E8: 14 | F8: 0.3 | G8: 10 | H8: 0.2 | I8: 5 | J8: 0.21621622 | K8: 37
A9: D. Smith | B9: 0.2 | C9: 10 | D9: 0.5 | E9: 8 | F9: 0.11111111 | G9: 9 | H9: 0.090909091 | I9: 11 | J9: 0.21052632 | K9: 38
A10: E. Garcia | B10: 0.2 | C10: 5 | D10: 0 | E10: 5 | F10: 0 | G10: 8 | H10: 0.125 | I10: 16 | J10: 0.088235294 | K10: 34
A11: F. Müller | B11: 0 | C11: 13 | D11: 0.066666667 | E11: 15 | F11: 0.25 | G11: 12 | H11: 0 | I11: 11 | J11: 0.078431373 | K11: 51
A12: G. Dubois | B12: 0 | C12: 3 | D12: 0.125 | E12: 8 | F12: 0.090909091 | G12: 11 | H12: 0.125 | I12: 8 | J12: 0.1 | K12: 30
A13: H. Kim | B13: 0.14285714 | C13: 7 | D13: 0.083333333 | E13: 12 | F13: 0.125 | G13: 16 | H13: 0.076923077 | I13: 13 | J13: 0.10416667 | K13: 48
A14: I. Johnson | B14: 0.25 | C14: 8 | D14: 0.35714286 | E14: 14 | F14: 0.125 | G14: 8 | H14: 0.125 | I14: 8 | J14: 0.23684211 | K14: 38
A15: J. Njeri | B15: 0.25 | C15: 12 | D15: 0 | E15: 10 | F15: 0.10526316 | G15: 19 | H15: 0.11111111 | I15: 9 | J15: 0.12 | K15: 50
A16: K. Singh | B16: 0 | C16: 14 | D16: 0.1 | E16: 10 | F16: 0.11111111 | G16: 9 | H16: 0.15384615 | I16: 13 | J16: 0.086956522 | K16: 46
A17: L. Okafor | B17: 0.2 | C17: 10 | D17: 0.25 | E17: 12 | F17: 0.21428571 | G17: 14 | H17: 0 | I17: 10 | J17: 0.17391304 | K17: 46
... A21: Grand Total | B21: 0.15172414 | C21: 145 | D21: 0.17197452 | E21: 157 | F21: 0.14035088 | G21: 171 | H21: 0.10691824 | I21: 159 | J21: 0.14240506 | K21: 632

Sheet Revenue by productcategory
A3: Row Labels | B3: Sum of GrossRevenue
A4: Accessories | B4: 1342046.6
A5: Components | B5: 1550200.5
A6: Laptops | B6: 1711094.4
A7: Monitors | B7: 1551590.9
A8: Networking | B8: 1774683.1
A9: Phones | B9: 1399242.2
A10: Printers | B10: 1616910.2
A11: Grand Total | B11: 10945768

Sheet Data
A1: OrderID | B1: OrderDate | C1: NewOrderDate | D1: RequiredDate | E1: NewRequiredDate | F1: LeadTimedays | G1: MetTarget | H1: Month | I1: Quarters | J1: FirstOrderDate | K1: FirstOrderMonth | L1: Region | M1: Country | N1: City | O1: NewCity | P1: CustomerSegment | Q1: Channel | R1: NewChannel | S1: Salesperson | T1: NewSalesperson | U1: ProductCategory | V1: PriceBand | W1: SKU | X1: SKUcategory | Y1: UnitCost | Z1: UnitPrice | AA1: NewUnitPrice | AB1: DiscountPct | AC1: NewDiscountPct | AD1: HighestDscnt | AE1: Quantity | AF1: GrossRevenue | AG1: CostOfGoods | AH1: GrossProfit | AI1: MarginPct | AJ1: C.Rev | AK1: C.Pct | AL1: ScenarioDiscount | AM1: ScenarioQuantity | AN1: ScenarioUnitCost | AO1: ScenarioRevenue
A2: ORD-2025-132174 | B2: 45855 | C2: =IF(D2<B2,D2,B2) -> 45855 | D2: 45861 | E2: =IF(D2<B2,B2,D2) -> 45861 | F2: =E2-C2 -> 6 | G2: =IF(Data!F2<=7,1,0) -> 1 | H2: =TEXT(C2,"MM-YYYY") -> 07-2025 | I2: ="Q"&ROUNDUP(MONTH(H2)/3,0)&"-"&YEAR(H2) -> Q3-2025 | J2: =_xlfn.MINIFS(C:C,M:M,M2) -> 44928 | K2: =TEXT(J2,"MM-YYYY") -> 01-2023 | L2: Americas | M2: Canada | N2: Vancouver | O2: =IF(N2="",_xlfn.XLOOKUP(M2,M:M,N:N),N2) -> Vancouver | P2: Consumer | Q2: Online | R2: =IF(Q2="",_xlfn.XLOOKUP(M2,M:M,Q:Q),Q2) -> Online | S2: H. Kim | T2: =IF(S2="",_xlfn.XLOOKUP(L2,L:L,S:S),S2) -> H. Kim | U2: Components | V2: =IF(AA2<815.0987,"Low",IF(AA2<1640.058,"Medium","High")) -> High | W2: CMP-8851 | X2: =IF(AK2<=80%,"A",IF(AK2<=95%,"B","C")) -> A | Y2: 1364.89 | Z2: 2757.54 | AA2: =ABS(Z2) -> 2757.54 | AB2: 0.172 | AC2: =MIN(AB2,30%) -> 0.172 | AD2: =IF(AC2>20%,1,0) -> 0 | AE2: 61 | AF2: =AA2*AE2*(1-AC2) -> 139277.83 | AG2: =Y2*AE2 -> 83258.29 | AH2: =ABS(AF2-AG2) -> 56019.54 | AI2: =IF(AF2=0,0,AH2/AF2) -> 0.40221434 | AJ2: 139277.83 | AK2: =AJ2/SUM(AF:AF) -> 0.012724354 | AL2: =MIN(AC2,'What-If Analysis'!$B$2) -> 0.172 | AM2: =AE2*(1+'What-If Analysis'!$B$3) -> 79.3 | AN2: =Y2*(1+'What-If Analysis'!$B$4) -> 1501.379 | AO2: =AA2*AM2*(1-AL2) -> 181061.18
A3: ORD-2025-639542 | B3: 45817 | C3: =IF(D3<B3,D3,B3) -> 45817 | D3: 45826 | E3: =IF(D3<B3,B3,D3) -> 45826 | F3: =E3-C3 -> 9 | G3: =IF(Data!F624<=7,1,0) -> 1 | H3: =TEXT(C3,"MM-YYYY") -> 06-2025 | I3: ="Q"&ROUNDUP(MONTH(H3)/3,0)&"-"&YEAR(H3) -> Q2-2025 | J3: =_xlfn.MINIFS(C:C,M:M,M3) -> 44936 | K3: =TEXT(J3,"MM-YYYY") -> 01-2023 | L3: Europe | M3: France | N3: Marseille | O3: =IF(N3="",_xlfn.XLOOKUP(M3,M:M,N:N),N3) -> Marseille | P3: Small Business | Q3: Marketplace | R3: =IF(Q3="",_xlfn.XLOOKUP(M3,M:M,Q:Q),Q3) -> Marketplace | S3: H. Kim | T3: =IF(S3="",_xlfn.XLOOKUP(L3,L:L,S:S),S3) -> H. Kim | U3: Accessories | V3: =IF(AA3<815.0987,"Low",IF(AA3<1640.058,"Medium","High")) -> Low | W3: ACC-1770 | X3: =IF(AK3<=80%,"A",IF(AK3<=95%,"B","C")) -> A | Y3: 1225.5 | Z3: -5.27 | AA3: =ABS(Z3) -> 5.27 | AB3: 0.075 | AC3: =MIN(AB3,30%) -> 0.075 | AD3: =IF(AC3>20%,1,0) -> 0 | AE3: 56 | AF3: =AA3*AE3*(1-AC3) -> 272.986 | AG3: =Y3*AE3 -> 68628 | AH3: =ABS(AF3-AG3) -> 68355.014 | AI3: =IF(AF3=0,0,AH3/AF3) -> 250.39751 | AJ3: =AJ2+AF3 -> 139550.82 | AK3: =AJ3/SUM(AF:AF) -> 0.012749294 | AL3: =MIN(AC3,'What-If Analysis'!$B$2) -> 0.075 | AM3: =AE3*(1+'What-If Analysis'!$B$3) -> 72.8 | AN3: =Y3*(1+'What-If Analysis'!$B$4) -> 1348.05 | AO3: =AA3*AM3*(1-AL3) -> 354.8818
A4: ORD-2023-906481 | B4: 45048 | C4: =IF(D4<B4,D4,B4) -> 45048 | D4: 45064 | E4: =IF(D4<B4,B4,D4) -> 45064 | F4: =E4-C4 -> 16 | G4: =IF(Data!F6<=7,1,0) -> 1 | H4: =TEXT(C4,"MM-YYYY") -> 05-2023 | I4: ="Q"&ROUNDUP(MONTH(H4)/3,0)&"-"&YEAR(H4) -> Q2-2023 | J4: =_xlfn.MINIFS(C:C,M:M,M4) -> 44955 | K4: =TEXT(J4,"MM-YYYY") -> 01-2023 | L4: Asia | M4: India | N4: Delhi | O4: =IF(N4="",_xlfn.XLOOKUP(M4,M:M,N:N),N4) -> Delhi | P4: Small Business | Q4: Marketplace | R4: =IF(Q4="",_xlfn.XLOOKUP(M4,M:M,Q:Q),Q4) -> Marketplace | S4: K. Singh | T4: =IF(S4="",_xlfn.XLOOKUP(L4,L:L,S:S),S4) -> K. Singh | U4: Monitors | V4: =IF(AA4<815.0987,"Low",IF(AA4<1640.058,"Medium","High")) -> High | W4: MON-2266 | X4: =IF(AK4<=80%,"A",IF(AK4<=95%,"B","C")) -> A | Y4: 1463.92 | Z4: 2252.24 | AA4: =ABS(Z4) -> 2252.24 | AB4: 0.118 | AC4: =MIN(AB4,30%) -> 0.118 | AD4: =IF(AC4>20%,1,0) -> 0 | AE4: 44 | AF4: =AA4*AE4*(1-AC4) -> 87404.93 | AG4: =Y4*AE4 -> 64412.48 | AH4: =ABS(AF4-AG4) -> 22992.45 | AI4: =IF(AF4=0,0,AH4/AF4) -> 0.26305667 | AJ4: =AJ3+AF4 -> 226955.75 | AK4: =AJ4/SUM(AF:AF) -> 0.020734566 | AL4: =MIN(AC4,'What-If Analysis'!$B$2) -> 0.118 | AM4: =AE4*(1+'What-If Analysis'!$B$3) -> 57.2 | AN4: =Y4*(1+'What-If Analysis'!$B$4) -> 1610.312 | AO4: =AA4*AM4*(1-AL4) -> 113626.41
A5: ORD-2024-247979 | B5: 45598 | C5: =IF(D5<B5,D5,B5) -> 45598 | D5: 45614 | E5: =IF(D5<B5,B5,D5) -> 45614 | F5: =E5-C5 -> 16 | G5: =IF(Data!F13<=7,1,0) -> 0 | H5: =TEXT(C5,"MM-YYYY") -> 11-2024 | I5: ="Q"&ROUNDUP(MONTH(H5)/3,0)&"-"&YEAR(H5) -> Q4-2024 | J5: =_xlfn.MINIFS(C:C,M:M,M5) -> 44955 | K5: =TEXT(J5,"MM-YYYY") -> 01-2023 | L5: Asia | M5: India | N5: Mumbai | O5: =IF(N5="",_xlfn.XLOOKUP(M5,M:M,N:N),N5) -> Mumbai | P5: Small Business | Q5: Distributor | R5: =IF(Q5="",_xlfn.XLOOKUP(M5,M:M,Q:Q),Q5) -> Distributor | S5: O. Wang | T5: =IF(S5="",_xlfn.XLOOKUP(L5,L:L,S:S),S5) -> O. Wang | U5: Monitors | V5: =IF(AA5<815.0987,"Low",IF(AA5<1640.058,"Medium","High")) -> High | W5: MON-5188 | X5: =IF(AK5<=80%,"A",IF(AK5<=95%,"B","C")) -> A | Y5: 1233.58 | Z5: 1912.51 | AA5: =ABS(Z5) -> 1912.51 | AB5: 0.255 | AC5: =MIN(AB5,30%) -> 0.255 | AD5: =IF(AC5>20%,1,0) -> 1 | AE5: 51 | AF5: =AA5*AE5*(1-AC5) -> 72665.817 | AG5: =Y5*AE5 -> 62912.58 | AH5: =ABS(AF5-AG5) -> 9753.2375 | AI5: =IF(AF5=0,0,AH5/AF5) -> 0.13422043 | AJ5: =AJ4+AF5 -> 299621.56 | AK5: =AJ5/SUM(AF:AF) -> 0.027373279 | AL5: =MIN(AC5,'What-If Analysis'!$B$2) -> 0.2 | AM5: =AE5*(1+'What-If Analysis'!$B$3) -> 66.3 | AN5: =Y5*(1+'What-If Analysis'!$B$4) -> 1356.938 | AO5: =AA5*AM5*(1-AL5) -> 101439.53
A6: ORD-2025-650841 | B6: 45841 | C6: =IF(D6<B6,D6,B6) -> 45841 | D6: 45844 | E6: =IF(D6<B6,B6,D6) -> 45844 | F6: =E6-C6 -> 3 | G6: =IF(Data!F4<=7,1,0) -> 0 | H6: =TEXT(C6,"MM-YYYY") -> 07-2025 | I6: ="Q"&ROUNDUP(MONTH(H6)/3,0)&"-"&YEAR(H6) -> Q3-2025 | J6: =_xlfn.MINIFS(C:C,M:M,M6) -> 44939 | K6: =TEXT(J6,"MM-YYYY") -> 01-2023 | L6: Africa | M6: Nigeria | N6: Lagos | O6: =IF(N6="",_xlfn.XLOOKUP(M6,M:M,N:N),N6) -> Lagos | P6: Consumer | Q6: Online | R6: =IF(Q6="",_xlfn.XLOOKUP(M6,M:M,Q:Q),Q6) -> Online | T6: A. Patel | U6: Laptops | V6: =IF(AA6<815.0987,"Low",IF(AA6<1640.058,"Medium","High")) -> High | W6: LAP-8910 | X6: =IF(AK6<=80%,"A",IF(AK6<=95%,"B","C")) -> A | Y6: 1313.3 | Z6: 2884.34 | AA6: =ABS(Z6) -> 2884.34 | AB6: 0.157 | AC6: =MIN(AB6,30%) -> 0.157 | AD6: =IF(AC6>20%,1,0) -> 0 | AE6: 42 | AF6: =AA6*AE6*(1-AC6) -> 102122.94 | AG6: =Y6*AE6 -> 55158.6 | AH6: =ABS(AF6-AG6) -> 46964.342 | AI6: =IF(AF6=0,0,AH6/AF6) -> 0.45988043 | AJ6: =AJ5+AF6 -> 401744.51 | AK6: =AJ6/SUM(AF:AF) -> 0.036703181 | AL6: =MIN(AC6,'What-If Analysis'!$B$2) -> 0.157 | AM6: =AE6*(1+'What-If Analysis'!$B$3) -> 54.6 | AN6: =Y6*(1+'What-If Analysis'!$B$4) -> 1444.63 | AO6: =AA6*AM6*(1-AL6) -> 132759.82
A7: ORD-2023-884625 | B7: 44976 | C7: =IF(D7<B7,D7,B7) -> 44976 | D7: 44997 | E7: =IF(D7<B7,B7,D7) -> 44997 | F7: =E7-C7 -> 21 | G7: =IF(Data!F7<=7,1,0) -> 0 | H7: =TEXT(C7,"MM-YYYY") -> 02-2023 | I7: ="Q"&ROUNDUP(MONTH(H7)/3,0)&"-"&YEAR(H7) -> Q1-2023 | J7: =_xlfn.MINIFS(C:C,M:M,M7) -> 44947 | K7: =TEXT(J7,"MM-YYYY") -> 01-2023 | L7: Europe | M7: Germany | N7: Berlin | O7: =IF(N7="",_xlfn.XLOOKUP(M7,M:M,N:N),N7) -> Berlin | P7: Small Business | Q7: Direct | R7: =IF(Q7="",_xlfn.XLOOKUP(M7,M:M,Q:Q),Q7) -> Direct | S7: L. Okafor | T7: =IF(S7="",_xlfn.XLOOKUP(L7,L:L,S:S),S7) -> L. Okafor | U7: Monitors | V7: =IF(AA7<815.0987,"Low",IF(AA7<1640.058,"Medium","High")) -> High | W7: MON-6699 | X7: =IF(AK7<=80%,"A",IF(AK7<=95%,"B","C")) -> A | Y7: 1234.81 | Z7: 2055.24 | AA7: =ABS(Z7) -> 2055.24 | AB7: 0.053 | AC7: =MIN(AB7,30%) -> 0.053 | AD7: =IF(AC7>20%,1,0) -> 0 | AE7: 44 | AF7: =AA7*AE7*(1-AC7) -> 85637.74 | AG7: =Y7*AE7 -> 54331.64 | AH7: =ABS(AF7-AG7) -> 31306.1 | AI7: =IF(AF7=0,0,AH7/AF7) -> 0.3655643 | AJ7: =AJ6+AF7 -> 487382.25 | AK7: =AJ7/SUM(AF:AF) -> 0.044527003 | AL7: =MIN(AC7,'What-If Analysis'!$B$2) -> 0.053 | AM7: =AE7*(1+'What-If Analysis'!$B$3) -> 57.2 | AN7: =Y7*(1+'What-If Analysis'!$B$4) -> 1358.291 | AO7: =AA7*AM7*(1-AL7) -> 111329.06
A8: ORD-2025-845715 | B8: 45761 | C8: =IF(D8<B8,D8,B8) -> 45761 | D8: 45781 | E8: =IF(D8<B8,B8,D8) -> 45781 | F8: =E8-C8 -> 20 | G8: =IF(Data!F5<=7,1,0) -> 0 | H8: =TEXT(C8,"MM-YYYY") -> 04-2025 | I8: ="Q"&ROUNDUP(MONTH(H8)/3,0)&"-"&YEAR(H8) -> Q2-2025 | J8: =_xlfn.MINIFS(C:C,M:M,M8) -> 44945 | K8: =TEXT(J8,"MM-YYYY") -> 01-2023 | L8: Europe | M8: United Kingdom | N8: Birmingham | O8: =IF(N8="",_xlfn.XLOOKUP(M8,M:M,N:N),N8) -> Birmingham | P8: Enterprise | Q8: Marketplace | R8: =IF(Q8="",_xlfn.XLOOKUP(M8,M:M,Q:Q),Q8) -> Marketplace | S8: K. Singh | T8: =IF(S8="",_xlfn.XLOOKUP(L8,L:L,S:S),S8) -> K. Singh | U8: Monitors | V8: =IF(AA8<815.0987,"Low",IF(AA8<1640.058,"Medium","High")) -> High | W8: MON-6962 | X8: =IF(AK8<=80%,"A",IF(AK8<=95%,"B","C")) -> A | Y8: 1413.87 | Z8: 3275 | AA8: =ABS(Z8) -> 3275 | AB8: 0.255 | AC8: =MIN(AB8,30%) -> 0.255 | AD8: =IF(AC8>20%,1,0) -> 1 | AE8: 38 | AF8: =AA8*AE8*(1-AC8) -> 92715.25 | AG8: =Y8*AE8 -> 53727.06 | AH8: =ABS(AF8-AG8) -> 38988.19 | AI8: =IF(AF8=0,0,AH8/AF8) -> 0.4205154 | AJ8: =AJ7+AF8 -> 580097.5 | AK8: =AJ8/SUM(AF:AF) -> 0.052997423 | AL8: =MIN(AC8,'What-If Analysis'!$B$2) -> 0.2 | AM8: =AE8*(1+'What-If Analysis'!$B$3) -> 49.4 | AN8: =Y8*(1+'What-If Analysis'!$B$4) -> 1555.257 | AO8: =AA8*AM8*(1-AL8) -> 129428
A9: ORD-2024-948800 | B9: 45378 | C9: =IF(D9<B9,D9,B9) -> 45378 | D9: 45393 | E9: =IF(D9<B9,B9,D9) -> 45393 | F9: =E9-C9 -> 15 | G9: =IF(Data!F11<=7,1,0) -> 0 | H9: =TEXT(C9,"MM-YYYY") -> 03-2024 | I9: ="Q"&ROUNDUP(MONTH(H9)/3,0)&"-"&YEAR(H9) -> Q1-2024 | J9: =_xlfn.MINIFS(C:C,M:M,M9) -> 44939 | K9: =TEXT(J9,"MM-YYYY") -> 01-2023 | L9: Americas | M9: USA | N9: San Francisco | O9: =IF(N9="",_xlfn.XLOOKUP(M9,M:M,N:N),N9) -> San Francisco | P9: Small Business | Q9: Direct | R9: =IF(Q9="",_xlfn.XLOOKUP(M9,M:M,Q:Q),Q9) -> Direct | S9: O. Wang | T9: =IF(S9="",_xlfn.XLOOKUP(L9,L:L,S:S),S9) -> O. Wang | U9: Networking | V9: =IF(AA9<815.0987,"Low",IF(AA9<1640.058,"Medium","High")) -> High | W9: NET-5523 | X9: =IF(AK9<=80%,"A",IF(AK9<=95%,"B","C")) -> A | Y9: 1338.35 | Z9: 2247.14 | AA9: =ABS(Z9) -> 2247.14 | AB9: 0.115 | AC9: =MIN(AB9,30%) -> 0.115 | AD9: =IF(AC9>20%,1,0) -> 0 | AE9: 40 | AF9: =AA9*AE9*(1-AC9) -> 79548.756 | AG9: =Y9*AE9 -> 53534 | AH9: =ABS(AF9-AG9) -> 26014.756 | AI9: =IF(AF9=0,0,AH9/AF9) -> 0.32702907 | AJ9: =AJ8+AF9 -> 659646.25 | AK9: =AJ9/SUM(AF:AF) -> 0.060264959 | AL9: =MIN(AC9,'What-If Analysis'!$B$2) -> 0.115 | AM9: =AE9*(1+'What-If Analysis'!$B$3) -> 52 | AN9: =Y9*(1+'What-If Analysis'!$B$4) -> 1472.185 | AO9: =AA9*AM9*(1-AL9) -> 103413.38
A10: ORD-2024-508213 | B10: 45618 | C10: =IF(D10<B10,D10,B10) -> 45618 | D10: 45641 | E10: =IF(D10<B10,B10,D10) -> 45641 | F10: =E10-C10 -> 23 | G10: =IF(Data!F8<=7,1,0) -> 0 | H10: =TEXT(C10,"MM-YYYY") -> 11-2024 | I10: ="Q"&ROUNDUP(MONTH(H10)/3,0)&"-"&YEAR(H10) -> Q4-2024 | J10: =_xlfn.MINIFS(C:C,M:M,M10) -> 44946 | K10: =TEXT(J10,"MM-YYYY") -> 01-2023 | L10: Africa | M10: Kenya | N10: Mombasa | O10: =IF(N10="",_xlfn.XLOOKUP(M10,M:M,N:N),N10) -> Mombasa | P10: Non-Profit | Q10: Distributor | R10: =IF(Q10="",_xlfn.XLOOKUP(M10,M:M,Q:Q),Q10) -> Distributor | S10: C. Otieno | T10: =IF(S10="",_xlfn.XLOOKUP(L10,L:L,S:S),S10) -> C. Otieno | U10: Components | V10: =IF(AA10<815.0987,"Low",IF(AA10<1640.058,"Medium","High")) -> High | W10: CMP-3938 | X10: =IF(AK10<=80%,"A",IF(AK10<=95%,"B","C")) -> A | Y10: 1335.76 | Z10: 2665.91 | AA10: =ABS(Z10) -> 2665.91 | AB10: 0.211 | AC10: =MIN(AB10,30%) -> 0.211 | AD10: =IF(AC10>20%,1,0) -> 1 | AE10: 40 | AF10: =AA10*AE10*(1-AC10) -> 84136.12 | AG10: =Y10*AE10 -> 53430.4 | AH10: =ABS(AF10-AG10) -> 30705.72 | AI10: =IF(AF10=0,0,AH10/AF10) -> 0.36495289 | AJ10: =AJ9+AF10 -> 743782.37 | AK10: =AJ10/SUM(AF:AF) -> 0.067951593 | AL10: =MIN(AC10,'What-If Analysis'!$B$2) -> 0.2 | AM10: =AE10*(1+'What-If Analysis'!$B$3) -> 52 | AN10: =Y10*(1+'What-If Analysis'!$B$4) -> 1469.336 | AO10: =AA10*AM10*(1-AL10) -> 110901.86
A11: ORD-2024-713332 | B11: 45448 | C11: =IF(D11<B11,D11,B11) -> 45448 | D11: 45466 | E11: =IF(D11<B11,B11,D11) -> 45466 | F11: =E11-C11 -> 18 | G11: =IF(Data!F22<=7,1,0) -> 1 | H11: =TEXT(C11,"MM-YYYY") -> 06-2024 | I11: ="Q"&ROUNDUP(MONTH(H11)/3,0)&"-"&YEAR(H11) -> Q2-2024 | J11: =_xlfn.MINIFS(C:C,M:M,M11) -> 44946 | K11: =TEXT(J11,"MM-YYYY") -> 01-2023 | L11: Africa | M11: Kenya | N11: Nairobi | O11: =IF(N11="",_xlfn.XLOOKUP(M11,M:M,N:N),N11) -> Nairobi | P11: Consumer | Q11: Distributor | R11: =IF(Q11="",_xlfn.XLOOKUP(M11,M:M,Q:Q),Q11) -> Distributor | S11: D. Smith | T11: =IF(S11="",_xlfn.XLOOKUP(L11,L:L,S:S),S11) -> D. Smith | U11: Laptops | V11: =IF(AA11<815.0987,"Low",IF(AA11<1640.058,"Medium","High")) -> Medium | W11: LAP-1739 | X11: =IF(AK11<=80%,"A",IF(AK11<=95%,"B","C")) -> A | Y11: 1208.74 | Z11: 1594.78 | AA11: =ABS(Z11) -> 1594.78 | AB11: 0.059 | AC11: =MIN(AB11,30%) -> 0.059 | AD11: =IF(AC11>20%,1,0) -> 0 | AE11: 39 | AF11: =AA11*AE11*(1-AC11) -> 58526.831 | AG11: =Y11*AE11 -> 47140.86 | AH11: =ABS(AF11-AG11) -> 11385.971 | AI11: =IF(AF11=0,0,AH11/AF11) -> 0.19454276 | AJ11: =AJ10+AF11 -> 802309.2 | AK11: =AJ11/SUM(AF:AF) -> 0.073298576 | AL11: =MIN(AC11,'What-If Analysis'!$B$2) -> 0.059 | AM11: =AE11*(1+'What-If Analysis'!$B$3) -> 50.7 | AN11: =Y11*(1+'What-If Analysis'!$B$4) -> 1329.614 | AO11: =AA11*AM11*(1-AL11) -> 76084.881
A12: ORD-2023-594955 | B12: 45097 | C12: =IF(D12<B12,D12,B12) -> 45097 | D12: 45115 | E12: =IF(D12<B12,B12,D12) -> 45115 | F12: =E12-C12 -> 18 | G12: =IF(Data!F37<=7,1,0) -> 0 | H12: =TEXT(C12,"MM-YYYY") -> 06-2023 | I12: ="Q"&ROUNDUP(MONTH(H12)/3,0)&"-"&YEAR(H12) -> Q2-2023 | J12: =_xlfn.MINIFS(C:C,M:M,M12) -> 44939 | K12: =TEXT(J12,"MM-YYYY") -> 01-2023 | L12: Americas | M12: USA | N12: New York | O12: =IF(N12="",_xlfn.XLOOKUP(M12,M:M,N:N),N12) -> New York | P12: Consumer | Q12: Marketplace | R12: =IF(Q12="",_xlfn.XLOOKUP(M12,M:M,Q:Q),Q12) -> Marketplace | S12: O. Wang | T12: =IF(S12="",_xlfn.XLOOKUP(L12,L:L,S:S),S12) -> O. Wang | U12: Networking | V12: =IF(AA12<815.0987,"Low",IF(AA12<1640.058,"Medium","High")) -> Medium | W12: NET-3828 | X12: =IF(AK12<=80%,"A",IF(AK12<=95%,"B","C")) -> A | Y12: 1145.53 | Z12: 1278.3 | AA12: =ABS(Z12) -> 1278.3 | AB12: 0.09 | AC12: =MIN(AB12,30%) -> 0.09 | AD12: =IF(AC12>20%,1,0) -> 0 | AE12: 41 | AF12: =AA12*AE12*(1-AC12) -> 47693.373 | AG12: =Y12*AE12 -> 46966.73 | AH12: =ABS(AF12-AG12) -> 726.643 | AI12: =IF(AF12=0,0,AH12/AF12) -> 0.015235723 | AJ12: =AJ11+AF12 -> 850002.58 | AK12: =AJ12/SUM(AF:AF) -> 0.077655819 | AL12: =MIN(AC12,'What-If Analysis'!$B$2) -> 0.09 | AM12: =AE12*(1+'What-If Analysis'!$B$3) -> 53.3 | AN12: =Y12*(1+'What-If Analysis'!$B$4) -> 1260.083 | AO12: =AA12*AM12*(1-AL12) -> 62001.385
A13: ORD-2023-835010 | B13: 45008 | C13: =IF(D13<B13,D13,B13) -> 45008 | D13: 45031 | E13: =IF(D13<B13,B13,D13) -> 45031 | F13: =E13-C13 -> 23 | G13: =IF(Data!F27<=7,1,0) -> 0 | H13: =TEXT(C13,"MM-YYYY") -> 03-2023 | I13: ="Q"&ROUNDUP(MONTH(H13)/3,0)&"-"&YEAR(H13) -> Q1-2023 | J13: =_xlfn.MINIFS(C:C,M:M,M13) -> 44946 | K13: =TEXT(J13,"MM-YYYY") -> 01-2023 | L13: Africa | M13: Kenya | N13: Mombasa | O13: =IF(N13="",_xlfn.XLOOKUP(M13,M:M,N:N),N13) -> Mombasa | P13: Small Business | Q13: Retail | R13: =IF(Q13="",_xlfn.XLOOKUP(M13,M:M,Q:Q),Q13) -> Retail | S13: C. Otieno | T13: =IF(S13="",_xlfn.XLOOKUP(L13,L:L,S:S),S13) -> C. Otieno | U13: Accessories | V13: =IF(AA13<815.0987,"Low",IF(AA13<1640.058,"Medium","High")) -> Medium | W13: ACC-2988 | X13: =IF(AK13<=80%,"A",IF(AK13<=95%,"B","C")) -> A | Y13: 875.36 | Z13: 1178.62 | AA13: =ABS(Z13) -> 1178.62 | AB13: 0.151 | AC13: =MIN(AB13,30%) -> 0.151 | AD13: =IF(AC13>20%,1,0) -> 0 | AE13: 53 | AF13: =AA13*AE13*(1-AC13) -> 53034.364 | AG13: =Y13*AE13 -> 46394.08 | AH13: =ABS(AF13-AG13) -> 6640.2841 | AI13: =IF(AF13=0,0,AH13/AF13) -> 0.1252072 | AJ13: =AJ12+AF13 -> 903036.94 | AK13: =AJ13/SUM(AF:AF) -> 0.082501013 | AL13: =MIN(AC13,'What-If Analysis'!$B$2) -> 0.151 | AM13: =AE13*(1+'What-If Analysis'!$B$3) -> 68.9 | AN13: =Y13*(1+'What-If Analysis'!$B$4) -> 962.896 | AO13: =AA13*AM13*(1-AL13) -> 68944.673
A14: ORD-2024-964950 | B14: 45575 | C14: =IF(D14<B14,D14,B14) -> 45575 | D14: 45576 | E14: =IF(D14<B14,B14,D14) -> 45576 | F14: =E14-C14 -> 1 | G14: =IF(Data!F33<=7,1,0) -> 0 | H14: =TEXT(C14,"MM-YYYY") -> 10-2024 | I14: ="Q"&ROUNDUP(MONTH(H14)/3,0)&"-"&YEAR(H14) -> Q4-2024 | J14: =_xlfn.MINIFS(C:C,M:M,M14) -> 44945 | K14: =TEXT(J14,"MM-YYYY") -> 01-2023 | L14: Europe | M14: United Kingdom | N14: Manchester | O14: =IF(N14="",_xlfn.XLOOKUP(M14,M:M,N:N),N14) -> Manchester | P14: Non-Profit | Q14: Distributor | R14: =IF(Q14="",_xlfn.XLOOKUP(M14,M:M,Q:Q),Q14) -> Distributor | S14: L. Okafor | T14: =IF(S14="",_xlfn.XLOOKUP(L14,L:L,S:S),S14) -> L. Okafor | U14: Components | V14: =IF(AA14<815.0987,"Low",IF(AA14<1640.058,"Medium","High")) -> High | W14: CMP-8127 | X14: =IF(AK14<=80%,"A",IF(AK14<=95%,"B","C")) -> A | Y14: 1389.46 | Z14: 1784.7 | AA14: =ABS(Z14) -> 1784.7 | AB14: 0.146 | AC14: =MIN(AB14,30%) -> 0.146 | AD14: =IF(AC14>20%,1,0) -> 0 | AE14: 33 | AF14: =AA14*AE14*(1-AC14) -> 50296.415 | AG14: =Y14*AE14 -> 45852.18 | AH14: =ABS(AF14-AG14) -> 4444.2354 | AI14: =IF(AF14=0,0,AH14/AF14) -> 0.088360878 | AJ14: =AJ13+AF14 -> 953333.36 | AK14: =AJ14/SUM(AF:AF) -> 0.087096069 | AL14: =MIN(AC14,'What-If Analysis'!$B$2) -> 0.146 | AM14: =AE14*(1+'What-If Analysis'!$B$3) -> 42.9 | AN14: =Y14*(1+'What-If Analysis'!$B$4) -> 1528.406 | AO14: =AA14*AM14*(1-AL14) -> 65385.34
A15: ORD-2024-548345 | B15: 45426 | C15: =IF(D15<B15,D15,B15) -> 45426 | D15: 45440 | E15: =IF(D15<B15,B15,D15) -> 45440 | F15: =E15-C15 -> 14 | G15: =IF(Data!F3<=7,1,0) -> 0 | H15: =TEXT(C15,"MM-YYYY") -> 05-2024 | I15: ="Q"&ROUNDUP(MONTH(H15)/3,0)&"-"&YEAR(H15) -> Q2-2024 | J15: =_xlfn.MINIFS(C:C,M:M,M15) -> 44945 | K15: =TEXT(J15,"MM-YYYY") -> 01-2023 | L15: Europe | M15: United Kingdom | N15: Birmingham | O15: =IF(N15="",_xlfn.XLOOKUP(M15,M:M,N:N),N15) -> Birmingham | P15: Consumer | Q15: Retail | R15: =IF(Q15="",_xlfn.XLOOKUP(M15,M:M,Q:Q),Q15) -> Retail | S15: B. Chen | T15: =IF(S15="",_xlfn.XLOOKUP(L15,L:L,S:S),S15) -> B. Chen | U15: Networking | V15: =IF(AA15<815.0987,"Low",IF(AA15<1640.058,"Medium","High")) -> High | W15: NET-2365 | X15: =IF(AK15<=80%,"A",IF(AK15<=95%,"B","C")) -> A | Y15: 1421.14 | Z15: 3524 | AA15: =ABS(Z15) -> 3524 | AB15: 0 | AC15: =MIN(AB15,30%) -> 0 | AD15: =IF(AC15>20%,1,0) -> 0 | AE15: 31 | AF15: =AA15*AE15*(1-AC15) -> 109244 | AG15: =Y15*AE15 -> 44055.34 | AH15: =ABS(AF15-AG15) -> 65188.66 | AI15: =IF(AF15=0,0,AH15/AF15) -> 0.59672531 | AJ15: =AJ14+AF15 -> 1062577.4 | AK15: =AJ15/SUM(AF:AF) -> 0.097076547 | AL15: =MIN(AC15,'What-If Analysis'!$B$2) -> 0 | AM15: =AE15*(1+'What-If Analysis'!$B$3) -> 40.3 | AN15: =Y15*(1+'What-If Analysis'!$B$4) -> 1563.254 | AO15: =AA15*AM15*(1-AL15) -> 142017.2
A16: ORD-2024-901115 | B16: 45498 | C16: =IF(D16<B16,D16,B16) -> 45498 | D16: 45506 | E16: =IF(D16<B16,B16,D16) -> 45506 | F16: =E16-C16 -> 8 | G16: =IF(Data!F12<=7,1,0) -> 0 | H16: =TEXT(C16,"MM-YYYY") -> 07-2024 | I16: ="Q"&ROUNDUP(MONTH(H16)/3,0)&"-"&YEAR(H16) -> Q3-2024 | J16: =_xlfn.MINIFS(C:C,M:M,M16) -> 44928 | K16: =TEXT(J16,"MM-YYYY") -> 01-2023 | L16: Americas | M16: Canada | N16: Montreal | O16: =IF(N16="",_xlfn.XLOOKUP(M16,M:M,N:N),N16) -> Montreal | P16: Consumer | Q16: Direct | R16: =IF(Q16="",_xlfn.XLOOKUP(M16,M:M,Q:Q),Q16) -> Direct | S16: J. Njeri | T16: =IF(S16="",_xlfn.XLOOKUP(L16,L:L,S:S),S16) -> J. Njeri | U16: Accessories | V16: =IF(AA16<815.0987,"Low",IF(AA16<1640.058,"Medium","High")) -> High | W16: ACC-6626 | X16: =IF(AK16<=80%,"A",IF(AK16<=95%,"B","C")) -> A | Y16: 986.81 | Z16: 2050.31 | AA16: =ABS(Z16) -> 2050.31 | AB16: 0.103 | AC16: =MIN(AB16,30%) -> 0.103 | AD16: =IF(AC16>20%,1,0) -> 0 | AE16: 43 | AF16: =AA16*AE16*(1-AC16) -> 79082.507 | AG16: =Y16*AE16 -> 42432.83 | AH16: =ABS(AF16-AG16) -> 36649.677 | AI16: =IF(AF16=0,0,AH16/AF16) -> 0.46343595 | AJ16: =AJ15+AF16 -> 1141659.9 | AK16: =AJ16/SUM(AF:AF) -> 0.10430149 | AL16: =MIN(AC16,'What-If Analysis'!$B$2) -> 0.103 | AM16: =AE16*(1+'What-If Analysis'!$B$3) -> 55.9 | AN16: =Y16*(1+'What-If Analysis'!$B$4) -> 1085.491 | AO16: =AA16*AM16*(1-AL16) -> 102807.26
A17: ORD-2025-997421 | B17: 45798 | C17: =IF(D17<B17,D17,B17) -> 45798 | D17: 45817 | E17: =IF(D17<B17,B17,D17) -> 45817 | F17: =E17-C17 -> 19 | G17: =IF(Data!F20<=7,1,0) -> 1 | H17: =TEXT(C17,"MM-YYYY") -> 05-2025 | I17: ="Q"&ROUNDUP(MONTH(H17)/3,0)&"-"&YEAR(H17) -> Q2-2025 | J17: =_xlfn.MINIFS(C:C,M:M,M17) -> 44955 | K17: =TEXT(J17,"MM-YYYY") -> 01-2023 | L17: Americas | M17: Brazil | N17: São Paulo | O17: =IF(N17="",_xlfn.XLOOKUP(M17,M:M,N:N),N17) -> São Paulo | P17: Non-Profit | Q17: Online | R17: =IF(Q17="",_xlfn.XLOOKUP(M17,M:M,Q:Q),Q17) -> Online | S17: A. Patel | T17: =IF(S17="",_xlfn.XLOOKUP(L17,L:L,S:S),S17) -> A. Patel | U17: Components | V17: =IF(AA17<815.0987,"Low",IF(AA17<1640.058,"Medium","High")) -> High | W17: CMP-3731 | X17: =IF(AK17<=80%,"A",IF(AK17<=95%,"B","C")) -> A | Y17: 1331.38 | Z17: 2309.56 | AA17: =ABS(Z17) -> 2309.56 | AB17: 0.149 | AC17: =MIN(AB17,30%) -> 0.149 | AD17: =IF(AC17>20%,1,0) -> 0 | AE17: 31 | AF17: =AA17*AE17*(1-AC17) -> 60928.502 | AG17: =Y17*AE17 -> 41272.78 | AH17: =ABS(AF17-AG17) -> 19655.722 | AI17: =IF(AF17=0,0,AH17/AF17) -> 0.32260308 | AJ17: =AJ16+AF17 -> 1202588.4 | AK17: =AJ17/SUM(AF:AF) -> 0.10986788 | AL17: =MIN(AC17,'What-If Analysis'!$B$2) -> 0.149 | AM17: =AE17*(1+'What-If Analysis'!$B$3) -> 40.3 | AN17: =Y17*(1+'What-If Analysis'!$B$4) -> 1464.518 | AO17: =AA17*AM17*(1-AL17) -> 79207.053
A18: ORD-2024-584090 | B18: 45450 | C18: =IF(D18<B18,D18,B18) -> 45450 | D18: 45469 | E18: =IF(D18<B18,B18,D18) -> 45469 | F18: =E18-C18 -> 19 | G18: =IF(Data!F18<=7,1,0) -> 0 | H18: =TEXT(C18,"MM-YYYY") -> 06-2024 | I18: ="Q"&ROUNDUP(MONTH(H18)/3,0)&"-"&YEAR(H18) -> Q2-2024 | J18: =_xlfn.MINIFS(C:C,M:M,M18) -> 44947 | K18: =TEXT(J18,"MM-YYYY") -> 01-2023 | L18: Europe | M18: Germany | N18: Berlin | O18: =IF(N18="",_xlfn.XLOOKUP(M18,M:M,N:N),N18) -> Berlin | P18: Non-Profit | Q18: Marketplace | R18: =IF(Q18="",_xlfn.XLOOKUP(M18,M:M,Q:Q),Q18) -> Marketplace | S18: M. Rossi | T18: =IF(S18="",_xlfn.XLOOKUP(L18,L:L,S:S),S18) -> M. Rossi | U18: Components | V18: =IF(AA18<815.0987,"Low",IF(AA18<1640.058,"Medium","High")) -> High | W18: CMP-2040 | X18: =IF(AK18<=80%,"A",IF(AK18<=95%,"B","C")) -> A | Y18: 1064.32 | Z18: 1848.39 | AA18: =ABS(Z18) -> 1848.39 | AB18: 0.073 | AC18: =MIN(AB18,30%) -> 0.073 | AD18: =IF(AC18>20%,1,0) -> 0 | AE18: 38 | AF18: =AA18*AE18*(1-AC18) -> 65111.386 | AG18: =Y18*AE18 -> 40444.16 | AH18: =ABS(AF18-AG18) -> 24667.226 | AI18: =IF(AF18=0,0,AH18/AF18) -> 0.37884658 | AJ18: =AJ17+AF18 -> 1267699.8 | AK18: =AJ18/SUM(AF:AF) -> 0.11581643 | AL18: =MIN(AC18,'What-If Analysis'!$B$2) -> 0.073 | AM18: =AE18*(1+'What-If Analysis'!$B$3) -> 49.4 | AN18: =Y18*(1+'What-If Analysis'!$B$4) -> 1170.752 | AO18: =AA18*AM18*(1-AL18) -> 84644.802
A19: ORD-2023-368449 | B19: 45208 | C19: =IF(D19<B19,D19,B19) -> 45208 | D19: 45225 | E19: =IF(D19<B19,B19,D19) -> 45225 | F19: =E19-C19 -> 17 | G19: =IF(Data!F29<=7,1,0) -> 1 | H19: =TEXT(C19,"MM-YYYY") -> 10-2023 | I19: ="Q"&ROUNDUP(MONTH(H19)/3,0)&"-"&YEAR(H19) -> Q4-2023 | J19: =_xlfn.MINIFS(C:C,M:M,M19) -> 44938 | K19: =TEXT(J19,"MM-YYYY") -> 01-2023 | L19: Asia | M19: China | N19: Shanghai | O19: =IF(N19="",_xlfn.XLOOKUP(M19,M:M,N:N),N19) -> Shanghai | P19: Consumer | Q19: Marketplace | R19: =IF(Q19="",_xlfn.XLOOKUP(M19,M:M,Q:Q),Q19) -> Marketplace | S19: C. Otieno | T19: =IF(S19="",_xlfn.XLOOKUP(L19,L:L,S:S),S19) -> C. Otieno | U19: Components | V19: =IF(AA19<815.0987,"Low",IF(AA19<1640.058,"Medium","High")) -> High | W19: CMP-2096 | X19: =IF(AK19<=80%,"A",IF(AK19<=95%,"B","C")) -> A | Y19: 1132.03 | Z19: 2137.21 | AA19: =ABS(Z19) -> 2137.21 | AB19: 0.357 | AC19: =MIN(AB19,30%) -> 0.3 | AD19: =IF(AC19>20%,1,0) -> 1 | AE19: 35 | AF19: =AA19*AE19*(1-AC19) -> 52361.645 | AG19: =Y19*AE19 -> 39621.05 | AH19: =ABS(AF19-AG19) -> 12740.595 | AI19: =IF(AF19=0,0,AH19/AF19) -> 0.24331923 | AJ19: =AJ18+AF19 -> 1320061.4 | AK19: =AJ19/SUM(AF:AF) -> 0.12060016 | AL19: =MIN(AC19,'What-If Analysis'!$B$2) -> 0.2 | AM19: =AE19*(1+'What-If Analysis'!$B$3) -> 45.5 | AN19: =Y19*(1+'What-If Analysis'!$B$4) -> 1245.233 | AO19: =AA19*AM19*(1-AL19) -> 77794.444
A20: ORD-2023-159821 | B20: 45108 | C20: =IF(D20<B20,D20,B20) -> 45108 | D20: 45115 | E20: =IF(D20<B20,B20,D20) -> 45115 | F20: =E20-C20 -> 7 | G20: =IF(Data!F9<=7,1,0) -> 0 | H20: =TEXT(C20,"MM-YYYY") -> 07-2023 | I20: ="Q"&ROUNDUP(MONTH(H20)/3,0)&"-"&YEAR(H20) -> Q3-2023 | J20: =_xlfn.MINIFS(C:C,M:M,M20) -> 44939 | K20: =TEXT(J20,"MM-YYYY") -> 01-2023 | L20: Africa | M20: Nigeria | N20: Port Harcourt | O20: =IF(N20="",_xlfn.XLOOKUP(M20,M:M,N:N),N20) -> Port Harcourt | P20: Corporate | Q20: Retail | R20: =IF(Q20="",_xlfn.XLOOKUP(M20,M:M,Q:Q),Q20) -> Retail | S20: A. Patel | T20: =IF(S20="",_xlfn.XLOOKUP(L20,L:L,S:S),S20) -> A. Patel | U20: Laptops | V20: =IF(AA20<815.0987,"Low",IF(AA20<1640.058,"Medium","High")) -> High | W20: LAP-3904 | X20: =IF(AK20<=80%,"A",IF(AK20<=95%,"B","C")) -> A | Y20: 834.26 | Z20: 1780.56 | AA20: =ABS(Z20) -> 1780.56 | AB20: 0.014 | AC20: =MIN(AB20,30%) -> 0.014 | AD20: =IF(AC20>20%,1,0) -> 0 | AE20: 47 | AF20: =AA20*AE20*(1-AC20) -> 82514.712 | AG20: =Y20*AE20 -> 39210.22 | AH20: =ABS(AF20-AG20) -> 43304.492 | AI20: =IF(AF20=0,0,AH20/AF20) -> 0.52480934 | AJ20: =AJ19+AF20 -> 1402576.1 | AK20: =AJ20/SUM(AF:AF) -> 0.12813867 | AL20: =MIN(AC20,'What-If Analysis'!$B$2) -> 0.014 | AM20: =AE20*(1+'What-If Analysis'!$B$3) -> 61.1 | AN20: =Y20*(1+'What-If Analysis'!$B$4) -> 917.686 | AO20: =AA20*AM20*(1-AL20) -> 107269.12
A21: ORD-2023-159379 | B21: 44965 | C21: =IF(D21<B21,D21,B21) -> 44965 | D21: 44968 | E21: =IF(D21<B21,B21,D21) -> 44968 | F21: =E21-C21 -> 3 | G21: =IF(Data!F21<=7,1,0) -> 1 | H21: =TEXT(C21,"MM-YYYY") -> 02-2023 | I21: ="Q"&ROUNDUP(MONTH(H21)/3,0)&"-"&YEAR(H21) -> Q1-2023 | J21: =_xlfn.MINIFS(C:C,M:M,M21) -> 44933 | K21: =TEXT(J21,"MM-YYYY") -> 01-2023 | L21: Africa | M21: South Africa | N21: Cape Town | O21: =IF(N21="",_xlfn.XLOOKUP(M21,M:M,N:N),N21) -> Cape Town | P21: Corporate | Q21: Direct | R21: =IF(Q21="",_xlfn.XLOOKUP(M21,M:M,Q:Q),Q21) -> Direct | S21: M. Rossi | T21: =IF(S21="",_xlfn.XLOOKUP(L21,L:L,S:S),S21) -> M. Rossi | U21: Networking | V21: =IF(AA21<815.0987,"Low",IF(AA21<1640.058,"Medium","High")) -> High | W21: NET-5018 | X21: =IF(AK21<=80%,"A",IF(AK21<=95%,"B","C")) -> A | Y21: 1410.05 | Z21: 2763.95 | AA21: =ABS(Z21) -> 2763.95 | AB21: 0.161 | AC21: =MIN(AB21,30%) -> 0.161 | AD21: =IF(AC21>20%,1,0) -> 0 | AE21: 26 | AF21: =AA21*AE21*(1-AC21) -> 60292.805 | AG21: =Y21*AE21 -> 36661.3 | AH21: =ABS(AF21-AG21) -> 23631.505 | AI21: =IF(AF21=0,0,AH21/AF21) -> 0.39194569 | AJ21: =AJ20+AF21 -> 1462868.9 | AK21: =AJ21/SUM(AF:AF) -> 0.13364699 | AL21: =MIN(AC21,'What-If Analysis'!$B$2) -> 0.161 | AM21: =AE21*(1+'What-If Analysis'!$B$3) -> 33.8 | AN21: =Y21*(1+'What-If Analysis'!$B$4) -> 1551.055 | AO21: =AA21*AM21*(1-AL21) -> 78380.647
A22: ORD-2023-974506 | B22: 45288 | C22: =IF(D22<B22,D22,B22) -> 45288 | D22: 45292 | E22: =IF(D22<B22,B22,D22) -> 45292 | F22: =E22-C22 -> 4 | G22: =IF(Data!F16<=7,1,0) -> 0 | H22: =TEXT(C22,"MM-YYYY") -> 12-2023 | I22: ="Q"&ROUNDUP(MONTH(H22)/3,0)&"-"&YEAR(H22) -> Q4-2023 | J22: =_xlfn.MINIFS(C:C,M:M,M22) -> 44933 | K22: =TEXT(J22,"MM-YYYY") -> 01-2023 | L22: Africa | M22: South Africa | N22: Cape Town | O22: =IF(N22="",_xlfn.XLOOKUP(M22,M:M,N:N),N22) -> Cape Town | P22: Education | Q22: Distributor | R22: =IF(Q22="",_xlfn.XLOOKUP(M22,M:M,Q:Q),Q22) -> Distributor | S22: A. Patel | T22: =IF(S22="",_xlfn.XLOOKUP(L22,L:L,S:S),S22) -> A. Patel | U22: Printers | V22: =IF(AA22<815.0987,"Low",IF(AA22<1640.058,"Medium","High")) -> High | W22: PRN-1654 | X22: =IF(AK22<=80%,"A",IF(AK22<=95%,"B","C")) -> A | Y22: 1141.8 | Z22: 2318.74 | AA22: =ABS(Z22) -> 2318.74 | AB22: 0.107 | AC22: =MIN(AB22,30%) -> 0.107 | AD22: =IF(AC22>20%,1,0) -> 0 | AE22: 32 | AF22: =AA22*AE22*(1-AC22) -> 66260.314 | AG22: =Y22*AE22 -> 36537.6 | AH22: =ABS(AF22-AG22) -> 29722.714 | AI22: =IF(AF22=0,0,AH22/AF22) -> 0.44857491 | AJ22: =AJ21+AF22 -> 1529129.2 | AK22: =AJ22/SUM(AF:AF) -> 0.1397005 | AL22: =MIN(AC22,'What-If Analysis'!$B$2) -> 0.107 | AM22: =AE22*(1+'What-If Analysis'!$B$3) -> 41.6 | AN22: =Y22*(1+'What-If Analysis'!$B$4) -> 1255.98 | AO22: =AA22*AM22*(1-AL22) -> 86138.409
A23: ORD-2023-586275 | B23: 44946 | C23: =IF(D23<B23,D23,B23) -> 44946 | D23: 44960 | E23: =IF(D23<B23,B23,D23) -> 44960 | F23: =E23-C23 -> 14 | G23: =IF(Data!F36<=7,1,0) -> 0 | H23: =TEXT(C23,"MM-YYYY") -> 01-2023 | I23: ="Q"&ROUNDUP(MONTH(H23)/3,0)&"-"&YEAR(H23) -> Q1-2023 | J23: =_xlfn.MINIFS(C:C,M:M,M23) -> 44946 | K23: =TEXT(J23,"MM-YYYY") -> 01-2023 | L23: Africa | M23: Kenya | N23: Kisumu | O23: =IF(N23="",_xlfn.XLOOKUP(M23,M:M,N:N),N23) -> Kisumu | P23: Corporate | Q23: Retail | R23: =IF(Q23="",_xlfn.XLOOKUP(M23,M:M,Q:Q),Q23) -> Retail | S23: M. Rossi | T23: =IF(S23="",_xlfn.XLOOKUP(L23,L:L,S:S),S23) -> M. Rossi | U23: Networking | V23: =IF(AA23<815.0987,"Low",IF(AA23<1640.058,"Medium","High")) -> Medium | W23: NET-6036 | X23: =IF(AK23<=80%,"A",IF(AK23<=95%,"B","C")) -> A | Y23: 884.36 | Z23: 1545.34 | AA23: =ABS(Z23) -> 1545.34 | AB23: 0.243 | AC23: =MIN(AB23,30%) -> 0.243 | AD23: =IF(AC23>20%,1,0) -> 1 | AE23: 41 | AF23: =AA23*AE23*(1-AC23) -> 47962.718 | AG23: =Y23*AE23 -> 36258.76 | AH23: =ABS(AF23-AG23) -> 11703.958 | AI23: =IF(AF23=0,0,AH23/AF23) -> 0.24402199 | AJ23: =AJ22+AF23 -> 1577091.9 | AK23: =AJ23/SUM(AF:AF) -> 0.14408235 | AL23: =MIN(AC23,'What-If Analysis'!$B$2) -> 0.2 | AM23: =AE23*(1+'What-If Analysis'!$B$3) -> 53.3 | AN23: =Y23*(1+'What-If Analysis'!$B$4) -> 972.796 | AO23: =AA23*AM23*(1-AL23) -> 65893.298
A24: ORD-2023-676553 | B24: 45066 | C24: =IF(D24<B24,D24,B24) -> 45066 | D24: 45096 | E24: =IF(D24<B24,B24,D24) -> 45096 | F24: =E24-C24 -> 30 | G24: =IF(Data!F177<=7,1,0) -> 0 | H24: =TEXT(C24,"MM-YYYY") -> 05-2023 | I24: ="Q"&ROUNDUP(MONTH(H24)/3,0)&"-"&YEAR(H24) -> Q2-2023 | J24: =_xlfn.MINIFS(C:C,M:M,M24) -> 44955 | K24: =TEXT(J24,"MM-YYYY") -> 01-2023 | L24: Asia | M24: India | N24: Delhi | O24: =IF(N24="",_xlfn.XLOOKUP(M24,M:M,N:N),N24) -> Delhi | P24: Non-Profit | Q24: Marketplace | R24: =IF(Q24="",_xlfn.XLOOKUP(M24,M:M,Q:Q),Q24) -> Marketplace | S24: H. Kim | T24: =IF(S24="",_xlfn.XLOOKUP(L24,L:L,S:S),S24) -> H. Kim | U24: Laptops | V24: =IF(AA24<815.0987,"Low",IF(AA24<1640.058,"Medium","High")) -> Medium | W24: LAP-2806 | X24: =IF(AK24<=80%,"A",IF(AK24<=95%,"B","C")) -> A | Y24: 1161.2 | Z24: 878.73 | AA24: =ABS(Z24) -> 878.73 | AB24: 0.19 | AC24: =MIN(AB24,30%) -> 0.19 | AD24: =IF(AC24>20%,1,0) -> 0 | AE24: 31 | AF24: =AA24*AE24*(1-AC24) -> 22064.91 | AG24: =Y24*AE24 -> 35997.2 | AH24: =ABS(AF24-AG24) -> 13932.29 | AI24: =IF(AF24=0,0,AH24/AF24) -> 0.6314229 | AJ24: =AJ23+AF24 -> 1599156.9 | AK24: =AJ24/SUM(AF:AF) -> 0.14609819 | AL24: =MIN(AC24,'What-If Analysis'!$B$2) -> 0.19 | AM24: =AE24*(1+'What-If Analysis'!$B$3) -> 40.3 | AN24: =Y24*(1+'What-If Analysis'!$B$4) -> 1277.32 | AO24: =AA24*AM24*(1-AL24) -> 28684.383
A25: ORD-2025-831576 | B25: 45915 | C25: =IF(D25<B25,D25,B25) -> 45915 | D25: 45925 | E25: =IF(D25<B25,B25,D25) -> 45925 | F25: =E25-C25 -> 10 | G25: =IF(Data!F115<=7,1,0) -> 0 | H25: =TEXT(C25,"MM-YYYY") -> 09-2025 | I25: ="Q"&ROUNDUP(MONTH(H25)/3,0)&"-"&YEAR(H25) -> Q3-2025 | J25: =_xlfn.MINIFS(C:C,M:M,M25) -> 44955 | K25: =TEXT(J25,"MM-YYYY") -> 01-2023 | L25: Asia | M25: India | N25: Delhi | O25: =IF(N25="",_xlfn.XLOOKUP(M25,M:M,N:N),N25) -> Delhi | P25: Consumer | Q25: Retail | R25: =IF(Q25="",_xlfn.XLOOKUP(M25,M:M,Q:Q),Q25) -> Retail | S25: A. Patel | T25: =IF(S25="",_xlfn.XLOOKUP(L25,L:L,S:S),S25) -> A. Patel | U25: Phones | V25: =IF(AA25<815.0987,"Low",IF(AA25<1640.058,"Medium","High")) -> Medium | W25: PHN-2859 | X25: =IF(AK25<=80%,"A",IF(AK25<=95%,"B","C")) -> A | Y25: 1488.91 | Z25: 1483.74 | AA25: =ABS(Z25) -> 1483.74 | AB25: 0.168 | AC25: =MIN(AB25,30%) -> 0.168 | AD25: =IF(AC25>20%,1,0) -> 0 | AE25: 24 | AF25: =AA25*AE25*(1-AC25) -> 29627.32 | AG25: =Y25*AE25 -> 35733.84 | AH25: =ABS(AF25-AG25) -> 6106.5197 | AI25: =IF(AF25=0,0,AH25/AF25) -> 0.2061111 | AJ25: =AJ24+AF25 -> 1628784.2 | AK25: =AJ25/SUM(AF:AF) -> 0.14880493 | AL25: =MIN(AC25,'What-If Analysis'!$B$2) -> 0.168 | AM25: =AE25*(1+'What-If Analysis'!$B$3) -> 31.2 | AN25: =Y25*(1+'What-If Analysis'!$B$4) -> 1637.801 | AO25: =AA25*AM25*(1-AL25) -> 38515.516
A26: ORD-2024-468655 | B26: 45341 | C26: =IF(D26<B26,D26,B26) -> 45341 | D26: 45357 | E26: =IF(D26<B26,B26,D26) -> 45357 | F26: =E26-C26 -> 16 | G26: =IF(Data!F23<=7,1,0) -> 0 | H26: =TEXT(C26,"MM-YYYY") -> 02-2024 | I26: ="Q"&ROUNDUP(MONTH(H26)/3,0)&"-"&YEAR(H26) -> Q1-2024 | J26: =_xlfn.MINIFS(C:C,M:M,M26) -> 44938 | K26: =TEXT(J26,"MM-YYYY") -> 01-2023 | L26: Asia | M26: China | N26: Beijing | O26: =IF(N26="",_xlfn.XLOOKUP(M26,M:M,N:N),N26) -> Beijing | P26: Education | Q26: Marketplace | R26: =IF(Q26="",_xlfn.XLOOKUP(M26,M:M,Q:Q),Q26) -> Marketplace | S26: O. Wang | T26: =IF(S26="",_xlfn.XLOOKUP(L26,L:L,S:S),S26) -> O. Wang | U26: Printers | V26: =IF(AA26<815.0987,"Low",IF(AA26<1640.058,"Medium","High")) -> High | W26: PRN-6308 | X26: =IF(AK26<=80%,"A",IF(AK26<=95%,"B","C")) -> A | Y26: 1477.84 | Z26: 3197.47 | AA26: =ABS(Z26) -> 3197.47 | AB26: 0.243 | AC26: =MIN(AB26,30%) -> 0.243 | AD26: =IF(AC26>20%,1,0) -> 1 | AE26: 24 | AF26: =AA26*AE26*(1-AC26) -> 58091.635 | AG26: =Y26*AE26 -> 35468.16 | AH26: =ABS(AF26-AG26) -> 22623.475 | AI26: =IF(AF26=0,0,AH26/AF26) -> 0.38944462 | AJ26: =AJ25+AF26 -> 1686875.8 | AK26: =AJ26/SUM(AF:AF) -> 0.15411215 | AL26: =MIN(AC26,'What-If Analysis'!$B$2) -> 0.2 | AM26: =AE26*(1+'What-If Analysis'!$B$3) -> 31.2 | AN26: =Y26*(1+'What-If Analysis'!$B$4) -> 1625.624 | AO26: =AA26*AM26*(1-AL26) -> 79808.851
A27: ORD-2024-756884 | B27: 45578 | C27: =IF(D27<B27,D27,B27) -> 45578 | D27: 45589 | E27: =IF(D27<B27,B27,D27) -> 45589 | F27: =E27-C27 -> 11 | G27: =IF(Data!F48<=7,1,0) -> 0 | H27: =TEXT(C27,"MM-YYYY") -> 10-2024 | I27: ="Q"&ROUNDUP(MONTH(H27)/3,0)&"-"&YEAR(H27) -> Q4-2024 | J27: =_xlfn.MINIFS(C:C,M:M,M27) -> 44936 | K27: =TEXT(J27,"MM-YYYY") -> 01-2023 | L27: Europe | M27: France | N27: Paris | O27: =IF(N27="",_xlfn.XLOOKUP(M27,M:M,N:N),N27) -> Paris | P27: Education | Q27: Distributor | R27: =IF(Q27="",_xlfn.XLOOKUP(M27,M:M,Q:Q),Q27) -> Distributor | S27: F. Müller | T27: =IF(S27="",_xlfn.XLOOKUP(L27,L:L,S:S),S27) -> F. Müller | U27: Components | V27: =IF(AA27<815.0987,"Low",IF(AA27<1640.058,"Medium","High")) -> Medium | W27: CMP-5006 | X27: =IF(AK27<=80%,"A",IF(AK27<=95%,"B","C")) -> A | Y27: 816.7 | Z27: 1010.75 | AA27: =ABS(Z27) -> 1010.75 | AB27: 0.047 | AC27: =MIN(AB27,30%) -> 0.047 | AD27: =IF(AC27>20%,1,0) -> 0 | AE27: 43 | AF27: =AA27*AE27*(1-AC27) -> 41419.524 | AG27: =Y27*AE27 -> 35118.1 | AH27: =ABS(AF27-AG27) -> 6301.4242 | AI27: =IF(AF27=0,0,AH27/AF27) -> 0.15213657 | AJ27: =AJ26+AF27 -> 1728295.3 | AK27: =AJ27/SUM(AF:AF) -> 0.15789622 | AL27: =MIN(AC27,'What-If Analysis'!$B$2) -> 0.047 | AM27: =AE27*(1+'What-If Analysis'!$B$3) -> 55.9 | AN27: =Y27*(1+'What-If Analysis'!$B$4) -> 898.37 | AO27: =AA27*AM27*(1-AL27) -> 53845.382
A28: ORD-2025-944081 | B28: 45741 | C28: =IF(D28<B28,D28,B28) -> 45741 | D28: 45742 | E28: =IF(D28<B28,B28,D28) -> 45742 | F28: =E28-C28 -> 1 | G28: =IF(Data!F44<=7,1,0) -> 0 | H28: =TEXT(C28,"MM-YYYY") -> 03-2025 | I28: ="Q"&ROUNDUP(MONTH(H28)/3,0)&"-"&YEAR(H28) -> Q1-2025 | J28: =_xlfn.MINIFS(C:C,M:M,M28) -> 44939 | K28: =TEXT(J28,"MM-YYYY") -> 01-2023 | L28: Africa | M28: Nigeria | N28: Lagos | O28: =IF(N28="",_xlfn.XLOOKUP(M28,M:M,N:N),N28) -> Lagos | P28: Education | Q28: Distributor | R28: =IF(Q28="",_xlfn.XLOOKUP(M28,M:M,Q:Q),Q28) -> Distributor | S28: G. Dubois | T28: =IF(S28="",_xlfn.XLOOKUP(L28,L:L,S:S),S28) -> G. Dubois | U28: Accessories | V28: =IF(AA28<815.0987,"Low",IF(AA28<1640.058,"Medium","High")) -> High | W28: ACC-9533 | X28: =IF(AK28<=80%,"A",IF(AK28<=95%,"B","C")) -> A | Y28: 1450.43 | Z28: 1994.67 | AA28: =ABS(Z28) -> 1994.67 | AB28: 0.1 | AC28: =MIN(AB28,30%) -> 0.1 | AD28: =IF(AC28>20%,1,0) -> 0 | AE28: 24 | AF28: =AA28*AE28*(1-AC28) -> 43084.872 | AG28: =Y28*AE28 -> 34810.32 | AH28: =ABS(AF28-AG28) -> 8274.552 | AI28: =IF(AF28=0,0,AH28/AF28) -> 0.19205238 | AJ28: =AJ27+AF28 -> 1771380.2 | AK28: =AJ28/SUM(AF:AF) -> 0.16183243 | AL28: =MIN(AC28,'What-If Analysis'!$B$2) -> 0.1 | AM28: =AE28*(1+'What-If Analysis'!$B$3) -> 31.2 | AN28: =Y28*(1+'What-If Analysis'!$B$4) -> 1595.473 | AO28: =AA28*AM28*(1-AL28) -> 56010.334
A29: ORD-2024-341535 | B29: 45468 | C29: =IF(D29<B29,D29,B29) -> 45468 | D29: 45473 | E29: =IF(D29<B29,B29,D29) -> 45473 | F29: =E29-C29 -> 5 | G29: =IF(Data!F10<=7,1,0) -> 0 | H29: =TEXT(C29,"MM-YYYY") -> 06-2024 | I29: ="Q"&ROUNDUP(MONTH(H29)/3,0)&"-"&YEAR(H29) -> Q2-2024 | J29: =_xlfn.MINIFS(C:C,M:M,M29) -> 44946 | K29: =TEXT(J29,"MM-YYYY") -> 01-2023 | L29: Africa | M29: Kenya | N29: Kisumu | O29: =IF(N29="",_xlfn.XLOOKUP(M29,M:M,N:N),N29) -> Kisumu | P29: Education | Q29: Direct | R29: =IF(Q29="",_xlfn.XLOOKUP(M29,M:M,Q:Q),Q29) -> Direct | S29: M. Rossi | T29: =IF(S29="",_xlfn.XLOOKUP(L29,L:L,S:S),S29) -> M. Rossi | U29: Networking | V29: =IF(AA29<815.0987,"Low",IF(AA29<1640.058,"Medium","High")) -> High | W29: NET-5987 | X29: =IF(AK29<=80%,"A",IF(AK29<=95%,"B","C")) -> A | Y29: 1323.55 | Z29: 3230.35 | AA29: =ABS(Z29) -> 3230.35 | AB29: 0.022 | AC29: =MIN(AB29,30%) -> 0.022 | AD29: =IF(AC29>20%,1,0) -> 0 | AE29: 26 | AF29: =AA29*AE29*(1-AC29) -> 82141.34 | AG29: =Y29*AE29 -> 34412.3 | AH29: =ABS(AF29-AG29) -> 47729.04 | AI29: =IF(AF29=0,0,AH29/AF29) -> 0.58105991 | AJ29: =AJ28+AF29 -> 1853521.5 | AK29: =AJ29/SUM(AF:AF) -> 0.16933682 | AL29: =MIN(AC29,'What-If Analysis'!$B$2) -> 0.022 | AM29: =AE29*(1+'What-If Analysis'!$B$3) -> 33.8 | AN29: =Y29*(1+'What-If Analysis'!$B$4) -> 1455.905 | AO29: =AA29*AM29*(1-AL29) -> 106783.74
A30: ORD-2024-572312 | B30: 45459 | C30: =IF(D30<B30,D30,B30) -> 45459 | D30: 45464 | E30: =IF(D30<B30,B30,D30) -> 45464 | F30: =E30-C30 -> 5 | G30: =IF(Data!F14<=7,1,0) -> 1 | H30: =TEXT(C30,"MM-YYYY") -> 06-2024 | I30: ="Q"&ROUNDUP(MONTH(H30)/3,0)&"-"&YEAR(H30) -> Q2-2024 | J30: =_xlfn.MINIFS(C:C,M:M,M30) -> 44988 | K30: =TEXT(J30,"MM-YYYY") -> 03-2023 | L30: Asia | M30: Japan | N30: Tokyo | O30: =IF(N30="",_xlfn.XLOOKUP(M30,M:M,N:N),N30) -> Tokyo | P30: Small Business | Q30: Distributor | R30: =IF(Q30="",_xlfn.XLOOKUP(M30,M:M,Q:Q),Q30) -> Distributor | S30: F. Müller | T30: =IF(S30="",_xlfn.XLOOKUP(L30,L:L,S:S),S30) -> F. Müller | U30: Phones | V30: =IF(AA30<815.0987,"Low",IF(AA30<1640.058,"Medium","High")) -> High | W30: PHN-9677 | X30: =IF(AK30<=80%,"A",IF(AK30<=95%,"B","C")) -> A | Y30: 1367.13 | Z30: 3062.01 | AA30: =ABS(Z30) -> 3062.01 | AB30: 0.103 | AC30: =MIN(AB30,30%) -> 0.103 | AD30: =IF(AC30>20%,1,0) -> 0 | AE30: 25 | AF30: =AA30*AE30*(1-AC30) -> 68665.574 | AG30: =Y30*AE30 -> 34178.25 | AH30: =ABS(AF30-AG30) -> 34487.324 | AI30: =IF(AF30=0,0,AH30/AF30) -> 0.50225058 | AJ30: =AJ29+AF30 -> 1922187.1 | AK30: =AJ30/SUM(AF:AF) -> 0.17561007 | AL30: =MIN(AC30,'What-If Analysis'!$B$2) -> 0.103 | AM30: =AE30*(1+'What-If Analysis'!$B$3) -> 32.5 | AN30: =Y30*(1+'What-If Analysis'!$B$4) -> 1503.843 | AO30: =AA30*AM30*(1-AL30) -> 89265.247
A31: ORD-2024-868223 | B31: 45354 | C31: =IF(D31<B31,D31,B31) -> 45354 | D31: 45370 | E31: =IF(D31<B31,B31,D31) -> 45370 | F31: =E31-C31 -> 16 | G31: =IF(Data!F64<=7,1,0) -> 0 | H31: =TEXT(C31,"MM-YYYY") -> 03-2024 | I31: ="Q"&ROUNDUP(MONTH(H31)/3,0)&"-"&YEAR(H31) -> Q1-2024 | J31: =_xlfn.MINIFS(C:C,M:M,M31) -> 44938 | K31: =TEXT(J31,"MM-YYYY") -> 01-2023 | L31: Asia | M31: China | N31: Beijing | O31: =IF(N31="",_xlfn.XLOOKUP(M31,M:M,N:N),N31) -> Beijing | P31: Consumer | Q31: Distributor | R31: =IF(Q31="",_xlfn.XLOOKUP(M31,M:M,Q:Q),Q31) -> Distributor | S31: G. Dubois | T31: =IF(S31="",_xlfn.XLOOKUP(L31,L:L,S:S),S31) -> G. Dubois | U31: Phones | V31: =IF(AA31<815.0987,"Low",IF(AA31<1640.058,"Medium","High")) -> Medium | W31: PHN-4915 | X31: =IF(AK31<=80%,"A",IF(AK31<=95%,"B","C")) -> A | Y31: 988.83 | Z31: 1206.04 | AA31: =ABS(Z31) -> 1206.04 | AB31: 0.063 | AC31: =MIN(AB31,30%) -> 0.063 | AD31: =IF(AC31>20%,1,0) -> 0 | AE31: 34 | AF31: =AA31*AE31*(1-AC31) -> 38422.022 | AG31: =Y31*AE31 -> 33620.22 | AH31: =ABS(AF31-AG31) -> 4801.8023 | AI31: =IF(AF31=0,0,AH31/AF31) -> 0.12497526 | AJ31: =AJ30+AF31 -> 1960609.1 | AK31: =AJ31/SUM(AF:AF) -> 0.17912029 | AL31: =MIN(AC31,'What-If Analysis'!$B$2) -> 0.063 | AM31: =AE31*(1+'What-If Analysis'!$B$3) -> 44.2 | AN31: =Y31*(1+'What-If Analysis'!$B$4) -> 1087.713 | AO31: =AA31*AM31*(1-AL31) -> 49948.629
A32: ORD-2024-358795 | B32: 45588 | C32: =IF(D32<B32,D32,B32) -> 45587 | D32: 45587 | E32: =IF(D32<B32,B32,D32) -> 45588 | F32: =E32-C32 -> 1 | G32: =IF(Data!F223<=7,1,0) -> 0 | H32: =TEXT(C32,"MM-YYYY") -> 10-2024 | I32: ="Q"&ROUNDUP(MONTH(H32)/3,0)&"-"&YEAR(H32) -> Q4-2024 | J32: =_xlfn.MINIFS(C:C,M:M,M32) -> 44939 | K32: =TEXT(J32,"MM-YYYY") -> 01-2023 | L32: Africa | M32: Nigeria | N32: Port Harcourt | O32: =IF(N32="",_xlfn.XLOOKUP(M32,M:M,N:N),N32) -> Port Harcourt | P32: Education | Q32: Online | R32: =IF(Q32="",_xlfn.XLOOKUP(M32,M:M,Q:Q),Q32) -> Online | S32: J. Njeri | T32: =IF(S32="",_xlfn.XLOOKUP(L32,L:L,S:S),S32) -> J. Njeri | U32: Printers | V32: =IF(AA32<815.0987,"Low",IF(AA32<1640.058,"Medium","High")) -> Low | W32: PRN-9322 | X32: =IF(AK32<=80%,"A",IF(AK32<=95%,"B","C")) -> A | Y32: 1084.39 | Z32: 759.33 | AA32: =ABS(Z32) -> 759.33 | AB32: 0.237 | AC32: =MIN(AB32,30%) -> 0.237 | AD32: =IF(AC32>20%,1,0) -> 1 | AE32: 31 | AF32: =AA32*AE32*(1-AC32) -> 17960.432 | AG32: =Y32*AE32 -> 33616.09 | AH32: =ABS(AF32-AG32) -> 15655.658 | AI32: =IF(AF32=0,0,AH32/AF32) -> 0.87167486 | AJ32: =AJ31+AF32 -> 1978569.6 | AK32: =AJ32/SUM(AF:AF) -> 0.18076115 | AL32: =MIN(AC32,'What-If Analysis'!$B$2) -> 0.2 | AM32: =AE32*(1+'What-If Analysis'!$B$3) -> 40.3 | AN32: =Y32*(1+'What-If Analysis'!$B$4) -> 1192.829 | AO32: =AA32*AM32*(1-AL32) -> 24480.799
A33: ORD-2025-440093 | B33: 45763 | C33: =IF(D33<B33,D33,B33) -> 45763 | D33: 45773 | E33: =IF(D33<B33,B33,D33) -> 45773 | F33: =E33-C33 -> 10 | G33: =IF(Data!F56<=7,1,0) -> 1 | H33: =TEXT(C33,"MM-YYYY") -> 04-2025 | I33: ="Q"&ROUNDUP(MONTH(H33)/3,0)&"-"&YEAR(H33) -> Q2-2025 | J33: =_xlfn.MINIFS(C:C,M:M,M33) -> 44939 | K33: =TEXT(J33,"MM-YYYY") -> 01-2023 | L33: Africa | M33: Nigeria | N33: Port Harcourt | O33: =IF(N33="",_xlfn.XLOOKUP(M33,M:M,N:N),N33) -> Port Harcourt | P33: Enterprise | Q33: Marketplace | R33: =IF(Q33="",_xlfn.XLOOKUP(M33,M:M,Q:Q),Q33) -> Marketplace | S33: F. Müller | T33: =IF(S33="",_xlfn.XLOOKUP(L33,L:L,S:S),S33) -> F. Müller | U33: Laptops | V33: =IF(AA33<815.0987,"Low",IF(AA33<1640.058,"Medium","High")) -> High | W33: LAP-3490 | X33: =IF(AK33<=80%,"A",IF(AK33<=95%,"B","C")) -> A | Y33: 1457.44 | Z33: 1996.81 | AA33: =ABS(Z33) -> 1996.81 | AB33: 0.126 | AC33: =MIN(AB33,30%) -> 0.126 | AD33: =IF(AC33>20%,1,0) -> 0 | AE33: 23 | AF33: =AA33*AE33*(1-AC33) -> 40139.875 | AG33: =Y33*AE33 -> 33521.12 | AH33: =ABS(AF33-AG33) -> 6618.7546 | AI33: =IF(AF33=0,0,AH33/AF33) -> 0.16489226 | AJ33: =AJ32+AF33 -> 2018709.4 | AK33: =AJ33/SUM(AF:AF) -> 0.18442831 | AL33: =MIN(AC33,'What-If Analysis'!$B$2) -> 0.126 | AM33: =AE33*(1+'What-If Analysis'!$B$3) -> 29.9 | AN33: =Y33*(1+'What-If Analysis'!$B$4) -> 1603.184 | AO33: =AA33*AM33*(1-AL33) -> 52181.837
A34: ORD-2023-701153 | B34: 45030 | C34: =IF(D34<B34,D34,B34) -> 45030 | D34: 45059 | E34: =IF(D34<B34,B34,D34) -> 45059 | F34: =E34-C34 -> 29 | G34: =IF(Data!F26<=7,1,0) -> 0 | H34: =TEXT(C34,"MM-YYYY") -> 04-2023 | I34: ="Q"&ROUNDUP(MONTH(H34)/3,0)&"-"&YEAR(H34) -> Q2-2023 | J34: =_xlfn.MINIFS(C:C,M:M,M34) -> 44947 | K34: =TEXT(J34,"MM-YYYY") -> 01-2023 | L34: Europe | M34: Germany | N34: Frankfurt | O34: =IF(N34="",_xlfn.XLOOKUP(M34,M:M,N:N),N34) -> Frankfurt | P34: Consumer | Q34: Direct | R34: =IF(Q34="",_xlfn.XLOOKUP(M34,M:M,Q:Q),Q34) -> Direct | S34: J. Njeri | T34: =IF(S34="",_xlfn.XLOOKUP(L34,L:L,S:S),S34) -> J. Njeri | U34: Printers | V34: =IF(AA34<815.0987,"Low",IF(AA34<1640.058,"Medium","High")) -> High | W34: PRN-7019 | X34: =IF(AK34<=80%,"A",IF(AK34<=95%,"B","C")) -> A | Y34: 1320.33 | Z34: 2645.23 | AA34: =ABS(Z34) -> 2645.23 | AB34: 0.155 | AC34: =MIN(AB34,30%) -> 0.155 | AD34: =IF(AC34>20%,1,0) -> 0 | AE34: 25 | AF34: =AA34*AE34*(1-AC34) -> 55880.484 | AG34: =Y34*AE34 -> 33008.25 | AH34: =ABS(AF34-AG34) -> 22872.234 | AI34: =IF(AF34=0,0,AH34/AF34) -> 0.40930629 | AJ34: =AJ33+AF34 -> 2074589.9 | AK34: =AJ34/SUM(AF:AF) -> 0.18953352 | AL34: =MIN(AC34,'What-If Analysis'!$B$2) -> 0.155 | AM34: =AE34*(1+'What-If Analysis'!$B$3) -> 32.5 | AN34: =Y34*(1+'What-If Analysis'!$B$4) -> 1452.363 | AO34: =AA34*AM34*(1-AL34) -> 72644.629
A35: ORD-2025-765220 | B35: 45753 | C35: =IF(D35<B35,D35,B35) -> 45753 | D35: 45777 | E35: =IF(D35<B35,B35,D35) -> 45777 | F35: =E35-C35 -> 24 | G35: =IF(Data!F98<=7,1,0) -> 0 | H35: =TEXT(C35,"MM-YYYY") -> 04-2025 | I35: ="Q"&ROUNDUP(MONTH(H35)/3,0)&"-"&YEAR(H35) -> Q2-2025 | J35: =_xlfn.MINIFS(C:C,M:M,M35) -> 44955 | K35: =TEXT(J35,"MM-YYYY") -> 01-2023 | L35: Americas | M35: Brazil | N35: Brasília | O35: =IF(N35="",_xlfn.XLOOKUP(M35,M:M,N:N),N35) -> Brasília | P35: Education | Q35: Online | R35: =IF(Q35="",_xlfn.XLOOKUP(M35,M:M,Q:Q),Q35) -> Online | S35: K. Singh | T35: =IF(S35="",_xlfn.XLOOKUP(L35,L:L,S:S),S35) -> K. Singh | U35: Monitors | V35: =IF(AA35<815.0987,"Low",IF(AA35<1640.058,"Medium","High")) -> Medium | W35: MON-4925 | X35: =IF(AK35<=80%,"A",IF(AK35<=95%,"B","C")) -> A | Y35: 855.78 | Z35: 977.38 | AA35: =ABS(Z35) -> 977.38 | AB35: 0.147 | AC35: =MIN(AB35,30%) -> 0.147 | AD35: =IF(AC35>20%,1,0) -> 0 | AE35: 38 | AF35: =AA35*AE35*(1-AC35) -> 31680.795 | AG35: =Y35*AE35 -> 32519.64 | AH35: =ABS(AF35-AG35) -> 838.84468 | AI35: =IF(AF35=0,0,AH35/AF35) -> 0.026478018 | AJ35: =AJ34+AF35 -> 2106270.7 | AK35: =AJ35/SUM(AF:AF) -> 0.19242786 | AL35: =MIN(AC35,'What-If Analysis'!$B$2) -> 0.147 | AM35: =AE35*(1+'What-If Analysis'!$B$3) -> 49.4 | AN35: =Y35*(1+'What-If Analysis'!$B$4) -> 941.358 | AO35: =AA35*AM35*(1-AL35) -> 41185.034
A36: ORD-2024-817997 | B36: 45501 | C36: =IF(D36<B36,D36,B36) -> 45501 | D36: 45527 | E36: =IF(D36<B36,B36,D36) -> 45527 | F36: =E36-C36 -> 26 | G36: =IF(Data!F110<=7,1,0) -> 0 | H36: =TEXT(C36,"MM-YYYY") -> 07-2024 | I36: ="Q"&ROUNDUP(MONTH(H36)/3,0)&"-"&YEAR(H36) -> Q3-2024 | J36: =_xlfn.MINIFS(C:C,M:M,M36) -> 44955 | K36: =TEXT(J36,"MM-YYYY") -> 01-2023 | L36: Asia | M36: India | N36: Hyderabad | O36: =IF(N36="",_xlfn.XLOOKUP(M36,M:M,N:N),N36) -> Hyderabad | P36: Corporate | Q36: Retail | R36: =IF(Q36="",_xlfn.XLOOKUP(M36,M:M,Q:Q),Q36) -> Retail | S36: J. Njeri | T36: =IF(S36="",_xlfn.XLOOKUP(L36,L:L,S:S),S36) -> J. Njeri | U36: Networking | V36: =IF(AA36<815.0987,"Low",IF(AA36<1640.058,"Medium","High")) -> Medium | W36: NET-4675 | X36: =IF(AK36<=80%,"A",IF(AK36<=95%,"B","C")) -> A | Y36: 1339.24 | Z36: 1558.89 | AA36: =ABS(Z36) -> 1558.89 | AB36: 0.192 | AC36: =MIN(AB36,30%) -> 0.192 | AD36: =IF(AC36>20%,1,0) -> 0 | AE36: 24 | AF36: =AA36*AE36*(1-AC36) -> 30229.995 | AG36: =Y36*AE36 -> 32141.76 | AH36: =ABS(AF36-AG36) -> 1911.7651 | AI36: =IF(AF36=0,0,AH36/AF36) -> 0.06324067 | AJ36: =AJ35+AF36 -> 2136500.7 | AK36: =AJ36/SUM(AF:AF) -> 0.19518966 | AL36: =MIN(AC36,'What-If Analysis'!$B$2) -> 0.192 | AM36: =AE36*(1+'What-If Analysis'!$B$3) -> 31.2 | AN36: =Y36*(1+'What-If Analysis'!$B$4) -> 1473.164 | AO36: =AA36*AM36*(1-AL36) -> 39298.993
A37: ORD-2024-805860 | B37: 45548 | C37: =IF(D37<B37,D37,B37) -> 45548 | D37: 45567 | E37: =IF(D37<B37,B37,D37) -> 45567 | F37: =E37-C37 -> 19 | G37: =IF(Data!F67<=7,1,0) -> 0 | H37: =TEXT(C37,"MM-YYYY") -> 09-2024 | I37: ="Q"&ROUNDUP(MONTH(H37)/3,0)&"-"&YEAR(H37) -> Q3-2024 | J37: =_xlfn.MINIFS(C:C,M:M,M37) -> 44946 | K37: =TEXT(J37,"MM-YYYY") -> 01-2023 | L37: Africa | M37: Kenya | N37: Mombasa | O37: =IF(N37="",_xlfn.XLOOKUP(M37,M:M,N:N),N37) -> Mombasa | P37: Small Business | Q37: Retail | R37: =IF(Q37="",_xlfn.XLOOKUP(M37,M:M,Q:Q),Q37) -> Retail | S37: M. Rossi | T37: =IF(S37="",_xlfn.XLOOKUP(L37,L:L,S:S),S37) -> M. Rossi | U37: Phones | V37: =IF(AA37<815.0987,"Low",IF(AA37<1640.058,"Medium","High")) -> High | W37: PHN-8804 | X37: =IF(AK37<=80%,"A",IF(AK37<=95%,"B","C")) -> A | Y37: 1338.99 | Z37: 1765.76 | AA37: =ABS(Z37) -> 1765.76 | AB37: 0.126 | AC37: =MIN(AB37,30%) -> 0.126 | AD37: =IF(AC37>20%,1,0) -> 0 | AE37: 24 | AF37: =AA37*AE37*(1-AC37) -> 37038.582 | AG37: =Y37*AE37 -> 32135.76 | AH37: =ABS(AF37-AG37) -> 4902.8218 | AI37: =IF(AF37=0,0,AH37/AF37) -> 0.13237067 | AJ37: =AJ36+AF37 -> 2173539.3 | AK37: =AJ37/SUM(AF:AF) -> 0.19857349 | AL37: =MIN(AC37,'What-If Analysis'!$B$2) -> 0.126 | AM37: =AE37*(1+'What-If Analysis'!$B$3) -> 31.2 | AN37: =Y37*(1+'What-If Analysis'!$B$4) -> 1472.889 | AO37: =AA37*AM37*(1-AL37) -> 48150.156
A38: ORD-2024-474999 | B38: 45653 | C38: =IF(D38<B38,D38,B38) -> 45653 | D38: 45659 | E38: =IF(D38<B38,B38,D38) -> 45659 | F38: =E38-C38 -> 6 | G38: =IF(Data!F17<=7,1,0) -> 0 | H38: =TEXT(C38,"MM-YYYY") -> 12-2024 | I38: ="Q"&ROUNDUP(MONTH(H38)/3,0)&"-"&YEAR(H38) -> Q4-2024 | J38: =_xlfn.MINIFS(C:C,M:M,M38) -> 44947 | K38: =TEXT(J38,"MM-YYYY") -> 01-2023 | L38: Europe | M38: Germany | N38: Frankfurt | O38: =IF(N38="",_xlfn.XLOOKUP(M38,M:M,N:N),N38) -> Frankfurt | P38: Education | Q38: Direct | R38: =IF(Q38="",_xlfn.XLOOKUP(M38,M:M,Q:Q),Q38) -> Direct | S38: F. Müller | T38: =IF(S38="",_xlfn.XLOOKUP(L38,L:L,S:S),S38) -> F. Müller | U38: Laptops | V38: =IF(AA38<815.0987,"Low",IF(AA38<1640.058,"Medium","High")) -> High | W38: LAP-8214 | X38: =IF(AK38<=80%,"A",IF(AK38<=95%,"B","C")) -> A | Y38: 1391.99 | Z38: 3469.7 | AA38: =ABS(Z38) -> 3469.7 | AB38: 0.184 | AC38: =MIN(AB38,30%) -> 0.184 | AD38: =IF(AC38>20%,1,0) -> 0 | AE38: 23 | AF38: =AA38*AE38*(1-AC38) -> 65119.33 | AG38: =Y38*AE38 -> 32015.77 | AH38: =ABS(AF38-AG38) -> 33103.56 | AI38: =IF(AF38=0,0,AH38/AF38) -> 0.50835228 | AJ38: =AJ37+AF38 -> 2238658.6 | AK38: =AJ38/SUM(AF:AF) -> 0.20452276 | AL38: =MIN(AC38,'What-If Analysis'!$B$2) -> 0.184 | AM38: =AE38*(1+'What-If Analysis'!$B$3) -> 29.9 | AN38: =Y38*(1+'What-If Analysis'!$B$4) -> 1531.189 | AO38: =AA38*AM38*(1-AL38) -> 84655.128
A39: ORD-2025-789245 | B39: 45861 | C39: =IF(D39<B39,D39,B39) -> 45861 | D39: 45886 | E39: =IF(D39<B39,B39,D39) -> 45886 | F39: =E39-C39 -> 25 | G39: =IF(Data!F66<=7,1,0) -> 1 | H39: =TEXT(C39,"MM-YYYY") -> 07-2025 | I39: ="Q"&ROUNDUP(MONTH(H39)/3,0)&"-"&YEAR(H39) -> Q3-2025 | J39: =_xlfn.MINIFS(C:C,M:M,M39) -> 44945 | K39: =TEXT(J39,"MM-YYYY") -> 01-2023 | L39: Europe | M39: United Kingdom | N39: Birmingham | O39: =IF(N39="",_xlfn.XLOOKUP(M39,M:M,N:N),N39) -> Birmingham | P39: Education | Q39: Online | R39: =IF(Q39="",_xlfn.XLOOKUP(M39,M:M,Q:Q),Q39) -> Online | S39: I. Johnson | T39: =IF(S39="",_xlfn.XLOOKUP(L39,L:L,S:S),S39) -> I. Johnson | U39: Printers | V39: =IF(AA39<815.0987,"Low",IF(AA39<1640.058,"Medium","High")) -> Medium | W39: PRN-5876 | X39: =IF(AK39<=80%,"A",IF(AK39<=95%,"B","C")) -> A | Y39: 1142.06 | Z39: 1455 | AA39: =ABS(Z39) -> 1455 | AB39: 0.078 | AC39: =MIN(AB39,30%) -> 0.078 | AD39: =IF(AC39>20%,1,0) -> 0 | AE39: 28 | AF39: =AA39*AE39*(1-AC39) -> 37562.28 | AG39: =Y39*AE39 -> 31977.68 | AH39: =ABS(AF39-AG39) -> 5584.6 | AI39: =IF(AF39=0,0,AH39/AF39) -> 0.14867575 | AJ39: =AJ38+AF39 -> 2276220.9 | AK39: =AJ39/SUM(AF:AF) -> 0.20795443 | AL39: =MIN(AC39,'What-If Analysis'!$B$2) -> 0.078 | AM39: =AE39*(1+'What-If Analysis'!$B$3) -> 36.4 | AN39: =Y39*(1+'What-If Analysis'!$B$4) -> 1256.266 | AO39: =AA39*AM39*(1-AL39) -> 48830.964
A40: ORD-2024-510591 | B40: 45385 | C40: =IF(D40<B40,D40,B40) -> 45385 | D40: 45403 | E40: =IF(D40<B40,B40,D40) -> 45403 | F40: =E40-C40 -> 18 | G40: =IF(Data!F35<=7,1,0) -> 0 | H40: =TEXT(C40,"MM-YYYY") -> 04-2024 | I40: ="Q"&ROUNDUP(MONTH(H40)/3,0)&"-"&YEAR(H40) -> Q2-2024 | J40: =_xlfn.MINIFS(C:C,M:M,M40) -> 44955 | K40: =TEXT(J40,"MM-YYYY") -> 01-2023 | L40: Americas | M40: Brazil | N40: Brasília | O40: =IF(N40="",_xlfn.XLOOKUP(M40,M:M,N:N),N40) -> Brasília | P40: Small Business | Q40: Distributor | R40: =IF(Q40="",_xlfn.XLOOKUP(M40,M:M,Q:Q),Q40) -> Distributor | S40: B. Chen | T40: =IF(S40="",_xlfn.XLOOKUP(L40,L:L,S:S),S40) -> B. Chen | U40: Networking | V40: =IF(AA40<815.0987,"Low",IF(AA40<1640.058,"Medium","High")) -> High | W40: NET-3850 | X40: =IF(AK40<=80%,"A",IF(AK40<=95%,"B","C")) -> A | Y40: 1176.69 | Z40: 2201.54 | AA40: =ABS(Z40) -> 2201.54 | AB40: 0.17 | AC40: =MIN(AB40,30%) -> 0.17 | AD40: =IF(AC40>20%,1,0) -> 0 | AE40: 27 | AF40: =AA40*AE40*(1-AC40) -> 49336.511 | AG40: =Y40*AE40 -> 31770.63 | AH40: =ABS(AF40-AG40) -> 17565.881 | AI40: =IF(AF40=0,0,AH40/AF40) -> 0.35604223 | AJ40: =AJ39+AF40 -> 2325557.4 | AK40: =AJ40/SUM(AF:AF) -> 0.21246179 | AL40: =MIN(AC40,'What-If Analysis'!$B$2) -> 0.17 | AM40: =AE40*(1+'What-If Analysis'!$B$3) -> 35.1 | AN40: =Y40*(1+'What-If Analysis'!$B$4) -> 1294.359 | AO40: =AA40*AM40*(1-AL40) -> 64137.465
A41: ORD-2023-521818 | B41: 44955 | C41: =IF(D41<B41,D41,B41) -> 44955 | D41: 44985 | E41: =IF(D41<B41,B41,D41) -> 44985 | F41: =E41-C41 -> 30 | G41: =IF(Data!F134<=7,1,0) -> 0 | H41: =TEXT(C41,"MM-YYYY") -> 01-2023 | I41: ="Q"&ROUNDUP(MONTH(H41)/3,0)&"-"&YEAR(H41) -> Q1-2023 | J41: =_xlfn.MINIFS(C:C,M:M,M41) -> 44955 | K41: =TEXT(J41,"MM-YYYY") -> 01-2023 | L41: Asia | M41: India | N41: Bengaluru | O41: =IF(N41="",_xlfn.XLOOKUP(M41,M:M,N:N),N41) -> Bengaluru | P41: Non-Profit | Q41: Retail | R41: =IF(Q41="",_xlfn.XLOOKUP(M41,M:M,Q:Q),Q41) -> Retail | S41: B. Chen | T41: =IF(S41="",_xlfn.XLOOKUP(L41,L:L,S:S),S41) -> B. Chen | U41: Accessories | V41: =IF(AA41<815.0987,"Low",IF(AA41<1640.058,"Medium","High")) -> Medium | W41: ACC-4631 | X41: =IF(AK41<=80%,"A",IF(AK41<=95%,"B","C")) -> A | Y41: 1262.1 | Z41: 1395.53 | AA41: =ABS(Z41) -> 1395.53 | AB41: 0.233 | AC41: =MIN(AB41,30%) -> 0.233 | AD41: =IF(AC41>20%,1,0) -> 1 | AE41: 25 | AF41: =AA41*AE41*(1-AC41) -> 26759.288 | AG41: =Y41*AE41 -> 31552.5 | AH41: =ABS(AF41-AG41) -> 4793.2122 | AI41: =IF(AF41=0,0,AH41/AF41) -> 0.17912331 | AJ41: =AJ40+AF41 -> 2352316.7 | AK41: =AJ41/SUM(AF:AF) -> 0.2149065 | AL41: =MIN(AC41,'What-If Analysis'!$B$2) -> 0.2 | AM41: =AE41*(1+'What-If Analysis'!$B$3) -> 32.5 | AN41: =Y41*(1+'What-If Analysis'!$B$4) -> 1388.31 | AO41: =AA41*AM41*(1-AL41) -> 36283.78
A42: ORD-2024-728474 | B42: 45544 | C42: =IF(D42<B42,D42,B42) -> 45544 | D42: 45548 | E42: =IF(D42<B42,B42,D42) -> 45548 | F42: =E42-C42 -> 4 | G42: =IF(Data!F150<=7,1,0) -> 1 | H42: =TEXT(C42,"MM-YYYY") -> 09-2024 | I42: ="Q"&ROUNDUP(MONTH(H42)/3,0)&"-"&YEAR(H42) -> Q3-2024 | J42: =_xlfn.MINIFS(C:C,M:M,M42) -> 44945 | K42: =TEXT(J42,"MM-YYYY") -> 01-2023 | L42: Europe | M42: United Kingdom | N42: London | O42: =IF(N42="",_xlfn.XLOOKUP(M42,M:M,N:N),N42) -> London | P42: Consumer | Q42: Marketplace | R42: =IF(Q42="",_xlfn.XLOOKUP(M42,M:M,Q:Q),Q42) -> Marketplace | S42: F. Müller | T42: =IF(S42="",_xlfn.XLOOKUP(L42,L:L,S:S),S42) -> F. Müller | U42: Networking | V42: =IF(AA42<815.0987,"Low",IF(AA42<1640.058,"Medium","High")) -> Medium | W42: NET-1145 | X42: =IF(AK42<=80%,"A",IF(AK42<=95%,"B","C")) -> A | Y42: 1133.08 | Z42: 976.17 | AA42: =ABS(Z42) -> 976.17 | AB42: 0.042 | AC42: =MIN(AB42,30%) -> 0.042 | AD42: =IF(AC42>20%,1,0) -> 0 | AE42: 27 | AF42: =AA42*AE42*(1-AC42) -> 25249.613 | AG42: =Y42*AE42 -> 30593.16 | AH42: =ABS(AF42-AG42) -> 5343.5468 | AI42: =IF(AF42=0,0,AH42/AF42) -> 0.21162886 | AJ42: =AJ41+AF42 -> 2377566.3 | AK42: =AJ42/SUM(AF:AF) -> 0.2172133 | AL42: =MIN(AC42,'What-If Analysis'!$B$2) -> 0.042 | AM42: =AE42*(1+'What-If Analysis'!$B$3) -> 35.1 | AN42: =Y42*(1+'What-If Analysis'!$B$4) -> 1246.388 | AO42: =AA42*AM42*(1-AL42) -> 32824.497
A43: ORD-2023-472050 | B43: 45056 | C43: =IF(D43<B43,D43,B43) -> 45056 | D43: 45073 | E43: =IF(D43<B43,B43,D43) -> 45073 | F43: =E43-C43 -> 17 | G43: =IF(Data!F19<=7,1,0) -> 0 | H43: =TEXT(C43,"MM-YYYY") -> 05-2023 | I43: ="Q"&ROUNDUP(MONTH(H43)/3,0)&"-"&YEAR(H43) -> Q2-2023 | J43: =_xlfn.MINIFS(C:C,M:M,M43) -> 44955 | K43: =TEXT(J43,"MM-YYYY") -> 01-2023 | L43: Asia | M43: India | N43: Mumbai | O43: =IF(N43="",_xlfn.XLOOKUP(M43,M:M,N:N),N43) -> Mumbai | P43: Consumer | Q43: Retail | R43: =IF(Q43="",_xlfn.XLOOKUP(M43,M:M,Q:Q),Q43) -> Retail | S43: M. Rossi | T43: =IF(S43="",_xlfn.XLOOKUP(L43,L:L,S:S),S43) -> M. Rossi | U43: Laptops | V43: =IF(AA43<815.0987,"Low",IF(AA43<1640.058,"Medium","High")) -> High | W43: LAP-6499 | X43: =IF(AK43<=80%,"A",IF(AK43<=95%,"B","C")) -> A | Y43: 1286.16 | Z43: 3101.11 | AA43: =ABS(Z43) -> 3101.11 | AB43: 0.1 | AC43: =MIN(AB43,30%) -> 0.1 | AD43: =IF(AC43>20%,1,0) -> 0 | AE43: 23 | AF43: =AA43*AE43*(1-AC43) -> 64192.977 | AG43: =Y43*AE43 -> 29581.68 | AH43: =ABS(AF43-AG43) -> 34611.297 | AI43: =IF(AF43=0,0,AH43/AF43) -> 0.53917576 | AJ43: =AJ42+AF43 -> 2441759.3 | AK43: =AJ43/SUM(AF:AF) -> 0.22307794 | AL43: =MIN(AC43,'What-If Analysis'!$B$2) -> 0.1 | AM43: =AE43*(1+'What-If Analysis'!$B$3) -> 29.9 | AN43: =Y43*(1+'What-If Analysis'!$B$4) -> 1414.776 | AO43: =AA43*AM43*(1-AL43) -> 83450.87
A44: ORD-2023-912395 | B44: 45133 | C44: =IF(D44<B44,D44,B44) -> 45133 | D44: 45163 | E44: =IF(D44<B44,B44,D44) -> 45163 | F44: =E44-C44 -> 30 | G44: =IF(Data!F96<=7,1,0) -> 0 | H44: =TEXT(C44,"MM-YYYY") -> 07-2023 | I44: ="Q"&ROUNDUP(MONTH(H44)/3,0)&"-"&YEAR(H44) -> Q3-2023 | J44: =_xlfn.MINIFS(C:C,M:M,M44) -> 44939 | K44: =TEXT(J44,"MM-YYYY") -> 01-2023 | L44: Americas | M44: USA | N44: New York | O44: =IF(N44="",_xlfn.XLOOKUP(M44,M:M,N:N),N44) -> New York | P44: Consumer | Q44: Retail | R44: =IF(Q44="",_xlfn.XLOOKUP(M44,M:M,Q:Q),Q44) -> Retail | S44: M. Rossi | T44: =IF(S44="",_xlfn.XLOOKUP(L44,L:L,S:S),S44) -> M. Rossi | U44: Accessories | V44: =IF(AA44<815.0987,"Low",IF(AA44<1640.058,"Medium","High")) -> High | W44: ACC-7078 | X44: =IF(AK44<=80%,"A",IF(AK44<=95%,"B","C")) -> A | Y44: 1261.48 | Z44: 1643.18 | AA44: =ABS(Z44) -> 1643.18 | AB44: 0.151 | AC44: =MIN(AB44,30%) -> 0.151 | AD44: =IF(AC44>20%,1,0) -> 0 | AE44: 23 | AF44: =AA44*AE44*(1-AC44) -> 32086.376 | AG44: =Y44*AE44 -> 29014.04 | AH44: =ABS(AF44-AG44) -> 3072.3359 | AI44: =IF(AF44=0,0,AH44/AF44) -> 0.095752037 | AJ44: =AJ43+AF44 -> 2473845.7 | AK44: =AJ44/SUM(AF:AF) -> 0.22600933 | AL44: =MIN(AC44,'What-If Analysis'!$B$2) -> 0.151 | AM44: =AE44*(1+'What-If Analysis'!$B$3) -> 29.9 | AN44: =Y44*(1+'What-If Analysis'!$B$4) -> 1387.628 | AO44: =AA44*AM44*(1-AL44) -> 41712.289
A45: ORD-2025-678688 | B45: 45854 | C45: =IF(D45<B45,D45,B45) -> 45854 | D45: 45855 | E45: =IF(D45<B45,B45,D45) -> 45855 | F45: =E45-C45 -> 1 | G45: =IF(Data!F15<=7,1,0) -> 0 | H45: =TEXT(C45,"MM-YYYY") -> 07-2025 | I45: ="Q"&ROUNDUP(MONTH(H45)/3,0)&"-"&YEAR(H45) -> Q3-2025 | J45: =_xlfn.MINIFS(C:C,M:M,M45) -> 44933 | K45: =TEXT(J45,"MM-YYYY") -> 01-2023 | L45: Africa | M45: South Africa | N45: Durban | O45: =IF(N45="",_xlfn.XLOOKUP(M45,M:M,N:N),N45) -> Durban | P45: Small Business | Q45: Distributor | R45: =IF(Q45="",_xlfn.XLOOKUP(M45,M:M,Q:Q),Q45) -> Distributor | S45: B. Chen | T45: =IF(S45="",_xlfn.XLOOKUP(L45,L:L,S:S),S45) -> B. Chen | U45: Networking | V45: =IF(AA45<815.0987,"Low",IF(AA45<1640.058,"Medium","High")) -> High | W45: NET-1612 | X45: =IF(AK45<=80%,"A",IF(AK45<=95%,"B","C")) -> A | Y45: 1198.9 | Z45: 2941.2 | AA45: =ABS(Z45) -> 2941.2 | AB45: 0.051 | AC45: =MIN(AB45,30%) -> 0.051 | AD45: =IF(AC45>20%,1,0) -> 0 | AE45: 24 | AF45: =AA45*AE45*(1-AC45) -> 66988.771 | AG45: =Y45*AE45 -> 28773.6 | AH45: =ABS(AF45-AG45) -> 38215.171 | AI45: =IF(AF45=0,0,AH45/AF45) -> 0.5704713 | AJ45: =AJ44+AF45 -> 2540834.5 | AK45: =AJ45/SUM(AF:AF) -> 0.23212939 | AL45: =MIN(AC45,'What-If Analysis'!$B$2) -> 0.051 | AM45: =AE45*(1+'What-If Analysis'!$B$3) -> 31.2 | AN45: =Y45*(1+'What-If Analysis'!$B$4) -> 1318.79 | AO45: =AA45*AM45*(1-AL45) -> 87085.403
A46: ORD-2024-594527 | B46: 45541 | C46: =IF(D46<B46,D46,B46) -> 45539 | D46: 45539 | E46: =IF(D46<B46,B46,D46) -> 45541 | F46: =E46-C46 -> 2 | G46: =IF(Data!F52<=7,1,0) -> 0 | H46: =TEXT(C46,"MM-YYYY") -> 09-2024 | I46: ="Q"&ROUNDUP(MONTH(H46)/3,0)&"-"&YEAR(H46) -> Q3-2024 | J46: =_xlfn.MINIFS(C:C,M:M,M46) -> 44988 | K46: =TEXT(J46,"MM-YYYY") -> 03-2023 | L46: Asia | M46: Japan | N46: Osaka | O46: =IF(N46="",_xlfn.XLOOKUP(M46,M:M,N:N),N46) -> Osaka | P46: Corporate | Q46: Direct | R46: =IF(Q46="",_xlfn.XLOOKUP(M46,M:M,Q:Q),Q46) -> Direct | S46: A. Patel | T46: =IF(S46="",_xlfn.XLOOKUP(L46,L:L,S:S),S46) -> A. Patel | U46: Laptops | V46: =IF(AA46<815.0987,"Low",IF(AA46<1640.058,"Medium","High")) -> High | W46: LAP-4483 | X46: =IF(AK46<=80%,"A",IF(AK46<=95%,"B","C")) -> A | Y46: 1368.17 | Z46: 2307.75 | AA46: =ABS(Z46) -> 2307.75 | AB46: 0.163 | AC46: =MIN(AB46,30%) -> 0.163 | AD46: =IF(AC46>20%,1,0) -> 0 | AE46: 21 | AF46: =AA46*AE46*(1-AC46) -> 40563.322 | AG46: =Y46*AE46 -> 28731.57 | AH46: =ABS(AF46-AG46) -> 11831.752 | AI46: =IF(AF46=0,0,AH46/AF46) -> 0.29168597 | AJ46: =AJ45+AF46 -> 2581397.8 | AK46: =AJ46/SUM(AF:AF) -> 0.23583524 | AL46: =MIN(AC46,'What-If Analysis'!$B$2) -> 0.163 | AM46: =AE46*(1+'What-If Analysis'!$B$3) -> 27.3 | AN46: =Y46*(1+'What-If Analysis'!$B$4) -> 1504.987 | AO46: =AA46*AM46*(1-AL46) -> 52732.318
A47: ORD-2024-212990 | B47: 45516 | C47: =IF(D47<B47,D47,B47) -> 45516 | D47: 45538 | E47: =IF(D47<B47,B47,D47) -> 45538 | F47: =E47-C47 -> 22 | G47: =IF(Data!F156<=7,1,0) -> 1 | H47: =TEXT(C47,"MM-YYYY") -> 08-2024 | I47: ="Q"&ROUNDUP(MONTH(H47)/3,0)&"-"&YEAR(H47) -> Q3-2024 | J47: =_xlfn.MINIFS(C:C,M:M,M47) -> 44939 | K47: =TEXT(J47,"MM-YYYY") -> 01-2023 | L47: Americas | M47: USA | N47: Austin | O47: =IF(N47="",_xlfn.XLOOKUP(M47,M:M,N:N),N47) -> Austin | P47: Consumer | Q47: Distributor | R47: =IF(Q47="",_xlfn.XLOOKUP(M47,M:M,Q:Q),Q47) -> Distributor | S47: I. Johnson | T47: =IF(S47="",_xlfn.XLOOKUP(L47,L:L,S:S),S47) -> I. Johnson | U47: Laptops | V47: =IF(AA47<815.0987,"Low",IF(AA47<1640.058,"Medium","High")) -> Medium | W47: LAP-7979 | X47: =IF(AK47<=80%,"A",IF(AK47<=95%,"B","C")) -> A | Y47: 797.8 | Z47: 886.22 | AA47: =ABS(Z47) -> 886.22 | AB47: 0.236 | AC47: =MIN(AB47,30%) -> 0.236 | AD47: =IF(AC47>20%,1,0) -> 1 | AE47: 36 | AF47: =AA47*AE47*(1-AC47) -> 24374.595 | AG47: =Y47*AE47 -> 28720.8 | AH47: =ABS(AF47-AG47) -> 4346.2051 | AI47: =IF(AF47=0,0,AH47/AF47) -> 0.17830881 | AJ47: =AJ46+AF47 -> 2605772.4 | AK47: =AJ47/SUM(AF:AF) -> 0.23806209 | AL47: =MIN(AC47,'What-If Analysis'!$B$2) -> 0.2 | AM47: =AE47*(1+'What-If Analysis'!$B$3) -> 46.8 | AN47: =Y47*(1+'What-If Analysis'!$B$4) -> 877.58 | AO47: =AA47*AM47*(1-AL47) -> 33180.077
A48: ORD-2024-745822 | B48: 45382 | C48: =IF(D48<B48,D48,B48) -> 45382 | D48: 45399 | E48: =IF(D48<B48,B48,D48) -> 45399 | F48: =E48-C48 -> 17 | G48: =IF(Data!F78<=7,1,0) -> 0 | H48: =TEXT(C48,"MM-YYYY") -> 03-2024 | I48: ="Q"&ROUNDUP(MONTH(H48)/3,0)&"-"&YEAR(H48) -> Q1-2024 | J48: =_xlfn.MINIFS(C:C,M:M,M48) -> 44947 | K48: =TEXT(J48,"MM-YYYY") -> 01-2023 | L48: Europe | M48: Germany | N48: Frankfurt | O48: =IF(N48="",_xlfn.XLOOKUP(M48,M:M,N:N),N48) -> Frankfurt | P48: Education | Q48: Direct | R48: =IF(Q48="",_xlfn.XLOOKUP(M48,M:M,Q:Q),Q48) -> Direct | S48: H. Kim | T48: =IF(S48="",_xlfn.XLOOKUP(L48,L:L,S:S),S48) -> H. Kim | U48: Monitors | V48: =IF(AA48<815.0987,"Low",IF(AA48<1640.058,"Medium","High")) -> Medium | W48: MON-8651 | X48: =IF(AK48<=80%,"A",IF(AK48<=95%,"B","C")) -> A | Y48: 1025.51 | Z48: 1436.54 | AA48: =ABS(Z48) -> 1436.54 | AB48: 0.139 | AC48: =MIN(AB48,30%) -> 0.139 | AD48: =IF(AC48>20%,1,0) -> 0 | AE48: 28 | AF48: =AA48*AE48*(1-AC48) -> 34632.106 | AG48: =Y48*AE48 -> 28714.28 | AH48: =ABS(AF48-AG48) -> 5917.8263 | AI48: =IF(AF48=0,0,AH48/AF48) -> 0.17087688 | AJ48: =AJ47+AF48 -> 2640404.5 | AK48: =AJ48/SUM(AF:AF) -> 0.24122606 | AL48: =MIN(AC48,'What-If Analysis'!$B$2) -> 0.139 | AM48: =AE48*(1+'What-If Analysis'!$B$3) -> 36.4 | AN48: =Y48*(1+'What-If Analysis'!$B$4) -> 1128.061 | AO48: =AA48*AM48*(1-AL48) -> 45021.738
A49: ORD-2023-292714 | B49: 45117 | C49: =IF(D49<B49,D49,B49) -> 45117 | D49: 45139 | E49: =IF(D49<B49,B49,D49) -> 45139 | F49: =E49-C49 -> 22 | G49: =IF(Data!F79<=7,1,0) -> 0 | H49: =TEXT(C49,"MM-YYYY") -> 07-2023 | I49: ="Q"&ROUNDUP(MONTH(H49)/3,0)&"-"&YEAR(H49) -> Q3-2023 | J49: =_xlfn.MINIFS(C:C,M:M,M49) -> 44936 | K49: =TEXT(J49,"MM-YYYY") -> 01-2023 | L49: Europe | M49: France | N49: Marseille | O49: =IF(N49="",_xlfn.XLOOKUP(M49,M:M,N:N),N49) -> Marseille | P49: Consumer | Q49: Marketplace | R49: =IF(Q49="",_xlfn.XLOOKUP(M49,M:M,Q:Q),Q49) -> Marketplace | S49: B. Chen | T49: =IF(S49="",_xlfn.XLOOKUP(L49,L:L,S:S),S49) -> B. Chen | U49: Printers | V49: =IF(AA49<815.0987,"Low",IF(AA49<1640.058,"Medium","High")) -> High | W49: PRN-1504 | X49: =IF(AK49<=80%,"A",IF(AK49<=95%,"B","C")) -> A | Y49: 1303.56 | Z49: 1791.37 | AA49: =ABS(Z49) -> 1791.37 | AB49: 0.126 | AC49: =MIN(AB49,30%) -> 0.126 | AD49: =IF(AC49>20%,1,0) -> 0 | AE49: 22 | AF49: =AA49*AE49*(1-AC49) -> 34444.462 | AG49: =Y49*AE49 -> 28678.32 | AH49: =ABS(AF49-AG49) -> 5766.1424 | AI49: =IF(AF49=0,0,AH49/AF49) -> 0.16740405 | AJ49: =AJ48+AF49 -> 2674848.9 | AK49: =AJ49/SUM(AF:AF) -> 0.24437289 | AL49: =MIN(AC49,'What-If Analysis'!$B$2) -> 0.126 | AM49: =AE49*(1+'What-If Analysis'!$B$3) -> 28.6 | AN49: =Y49*(1+'What-If Analysis'!$B$4) -> 1433.916 | AO49: =AA49*AM49*(1-AL49) -> 44777.801
A50: ORD-2025-677880 | B50: 45890 | C50: =IF(D50<B50,D50,B50) -> 45890 | D50: 45914 | E50: =IF(D50<B50,B50,D50) -> 45914 | F50: =E50-C50 -> 24 | G50: =IF(Data!F25<=7,1,0) -> 0 | H50: =TEXT(C50,"MM-YYYY") -> 08-2025 | I50: ="Q"&ROUNDUP(MONTH(H50)/3,0)&"-"&YEAR(H50) -> Q3-2025 | J50: =_xlfn.MINIFS(C:C,M:M,M50) -> 44947 | K50: =TEXT(J50,"MM-YYYY") -> 01-2023 | L50: Europe | M50: Germany | N50: Berlin | O50: =IF(N50="",_xlfn.XLOOKUP(M50,M:M,N:N),N50) -> Berlin | P50: Non-Profit | Q50: Online | R50: =IF(Q50="",_xlfn.XLOOKUP(M50,M:M,Q:Q),Q50) -> Online | S50: A. Patel | T50: =IF(S50="",_xlfn.XLOOKUP(L50,L:L,S:S),S50) -> A. Patel | U50: Monitors | V50: =IF(AA50<815.0987,"Low",IF(AA50<1640.058,"Medium","High")) -> High | W50: MON-9662 | X50: =IF(AK50<=80%,"A",IF(AK50<=95%,"B","C")) -> A | Y50: 1397.67 | Z50: 3131.37 | AA50: =ABS(Z50) -> 3131.37 | AB50: 0.103 | AC50: =MIN(AB50,30%) -> 0.103 | AD50: =IF(AC50>20%,1,0) -> 0 | AE50: 20 | AF50: =AA50*AE50*(1-AC50) -> 56176.778 | AG50: =Y50*AE50 -> 27953.4 | AH50: =ABS(AF50-AG50) -> 28223.378 | AI50: =IF(AF50=0,0,AH50/AF50) -> 0.50240293 | AJ50: =AJ49+AF50 -> 2731025.7 | AK50: =AJ50/SUM(AF:AF) -> 0.24950517 | AL50: =MIN(AC50,'What-If Analysis'!$B$2) -> 0.103 | AM50: =AE50*(1+'What-If Analysis'!$B$3) -> 26 | AN50: =Y50*(1+'What-If Analysis'!$B$4) -> 1537.437 | AO50: =AA50*AM50*(1-AL50) -> 73029.811
A51: ORD-2023-594700 | B51: 45125 | C51: =IF(D51<B51,D51,B51) -> 45125 | D51: 45129 | E51: =IF(D51<B51,B51,D51) -> 45129 | F51: =E51-C51 -> 4 | G51: =IF(Data!F58<=7,1,0) -> 0 | H51: =TEXT(C51,"MM-YYYY") -> 07-2023 | I51: ="Q"&ROUNDUP(MONTH(H51)/3,0)&"-"&YEAR(H51) -> Q3-2023 | J51: =_xlfn.MINIFS(C:C,M:M,M51) -> 44955 | K51: =TEXT(J51,"MM-YYYY") -> 01-2023 | L51: Americas | M51: Brazil | N51: São Paulo | O51: =IF(N51="",_xlfn.XLOOKUP(M51,M:M,N:N),N51) -> São Paulo | P51: Consumer | Q51: Direct | R51: =IF(Q51="",_xlfn.XLOOKUP(M51,M:M,Q:Q),Q51) -> Direct | S51: F. Müller | T51: =IF(S51="",_xlfn.XLOOKUP(L51,L:L,S:S),S51) -> F. Müller | U51: Networking | V51: =IF(AA51<815.0987,"Low",IF(AA51<1640.058,"Medium","High")) -> High | W51: NET-1699 | X51: =IF(AK51<=80%,"A",IF(AK51<=95%,"B","C")) -> A | Y51: 1269.55 | Z51: 2071.1 | AA51: =ABS(Z51) -> 2071.1 | AB51: 0.129 | AC51: =MIN(AB51,30%) -> 0.129 | AD51: =IF(AC51>20%,1,0) -> 0 | AE51: 22 | AF51: =AA51*AE51*(1-AC51) -> 39686.418 | AG51: =Y51*AE51 -> 27930.1 | AH51: =ABS(AF51-AG51) -> 11756.318 | AI51: =IF(AF51=0,0,AH51/AF51) -> 0.29623027 | AJ51: =AJ50+AF51 -> 2770712.1 | AK51: =AJ51/SUM(AF:AF) -> 0.2531309 | AL51: =MIN(AC51,'What-If Analysis'!$B$2) -> 0.129 | AM51: =AE51*(1+'What-If Analysis'!$B$3) -> 28.6 | AN51: =Y51*(1+'What-If Analysis'!$B$4) -> 1396.505 | AO51: =AA51*AM51*(1-AL51) -> 51592.344
A52: ORD-2024-886939 | B52: 45446 | C52: =IF(D52<B52,D52,B52) -> 45446 | D52: 45467 | E52: =IF(D52<B52,B52,D52) -> 45467 | F52: =E52-C52 -> 21 | G52: =IF(Data!F39<=7,1,0) -> 0 | H52: =TEXT(C52,"MM-YYYY") -> 06-2024 | I52: ="Q"&ROUNDUP(MONTH(H52)/3,0)&"-"&YEAR(H52) -> Q2-2024 | J52: =_xlfn.MINIFS(C:C,M:M,M52) -> 44928 | K52: =TEXT(J52,"MM-YYYY") -> 01-2023 | L52: Americas | M52: Canada | N52: Toronto | O52: =IF(N52="",_xlfn.XLOOKUP(M52,M:M,N:N),N52) -> Toronto | P52: Small Business | Q52: Direct | R52: =IF(Q52="",_xlfn.XLOOKUP(M52,M:M,Q:Q),Q52) -> Direct | S52: G. Dubois | T52: =IF(S52="",_xlfn.XLOOKUP(L52,L:L,S:S),S52) -> G. Dubois | U52: Monitors | V52: =IF(AA52<815.0987,"Low",IF(AA52<1640.058,"Medium","High")) -> High | W52: MON-5386 | X52: =IF(AK52<=80%,"A",IF(AK52<=95%,"B","C")) -> A | Y52: 1205.5 | Z52: 2210.17 | AA52: =ABS(Z52) -> 2210.17 | AB52: 0.104 | AC52: =MIN(AB52,30%) -> 0.104 | AD52: =IF(AC52>20%,1,0) -> 0 | AE52: 23 | AF52: =AA52*AE52*(1-AC52) -> 45547.183 | AG52: =Y52*AE52 -> 27726.5 | AH52: =ABS(AF52-AG52) -> 17820.683 | AI52: =IF(AF52=0,0,AH52/AF52) -> 0.39125764 | AJ52: =AJ51+AF52 -> 2816259.3 | AK52: =AJ52/SUM(AF:AF) -> 0.25729207 | AL52: =MIN(AC52,'What-If Analysis'!$B$2) -> 0.104 | AM52: =AE52*(1+'What-If Analysis'!$B$3) -> 29.9 | AN52: =Y52*(1+'What-If Analysis'!$B$4) -> 1326.05 | AO52: =AA52*AM52*(1-AL52) -> 59211.338
A53: ORD-2024-635626 | B53: 45531 | C53: =IF(D53<B53,D53,B53) -> 45531 | D53: 45554 | E53: =IF(D53<B53,B53,D53) -> 45554 | F53: =E53-C53 -> 23 | G53: =IF(Data!F51<=7,1,0) -> 1 | H53: =TEXT(C53,"MM-YYYY") -> 08-2024 | I53: ="Q"&ROUNDUP(MONTH(H53)/3,0)&"-"&YEAR(H53) -> Q3-2024 | J53: =_xlfn.MINIFS(C:C,M:M,M53) -> 44947 | K53: =TEXT(J53,"MM-YYYY") -> 01-2023 | L53: Europe | M53: Germany | N53: Berlin | O53: =IF(N53="",_xlfn.XLOOKUP(M53,M:M,N:N),N53) -> Berlin | P53: Small Business | Q53: Direct | R53: =IF(Q53="",_xlfn.XLOOKUP(M53,M:M,Q:Q),Q53) -> Direct | S53: D. Smith | T53: =IF(S53="",_xlfn.XLOOKUP(L53,L:L,S:S),S53) -> D. Smith | U53: Monitors | V53: =IF(AA53<815.0987,"Low",IF(AA53<1640.058,"Medium","High")) -> Medium | W53: MON-9967 | X53: =IF(AK53<=80%,"A",IF(AK53<=95%,"B","C")) -> A | Y53: 1024.01 | Z53: 1580.97 | AA53: =ABS(Z53) -> 1580.97 | AB53: 0.037 | AC53: =MIN(AB53,30%) -> 0.037 | AD53: =IF(AC53>20%,1,0) -> 0 | AE53: 27 | AF53: =AA53*AE53*(1-AC53) -> 41106.801 | AG53: =Y53*AE53 -> 27648.27 | AH53: =ABS(AF53-AG53) -> 13458.531 | AI53: =IF(AF53=0,0,AH53/AF53) -> 0.327404 | AJ53: =AJ52+AF53 -> 2857366.1 | AK53: =AJ53/SUM(AF:AF) -> 0.26104757 | AL53: =MIN(AC53,'What-If Analysis'!$B$2) -> 0.037 | AM53: =AE53*(1+'What-If Analysis'!$B$3) -> 35.1 | AN53: =Y53*(1+'What-If Analysis'!$B$4) -> 1126.411 | AO53: =AA53*AM53*(1-AL53) -> 53438.841
A54: ORD-2024-353078 | B54: 45520 | C54: =IF(D54<B54,D54,B54) -> 45520 | D54: 45530 | E54: =IF(D54<B54,B54,D54) -> 45530 | F54: =E54-C54 -> 10 | G54: =IF(Data!F31<=7,1,0) -> 0 | H54: =TEXT(C54,"MM-YYYY") -> 08-2024 | I54: ="Q"&ROUNDUP(MONTH(H54)/3,0)&"-"&YEAR(H54) -> Q3-2024 | J54: =_xlfn.MINIFS(C:C,M:M,M54) -> 44939 | K54: =TEXT(J54,"MM-YYYY") -> 01-2023 | L54: Americas | M54: USA | N54: Chicago | O54: =IF(N54="",_xlfn.XLOOKUP(M54,M:M,N:N),N54) -> Chicago | P54: Corporate | Q54: Distributor | R54: =IF(Q54="",_xlfn.XLOOKUP(M54,M:M,Q:Q),Q54) -> Distributor | S54: L. Okafor | T54: =IF(S54="",_xlfn.XLOOKUP(L54,L:L,S:S),S54) -> L. Okafor | U54: Laptops | V54: =IF(AA54<815.0987,"Low",IF(AA54<1640.058,"Medium","High")) -> High | W54: LAP-5763 | X54: =IF(AK54<=80%,"A",IF(AK54<=95%,"B","C")) -> A | Y54: 1291.7 | Z54: 2657.84 | AA54: =ABS(Z54) -> 2657.84 | AB54: 0.087 | AC54: =MIN(AB54,30%) -> 0.087 | AD54: =IF(AC54>20%,1,0) -> 0 | AE54: 21 | AF54: =AA54*AE54*(1-AC54) -> 50958.766 | AG54: =Y54*AE54 -> 27125.7 | AH54: =ABS(AF54-AG54) -> 23833.066 | AI54: =IF(AF54=0,0,AH54/AF54) -> 0.46769316 | AJ54: =AJ53+AF54 -> 2908324.9 | AK54: =AJ54/SUM(AF:AF) -> 0.26570314 | AL54: =MIN(AC54,'What-If Analysis'!$B$2) -> 0.087 | AM54: =AE54*(1+'What-If Analysis'!$B$3) -> 27.3 | AN54: =Y54*(1+'What-If Analysis'!$B$4) -> 1420.87 | AO54: =AA54*AM54*(1-AL54) -> 66246.396
A55: ORD-2025-188059 | B55: 45835 | C55: =IF(D55<B55,D55,B55) -> 45835 | D55: 45849 | E55: =IF(D55<B55,B55,D55) -> 45849 | F55: =E55-C55 -> 14 | G55: =IF(Data!F42<=7,1,0) -> 1 | H55: =TEXT(C55,"MM-YYYY") -> 06-2025 | I55: ="Q"&ROUNDUP(MONTH(H55)/3,0)&"-"&YEAR(H55) -> Q2-2025 | J55: =_xlfn.MINIFS(C:C,M:M,M55) -> 44938 | K55: =TEXT(J55,"MM-YYYY") -> 01-2023 | L55: Asia | M55: China | N55: Shanghai | O55: =IF(N55="",_xlfn.XLOOKUP(M55,M:M,N:N),N55) -> Shanghai | P55: Small Business | Q55: Marketplace | R55: =IF(Q55="",_xlfn.XLOOKUP(M55,M:M,Q:Q),Q55) -> Marketplace | S55: L. Okafor | T55: =IF(S55="",_xlfn.XLOOKUP(L55,L:L,S:S),S55) -> L. Okafor | U55: Networking | V55: =IF(AA55<815.0987,"Low",IF(AA55<1640.058,"Medium","High")) -> High | W55: NET-3535 | X55: =IF(AK55<=80%,"A",IF(AK55<=95%,"B","C")) -> A | Y55: 1227.7 | Z55: 2197.23 | AA55: =ABS(Z55) -> 2197.23 | AB55: 0.099 | AC55: =MIN(AB55,30%) -> 0.099 | AD55: =IF(AC55>20%,1,0) -> 0 | AE55: 22 | AF55: =AA55*AE55*(1-AC55) -> 43553.493 | AG55: =Y55*AE55 -> 27009.4 | AH55: =ABS(AF55-AG55) -> 16544.093 | AI55: =IF(AF55=0,0,AH55/AF55) -> 0.37985686 | AJ55: =AJ54+AF55 -> 2951878.4 | AK55: =AJ55/SUM(AF:AF) -> 0.26968216 | AL55: =MIN(AC55,'What-If Analysis'!$B$2) -> 0.099 | AM55: =AE55*(1+'What-If Analysis'!$B$3) -> 28.6 | AN55: =Y55*(1+'What-If Analysis'!$B$4) -> 1350.47 | AO55: =AA55*AM55*(1-AL55) -> 56619.541
A56: ORD-2025-646342 | B56: 45871 | C56: =IF(D56<B56,D56,B56) -> 45871 | D56: 45877 | E56: =IF(D56<B56,B56,D56) -> 45877 | F56: =E56-C56 -> 6 | G56: =IF(Data!F82<=7,1,0) -> 1 | H56: =TEXT(C56,"MM-YYYY") -> 08-2025 | I56: ="Q"&ROUNDUP(MONTH(H56)/3,0)&"-"&YEAR(H56) -> Q3-2025 | J56: =_xlfn.MINIFS(C:C,M:M,M56) -> 44988 | K56: =TEXT(J56,"MM-YYYY") -> 03-2023 | L56: Asia | M56: Japan | N56: Osaka | O56: =IF(N56="",_xlfn.XLOOKUP(M56,M:M,N:N),N56) -> Osaka | P56: Consumer | Q56: Direct | R56: =IF(Q56="",_xlfn.XLOOKUP(M56,M:M,Q:Q),Q56) -> Direct | S56: N. Brown | T56: =IF(S56="",_xlfn.XLOOKUP(L56,L:L,S:S),S56) -> N. Brown | U56: Laptops | V56: =IF(AA56<815.0987,"Low",IF(AA56<1640.058,"Medium","High")) -> High | W56: LAP-4828 | X56: =IF(AK56<=80%,"A",IF(AK56<=95%,"B","C")) -> A | Y56: 1225.94 | Z56: 1793.08 | AA56: =ABS(Z56) -> 1793.08 | AB56: 0.136 | AC56: =MIN(AB56,30%) -> 0.136 | AD56: =IF(AC56>20%,1,0) -> 0 | AE56: 22 | AF56: =AA56*AE56*(1-AC56) -> 34082.865 | AG56: =Y56*AE56 -> 26970.68 | AH56: =ABS(AF56-AG56) -> 7112.1846 | AI56: =IF(AF56=0,0,AH56/AF56) -> 0.20867332 | AJ56: =AJ55+AF56 -> 2985961.2 | AK56: =AJ56/SUM(AF:AF) -> 0.27279596 | AL56: =MIN(AC56,'What-If Analysis'!$B$2) -> 0.136 | AM56: =AE56*(1+'What-If Analysis'!$B$3) -> 28.6 | AN56: =Y56*(1+'What-If Analysis'!$B$4) -> 1348.534 | AO56: =AA56*AM56*(1-AL56) -> 44307.724
A57: ORD-2025-929414 | B57: 45834 | C57: =IF(D57<B57,D57,B57) -> 45834 | D57: 45849 | E57: =IF(D57<B57,B57,D57) -> 45849 | F57: =E57-C57 -> 15 | G57: =IF(Data!F40<=7,1,0) -> 0 | H57: =TEXT(C57,"MM-YYYY") -> 06-2025 | I57: ="Q"&ROUNDUP(MONTH(H57)/3,0)&"-"&YEAR(H57) -> Q2-2025 | J57: =_xlfn.MINIFS(C:C,M:M,M57) -> 44939 | K57: =TEXT(J57,"MM-YYYY") -> 01-2023 | L57: Africa | M57: Nigeria | N57: Port Harcourt | O57: =IF(N57="",_xlfn.XLOOKUP(M57,M:M,N:N),N57) -> Port Harcourt | P57: Small Business | Q57: Online | R57: =IF(Q57="",_xlfn.XLOOKUP(M57,M:M,Q:Q),Q57) -> Online | S57: A. Patel | T57: =IF(S57="",_xlfn.XLOOKUP(L57,L:L,S:S),S57) -> A. Patel | U57: Laptops | V57: =IF(AA57<815.0987,"Low",IF(AA57<1640.058,"Medium","High")) -> High | W57: LAP-7523 | X57: =IF(AK57<=80%,"A",IF(AK57<=95%,"B","C")) -> A | Y57: 1170.15 | Z57: 2115.19 | AA57: =ABS(Z57) -> 2115.19 | AB57: 0.092 | AC57: =MIN(AB57,30%) -> 0.092 | AD57: =IF(AC57>20%,1,0) -> 0 | AE57: 23 | AF57: =AA57*AE57*(1-AC57) -> 44173.628 | AG57: =Y57*AE57 -> 26913.45 | AH57: =ABS(AF57-AG57) -> 17260.178 | AI57: =IF(AF57=0,0,AH57/AF57) -> 0.3907349 | AJ57: =AJ56+AF57 -> 3030134.9 | AK57: =AJ57/SUM(AF:AF) -> 0.27683164 | AL57: =MIN(AC57,'What-If Analysis'!$B$2) -> 0.092 | AM57: =AE57*(1+'What-If Analysis'!$B$3) -> 29.9 | AN57: =Y57*(1+'What-If Analysis'!$B$4) -> 1287.165 | AO57: =AA57*AM57*(1-AL57) -> 57425.716
A58: ORD-2025-803803 | B58: 45897 | C58: =IF(D58<B58,D58,B58) -> 45897 | D58: 45905 | E58: =IF(D58<B58,B58,D58) -> 45905 | F58: =E58-C58 -> 8 | G58: =IF(Data!F109<=7,1,0) -> 0 | H58: =TEXT(C58,"MM-YYYY") -> 08-2025 | I58: ="Q"&ROUNDUP(MONTH(H58)/3,0)&"-"&YEAR(H58) -> Q3-2025 | J58: =_xlfn.MINIFS(C:C,M:M,M58) -> 44939 | K58: =TEXT(J58,"MM-YYYY") -> 01-2023 | L58: Africa | M58: Nigeria | N58: Port Harcourt | O58: =IF(N58="",_xlfn.XLOOKUP(M58,M:M,N:N),N58) -> Port Harcourt | P58: Small Business | Q58: Marketplace | R58: =IF(Q58="",_xlfn.XLOOKUP(M58,M:M,Q:Q),Q58) -> Marketplace | S58: E. Garcia | T58: =IF(S58="",_xlfn.XLOOKUP(L58,L:L,S:S),S58) -> E. Garcia | U58: Laptops | V58: =IF(AA58<815.0987,"Low",IF(AA58<1640.058,"Medium","High")) -> High | W58: LAP-7553 | X58: =IF(AK58<=80%,"A",IF(AK58<=95%,"B","C")) -> A | Y58: 1271.1 | Z58: 1932.42 | AA58: =ABS(Z58) -> 1932.42 | AB58: 0.25 | AC58: =MIN(AB58,30%) -> 0.25 | AD58: =IF(AC58>20%,1,0) -> 1 | AE58: 21 | AF58: =AA58*AE58*(1-AC58) -> 30435.615 | AG58: =Y58*AE58 -> 26693.1 | AH58: =ABS(AF58-AG58) -> 3742.515 | AI58: =IF(AF58=0,0,AH58/AF58) -> 0.12296499 | AJ58: =AJ57+AF58 -> 3060570.5 | AK58: =AJ58/SUM(AF:AF) -> 0.27961222 | AL58: =MIN(AC58,'What-If Analysis'!$B$2) -> 0.2 | AM58: =AE58*(1+'What-If Analysis'!$B$3) -> 27.3 | AN58: =Y58*(1+'What-If Analysis'!$B$4) -> 1398.21 | AO58: =AA58*AM58*(1-AL58) -> 42204.053
A59: ORD-2023-885216 | B59: 45141 | C59: =IF(D59<B59,D59,B59) -> 45140 | D59: 45140 | E59: =IF(D59<B59,B59,D59) -> 45141 | F59: =E59-C59 -> 1 | G59: =IF(Data!F34<=7,1,0) -> 0 | H59: =TEXT(C59,"MM-YYYY") -> 08-2023 | I59: ="Q"&ROUNDUP(MONTH(H59)/3,0)&"-"&YEAR(H59) -> Q3-2023 | J59: =_xlfn.MINIFS(C:C,M:M,M59) -> 44938 | K59: =TEXT(J59,"MM-YYYY") -> 01-2023 | L59: Asia | M59: China | N59: Shanghai | O59: =IF(N59="",_xlfn.XLOOKUP(M59,M:M,N:N),N59) -> Shanghai | P59: Non-Profit | Q59: Direct | R59: =IF(Q59="",_xlfn.XLOOKUP(M59,M:M,Q:Q),Q59) -> Direct | S59: J. Njeri | T59: =IF(S59="",_xlfn.XLOOKUP(L59,L:L,S:S),S59) -> J. Njeri | U59: Networking | V59: =IF(AA59<815.0987,"Low",IF(AA59<1640.058,"Medium","High")) -> High | W59: NET-4735 | X59: =IF(AK59<=80%,"A",IF(AK59<=95%,"B","C")) -> A | Y59: 1021.97 | Z59: 2296.25 | AA59: =ABS(Z59) -> 2296.25 | AB59: 0.161 | AC59: =MIN(AB59,30%) -> 0.161 | AD59: =IF(AC59>20%,1,0) -> 0 | AE59: 26 | AF59: =AA59*AE59*(1-AC59) -> 50090.397 | AG59: =Y59*AE59 -> 26571.22 | AH59: =ABS(AF59-AG59) -> 23519.177 | AI59: =IF(AF59=0,0,AH59/AF59) -> 0.46953465 | AJ59: =AJ58+AF59 -> 3110660.9 | AK59: =AJ59/SUM(AF:AF) -> 0.28418846 | AL59: =MIN(AC59,'What-If Analysis'!$B$2) -> 0.161 | AM59: =AE59*(1+'What-If Analysis'!$B$3) -> 33.8 | AN59: =Y59*(1+'What-If Analysis'!$B$4) -> 1124.167 | AO59: =AA59*AM59*(1-AL59) -> 65117.517
A60: ORD-2024-783321 | B60: 45616 | C60: =IF(D60<B60,D60,B60) -> 45616 | D60: 45641 | E60: =IF(D60<B60,B60,D60) -> 45641 | F60: =E60-C60 -> 25 | G60: =IF(Data!F71<=7,1,0) -> 0 | H60: =TEXT(C60,"MM-YYYY") -> 11-2024 | I60: ="Q"&ROUNDUP(MONTH(H60)/3,0)&"-"&YEAR(H60) -> Q4-2024 | J60: =_xlfn.MINIFS(C:C,M:M,M60) -> 44936 | K60: =TEXT(J60,"MM-YYYY") -> 01-2023 | L60: Europe | M60: France | N60: Paris | O60: =IF(N60="",_xlfn.XLOOKUP(M60,M:M,N:N),N60) -> Paris | P60: Corporate | Q60: Online | R60: =IF(Q60="",_xlfn.XLOOKUP(M60,M:M,Q:Q),Q60) -> Online | S60: G. Dubois | T60: =IF(S60="",_xlfn.XLOOKUP(L60,L:L,S:S),S60) -> G. Dubois | U60: Printers | V60: =IF(AA60<815.0987,"Low",IF(AA60<1640.058,"Medium","High")) -> High | W60: PRN-4911 | X60: =IF(AK60<=80%,"A",IF(AK60<=95%,"B","C")) -> A | Y60: 1203.58 | Z60: 1856.16 | AA60: =ABS(Z60) -> 1856.16 | AB60: 0.129 | AC60: =MIN(AB60,30%) -> 0.129 | AD60: =IF(AC60>20%,1,0) -> 0 | AE60: 22 | AF60: =AA60*AE60*(1-AC60) -> 35567.738 | AG60: =Y60*AE60 -> 26478.76 | AH60: =ABS(AF60-AG60) -> 9088.9779 | AI60: =IF(AF60=0,0,AH60/AF60) -> 0.25553995 | AJ60: =AJ59+AF60 -> 3146228.6 | AK60: =AJ60/SUM(AF:AF) -> 0.28743791 | AL60: =MIN(AC60,'What-If Analysis'!$B$2) -> 0.129 | AM60: =AE60*(1+'What-If Analysis'!$B$3) -> 28.6 | AN60: =Y60*(1+'What-If Analysis'!$B$4) -> 1323.938 | AO60: =AA60*AM60*(1-AL60) -> 46238.059
A61: ORD-2023-619493 | B61: 44984 | C61: =IF(D61<B61,D61,B61) -> 44983 | D61: 44983 | E61: =IF(D61<B61,B61,D61) -> 44984 | F61: =E61-C61 -> 1 | G61: =IF(Data!F30<=7,1,0) -> 1 | H61: =TEXT(C61,"MM-YYYY") -> 02-2023 | I61: ="Q"&ROUNDUP(MONTH(H61)/3,0)&"-"&YEAR(H61) -> Q1-2023 | J61: =_xlfn.MINIFS(C:C,M:M,M61) -> 44939 | K61: =TEXT(J61,"MM-YYYY") -> 01-2023 | L61: Americas | M61: USA | N61: San Francisco | O61: =IF(N61="",_xlfn.XLOOKUP(M61,M:M,N:N),N61) -> San Francisco | P61: Non-Profit | Q61: Online | R61: =IF(Q61="",_xlfn.XLOOKUP(M61,M:M,Q:Q),Q61) -> Online | S61: L. Okafor | T61: =IF(S61="",_xlfn.XLOOKUP(L61,L:L,S:S),S61) -> L. Okafor | U61: Networking | V61: =IF(AA61<815.0987,"Low",IF(AA61<1640.058,"Medium","High")) -> High | W61: NET-1282 | X61: =IF(AK61<=80%,"A",IF(AK61<=95%,"B","C")) -> A | Y61: 1015.91 | Z61: 2331.48 | AA61: =ABS(Z61) -> 2331.48 | AB61: 0.146 | AC61: =MIN(AB61,30%) -> 0.146 | AD61: =IF(AC61>20%,1,0) -> 0 | AE61: 26 | AF61: =AA61*AE61*(1-AC61) -> 51768.182 | AG61: =Y61*AE61 -> 26413.66 | AH61: =ABS(AF61-AG61) -> 25354.522 | AI61: =IF(AF61=0,0,AH61/AF61) -> 0.48977038 | AJ61: =AJ60+AF61 -> 3197996.8 | AK61: =AJ61/SUM(AF:AF) -> 0.29216742 | AL61: =MIN(AC61,'What-If Analysis'!$B$2) -> 0.146 | AM61: =AE61*(1+'What-If Analysis'!$B$3) -> 33.8 | AN61: =Y61*(1+'What-If Analysis'!$B$4) -> 1117.501 | AO61: =AA61*AM61*(1-AL61) -> 67298.636
A62: ORD-2024-444710 | B62: 45557 | C62: =IF(D62<B62,D62,B62) -> 45557 | D62: 45566 | E62: =IF(D62<B62,B62,D62) -> 45566 | F62: =E62-C62 -> 9 | G62: =IF(Data!F103<=7,1,0) -> 0 | H62: =TEXT(C62,"MM-YYYY") -> 09-2024 | I62: ="Q"&ROUNDUP(MONTH(H62)/3,0)&"-"&YEAR(H62) -> Q3-2024 | J62: =_xlfn.MINIFS(C:C,M:M,M62) -> 44955 | K62: =TEXT(J62,"MM-YYYY") -> 01-2023 | L62: Americas | M62: Brazil | N62: São Paulo | O62: =IF(N62="",_xlfn.XLOOKUP(M62,M:M,N:N),N62) -> São Paulo | P62: Non-Profit | Q62: Online | R62: =IF(Q62="",_xlfn.XLOOKUP(M62,M:M,Q:Q),Q62) -> Online | S62: K. Singh | T62: =IF(S62="",_xlfn.XLOOKUP(L62,L:L,S:S),S62) -> K. Singh | U62: Monitors | V62: =IF(AA62<815.0987,"Low",IF(AA62<1640.058,"Medium","High")) -> High | W62: MON-6341 | X62: =IF(AK62<=80%,"A",IF(AK62<=95%,"B","C")) -> A | Y62: 1378.8 | Z62: 1952.04 | AA62: =ABS(Z62) -> 1952.04 | AB62: 0.159 | AC62: =MIN(AB62,30%) -> 0.159 | AD62: =IF(AC62>20%,1,0) -> 0 | AE62: 19 | AF62: =AA62*AE62*(1-AC62) -> 31191.647 | AG62: =Y62*AE62 -> 26197.2 | AH62: =ABS(AF62-AG62) -> 4994.4472 | AI62: =IF(AF62=0,0,AH62/AF62) -> 0.1601213 | AJ62: =AJ61+AF62 -> 3229188.4 | AK62: =AJ62/SUM(AF:AF) -> 0.29501708 | AL62: =MIN(AC62,'What-If Analysis'!$B$2) -> 0.159 | AM62: =AE62*(1+'What-If Analysis'!$B$3) -> 24.7 | AN62: =Y62*(1+'What-If Analysis'!$B$4) -> 1516.68 | AO62: =AA62*AM62*(1-AL62) -> 40549.141
A63: ORD-2025-474368 | B63: 45774 | C63: =IF(D63<B63,D63,B63) -> 45774 | D63: 45794 | E63: =IF(D63<B63,B63,D63) -> 45794 | F63: =E63-C63 -> 20 | G63: =IF(Data!F77<=7,1,0) -> 1 | H63: =TEXT(C63,"MM-YYYY") -> 04-2025 | I63: ="Q"&ROUNDUP(MONTH(H63)/3,0)&"-"&YEAR(H63) -> Q2-2025 | J63: =_xlfn.MINIFS(C:C,M:M,M63) -> 44939 | K63: =TEXT(J63,"MM-YYYY") -> 01-2023 | L63: Americas | M63: USA | N63: Austin | O63: =IF(N63="",_xlfn.XLOOKUP(M63,M:M,N:N),N63) -> Austin | P63: Corporate | Q63: Direct | R63: =IF(Q63="",_xlfn.XLOOKUP(M63,M:M,Q:Q),Q63) -> Direct | S63: N. Brown | T63: =IF(S63="",_xlfn.XLOOKUP(L63,L:L,S:S),S63) -> N. Brown | U63: Phones | V63: =IF(AA63<815.0987,"Low",IF(AA63<1640.058,"Medium","High")) -> Medium | W63: PHN-8776 | X63: =IF(AK63<=80%,"A",IF(AK63<=95%,"B","C")) -> A | Y63: 932.26 | Z63: 1624.67 | AA63: =ABS(Z63) -> 1624.67 | AB63: 0.235 | AC63: =MIN(AB63,30%) -> 0.235 | AD63: =IF(AC63>20%,1,0) -> 1 | AE63: 28 | AF63: =AA63*AE63*(1-AC63) -> 34800.431 | AG63: =Y63*AE63 -> 26103.28 | AH63: =ABS(AF63-AG63) -> 8697.1514 | AI63: =IF(AF63=0,0,AH63/AF63) -> 0.24991505 | AJ63: =AJ62+AF63 -> 3263988.9 | AK63: =AJ63/SUM(AF:AF) -> 0.29819643 | AL63: =MIN(AC63,'What-If Analysis'!$B$2) -> 0.2 | AM63: =AE63*(1+'What-If Analysis'!$B$3) -> 36.4 | AN63: =Y63*(1+'What-If Analysis'!$B$4) -> 1025.486 | AO63: =AA63*AM63*(1-AL63) -> 47310.39
A64: ORD-2023-957692 | B64: 45053 | C64: =IF(D64<B64,D64,B64) -> 45053 | D64: 45066 | E64: =IF(D64<B64,B64,D64) -> 45066 | F64: =E64-C64 -> 13 | G64: =IF(Data!F38<=7,1,0) -> 1 | H64: =TEXT(C64,"MM-YYYY") -> 05-2023 | I64: ="Q"&ROUNDUP(MONTH(H64)/3,0)&"-"&YEAR(H64) -> Q2-2023 | J64: =_xlfn.MINIFS(C:C,M:M,M64) -> 44955 | K64: =TEXT(J64,"MM-YYYY") -> 01-2023 | L64: Asia | M64: India | N64: Mumbai | O64: =IF(N64="",_xlfn.XLOOKUP(M64,M:M,N:N),N64) -> Mumbai | P64: Enterprise | Q64: Retail | R64: =IF(Q64="",_xlfn.XLOOKUP(M64,M:M,Q:Q),Q64) -> Retail | S64: D. Smith | T64: =IF(S64="",_xlfn.XLOOKUP(L64,L:L,S:S),S64) -> D. Smith | U64: Accessories | V64: =IF(AA64<815.0987,"Low",IF(AA64<1640.058,"Medium","High")) -> High | W64: ACC-9283 | X64: =IF(AK64<=80%,"A",IF(AK64<=95%,"B","C")) -> A | Y64: 1443.28 | Z64: 2580.57 | AA64: =ABS(Z64) -> 2580.57 | AB64: 0 | AC64: =MIN(AB64,30%) -> 0 | AD64: =IF(AC64>20%,1,0) -> 0 | AE64: 18 | AF64: =AA64*AE64*(1-AC64) -> 46450.26 | AG64: =Y64*AE64 -> 25979.04 | AH64: =ABS(AF64-AG64) -> 20471.22 | AI64: =IF(AF64=0,0,AH64/AF64) -> 0.44071271 | AJ64: =AJ63+AF64 -> 3310439.1 | AK64: =AJ64/SUM(AF:AF) -> 0.3024401 | AL64: =MIN(AC64,'What-If Analysis'!$B$2) -> 0 | AM64: =AE64*(1+'What-If Analysis'!$B$3) -> 23.4 | AN64: =Y64*(1+'What-If Analysis'!$B$4) -> 1587.608 | AO64: =AA64*AM64*(1-AL64) -> 60385.338
A65: ORD-2025-881624 | B65: 45709 | C65: =IF(D65<B65,D65,B65) -> 45709 | D65: 45737 | E65: =IF(D65<B65,B65,D65) -> 45737 | F65: =E65-C65 -> 28 | G65: =IF(Data!F186<=7,1,0) -> 1 | H65: =TEXT(C65,"MM-YYYY") -> 02-2025 | I65: ="Q"&ROUNDUP(MONTH(H65)/3,0)&"-"&YEAR(H65) -> Q1-2025 | J65: =_xlfn.MINIFS(C:C,M:M,M65) -> 44939 | K65: =TEXT(J65,"MM-YYYY") -> 01-2023 | L65: Africa | M65: Nigeria | N65: Abuja | O65: =IF(N65="",_xlfn.XLOOKUP(M65,M:M,N:N),N65) -> Abuja | P65: Enterprise | Q65: Marketplace | R65: =IF(Q65="",_xlfn.XLOOKUP(M65,M:M,Q:Q),Q65) -> Marketplace | S65: I. Johnson | T65: =IF(S65="",_xlfn.XLOOKUP(L65,L:L,S:S),S65) -> I. Johnson | U65: Phones | V65: =IF(AA65<815.0987,"Low",IF(AA65<1640.058,"Medium","High")) -> Medium | W65: PHN-5887 | X65: =IF(AK65<=80%,"A",IF(AK65<=95%,"B","C")) -> A | Y65: 1437.39 | Z65: 1388.31 | AA65: =ABS(Z65) -> 1388.31 | AB65: 0.138 | AC65: =MIN(AB65,30%) -> 0.138 | AD65: =IF(AC65>20%,1,0) -> 0 | AE65: 18 | AF65: =AA65*AE65*(1-AC65) -> 21541.018 | AG65: =Y65*AE65 -> 25873.02 | AH65: =ABS(AF65-AG65) -> 4332.002 | AI65: =IF(AF65=0,0,AH65/AF65) -> 0.2011048 | AJ65: =AJ64+AF65 -> 3331980.2 | AK65: =AJ65/SUM(AF:AF) -> 0.30440808 | AL65: =MIN(AC65,'What-If Analysis'!$B$2) -> 0.138 | AM65: =AE65*(1+'What-If Analysis'!$B$3) -> 23.4 | AN65: =Y65*(1+'What-If Analysis'!$B$4) -> 1581.129 | AO65: =AA65*AM65*(1-AL65) -> 28003.323
A66: ORD-2023-472078 | B66: 44985 | C66: =IF(D66<B66,D66,B66) -> 44985 | D66: 44991 | E66: =IF(D66<B66,B66,D66) -> 44991 | F66: =E66-C66 -> 6 | G66: =IF(Data!F97<=7,1,0) -> 0 | H66: =TEXT(C66,"MM-YYYY") -> 02-2023 | I66: ="Q"&ROUNDUP(MONTH(H66)/3,0)&"-"&YEAR(H66) -> Q1-2023 | J66: =_xlfn.MINIFS(C:C,M:M,M66) -> 44947 | K66: =TEXT(J66,"MM-YYYY") -> 01-2023 | L66: Europe | M66: Germany | N66: Frankfurt | O66: =IF(N66="",_xlfn.XLOOKUP(M66,M:M,N:N),N66) -> Frankfurt | P66: Small Business | Q66: Marketplace | R66: =IF(Q66="",_xlfn.XLOOKUP(M66,M:M,Q:Q),Q66) -> Marketplace | S66: D. Smith | T66: =IF(S66="",_xlfn.XLOOKUP(L66,L:L,S:S),S66) -> D. Smith | U66: Printers | V66: =IF(AA66<815.0987,"Low",IF(AA66<1640.058,"Medium","High")) -> Medium | W66: PRN-9624 | X66: =IF(AK66<=80%,"A",IF(AK66<=95%,"B","C")) -> A | Y66: 880.02 | Z66: 1251.21 | AA66: =ABS(Z66) -> 1251.21 | AB66: 0.123 | AC66: =MIN(AB66,30%) -> 0.123 | AD66: =IF(AC66>20%,1,0) -> 0 | AE66: 29 | AF66: =AA66*AE66*(1-AC66) -> 31822.024 | AG66: =Y66*AE66 -> 25520.58 | AH66: =ABS(AF66-AG66) -> 6301.4439 | AI66: =IF(AF66=0,0,AH66/AF66) -> 0.19802147 | AJ66: =AJ65+AF66 -> 3363802.2 | AK66: =AJ66/SUM(AF:AF) -> 0.30731532 | AL66: =MIN(AC66,'What-If Analysis'!$B$2) -> 0.123 | AM66: =AE66*(1+'What-If Analysis'!$B$3) -> 37.7 | AN66: =Y66*(1+'What-If Analysis'!$B$4) -> 968.022 | AO66: =AA66*AM66*(1-AL66) -> 41368.631
A67: ORD-2024-651852 | B67: 45654 | C67: =IF(D67<B67,D67,B67) -> 45654 | D67: 45665 | E67: =IF(D67<B67,B67,D67) -> 45665 | F67: =E67-C67 -> 11 | G67: =IF(Data!F24<=7,1,0) -> 0 | H67: =TEXT(C67,"MM-YYYY") -> 12-2024 | I67: ="Q"&ROUNDUP(MONTH(H67)/3,0)&"-"&YEAR(H67) -> Q4-2024 | J67: =_xlfn.MINIFS(C:C,M:M,M67) -> 44938 | K67: =TEXT(J67,"MM-YYYY") -> 01-2023 | L67: Asia | M67: China | N67: Shenzhen | O67: =IF(N67="",_xlfn.XLOOKUP(M67,M:M,N:N),N67) -> Shenzhen | P67: Enterprise | Q67: Online | R67: =IF(Q67="",_xlfn.XLOOKUP(M67,M:M,Q:Q),Q67) -> Online | S67: K. Singh | T67: =IF(S67="",_xlfn.XLOOKUP(L67,L:L,S:S),S67) -> K. Singh | U67: Laptops | V67: =IF(AA67<815.0987,"Low",IF(AA67<1640.058,"Medium","High")) -> High | W67: LAP-8825 | X67: =IF(AK67<=80%,"A",IF(AK67<=95%,"B","C")) -> A | Y67: 1201.31 | Z67: 2764.65 | AA67: =ABS(Z67) -> 2764.65 | AB67: 0 | AC67: =MIN(AB67,30%) -> 0 | AD67: =IF(AC67>20%,1,0) -> 0 | AE67: 21 | AF67: =AA67*AE67*(1-AC67) -> 58057.65 | AG67: =Y67*AE67 -> 25227.51 | AH67: =ABS(AF67-AG67) -> 32830.14 | AI67: =IF(AF67=0,0,AH67/AF67) -> 0.56547483 | AJ67: =AJ66+AF67 -> 3421859.8 | AK67: =AJ67/SUM(AF:AF) -> 0.31261944 | AL67: =MIN(AC67,'What-If Analysis'!$B$2) -> 0 | AM67: =AE67*(1+'What-If Analysis'!$B$3) -> 27.3 | AN67: =Y67*(1+'What-If Analysis'!$B$4) -> 1321.441 | AO67: =AA67*AM67*(1-AL67) -> 75474.945
A68: ORD-2024-206081 | B68: 45636 | C68: =IF(D68<B68,D68,B68) -> 45636 | D68: 45665 | E68: =IF(D68<B68,B68,D68) -> 45665 | F68: =E68-C68 -> 29 | G68: =IF(Data!F142<=7,1,0) -> 0 | H68: =TEXT(C68,"MM-YYYY") -> 12-2024 | I68: ="Q"&ROUNDUP(MONTH(H68)/3,0)&"-"&YEAR(H68) -> Q4-2024 | J68: =_xlfn.MINIFS(C:C,M:M,M68) -> 44936 | K68: =TEXT(J68,"MM-YYYY") -> 01-2023 | L68: Europe | M68: France | N68: Marseille | O68: =IF(N68="",_xlfn.XLOOKUP(M68,M:M,N:N),N68) -> Marseille | P68: Small Business | Q68: Retail | R68: =IF(Q68="",_xlfn.XLOOKUP(M68,M:M,Q:Q),Q68) -> Retail | S68: K. Singh | T68: =IF(S68="",_xlfn.XLOOKUP(L68,L:L,S:S),S68) -> K. Singh | U68: Printers | V68: =IF(AA68<815.0987,"Low",IF(AA68<1640.058,"Medium","High")) -> Medium | W68: PRN-6791 | X68: =IF(AK68<=80%,"A",IF(AK68<=95%,"B","C")) -> A | Y68: 891.08 | Z68: 1040.1 | AA68: =ABS(Z68) -> 1040.1 | AB68: 0.109 | AC68: =MIN(AB68,30%) -> 0.109 | AD68: =IF(AC68>20%,1,0) -> 0 | AE68: 28 | AF68: =AA68*AE68*(1-AC68) -> 25948.415 | AG68: =Y68*AE68 -> 24950.24 | AH68: =ABS(AF68-AG68) -> 998.1748 | AI68: =IF(AF68=0,0,AH68/AF68) -> 0.03846766 | AJ68: =AJ67+AF68 -> 3447808.2 | AK68: =AJ68/SUM(AF:AF) -> 0.31499007 | AL68: =MIN(AC68,'What-If Analysis'!$B$2) -> 0.109 | AM68: =AE68*(1+'What-If Analysis'!$B$3) -> 36.4 | AN68: =Y68*(1+'What-If Analysis'!$B$4) -> 980.188 | AO68: =AA68*AM68*(1-AL68) -> 33732.939
A69: ORD-2024-915495 | B69: 45512 | C69: =IF(D69<B69,D69,B69) -> 45512 | D69: 45524 | E69: =IF(D69<B69,B69,D69) -> 45524 | F69: =E69-C69 -> 12 | G69: =IF(Data!F76<=7,1,0) -> 0 | H69: =TEXT(C69,"MM-YYYY") -> 08-2024 | I69: ="Q"&ROUNDUP(MONTH(H69)/3,0)&"-"&YEAR(H69) -> Q3-2024 | J69: =_xlfn.MINIFS(C:C,M:M,M69) -> 44988 | K69: =TEXT(J69,"MM-YYYY") -> 03-2023 | L69: Asia | M69: Japan | N69: Osaka | O69: =IF(N69="",_xlfn.XLOOKUP(M69,M:M,N:N),N69) -> Osaka | P69: Small Business | Q69: Retail | R69: =IF(Q69="",_xlfn.XLOOKUP(M69,M:M,Q:Q),Q69) -> Retail | S69: H. Kim | T69: =IF(S69="",_xlfn.XLOOKUP(L69,L:L,S:S),S69) -> H. Kim | U69: Networking | V69: =IF(AA69<815.0987,"Low",IF(AA69<1640.058,"Medium","High")) -> High | W69: NET-8957 | X69: =IF(AK69<=80%,"A",IF(AK69<=95%,"B","C")) -> A | Y69: 1233.36 | Z69: 2120.4 | AA69: =ABS(Z69) -> 2120.4 | AB69: 0.179 | AC69: =MIN(AB69,30%) -> 0.179 | AD69: =IF(AC69>20%,1,0) -> 0 | AE69: 20 | AF69: =AA69*AE69*(1-AC69) -> 34816.968 | AG69: =Y69*AE69 -> 24667.2 | AH69: =ABS(AF69-AG69) -> 10149.768 | AI69: =IF(AF69=0,0,AH69/AF69) -> 0.29151786 | AJ69: =AJ68+AF69 -> 3482625.2 | AK69: =AJ69/SUM(AF:AF) -> 0.31817094 | AL69: =MIN(AC69,'What-If Analysis'!$B$2) -> 0.179 | AM69: =AE69*(1+'What-If Analysis'!$B$3) -> 26 | AN69: =Y69*(1+'What-If Analysis'!$B$4) -> 1356.696 | AO69: =AA69*AM69*(1-AL69) -> 45262.058
A70: ORD-2025-150713 | B70: 45849 | C70: =IF(D70<B70,D70,B70) -> 45849 | D70: 45854 | E70: =IF(D70<B70,B70,D70) -> 45854 | F70: =E70-C70 -> 5 | G70: =IF(Data!F151<=7,1,0) -> 0 | H70: =TEXT(C70,"MM-YYYY") -> 07-2025 | I70: ="Q"&ROUNDUP(MONTH(H70)/3,0)&"-"&YEAR(H70) -> Q3-2025 | J70: =_xlfn.MINIFS(C:C,M:M,M70) -> 44945 | K70: =TEXT(J70,"MM-YYYY") -> 01-2023 | L70: Europe | M70: United Kingdom | N70: London | O70: =IF(N70="",_xlfn.XLOOKUP(M70,M:M,N:N),N70) -> London | P70: Enterprise | Q70: Online | R70: =IF(Q70="",_xlfn.XLOOKUP(M70,M:M,Q:Q),Q70) -> Online | S70: K. Singh | T70: =IF(S70="",_xlfn.XLOOKUP(L70,L:L,S:S),S70) -> K. Singh | U70: Printers | V70: =IF(AA70<815.0987,"Low",IF(AA70<1640.058,"Medium","High")) -> Medium | W70: PRN-5753 | X70: =IF(AK70<=80%,"A",IF(AK70<=95%,"B","C")) -> A | Y70: 930.03 | Z70: 1086.68 | AA70: =ABS(Z70) -> 1086.68 | AB70: 0.109 | AC70: =MIN(AB70,30%) -> 0.109 | AD70: =IF(AC70>20%,1,0) -> 0 | AE70: 26 | AF70: =AA70*AE70*(1-AC70) -> 25174.029 | AG70: =Y70*AE70 -> 24180.78 | AH70: =ABS(AF70-AG70) -> 993.24888 | AI70: =IF(AF70=0,0,AH70/AF70) -> 0.039455301 | AJ70: =AJ69+AF70 -> 3507799.2 | AK70: =AJ70/SUM(AF:AF) -> 0.32047082 | AL70: =MIN(AC70,'What-If Analysis'!$B$2) -> 0.109 | AM70: =AE70*(1+'What-If Analysis'!$B$3) -> 33.8 | AN70: =Y70*(1+'What-If Analysis'!$B$4) -> 1023.033 | AO70: =AA70*AM70*(1-AL70) -> 32726.238
A71: ORD-2024-668926 | B71: 45588 | C71: =IF(D71<B71,D71,B71) -> 45588 | D71: 45610 | E71: =IF(D71<B71,B71,D71) -> 45610 | F71: =E71-C71 -> 22 | G71: =IF(Data!F180<=7,1,0) -> 1 | H71: =TEXT(C71,"MM-YYYY") -> 10-2024 | I71: ="Q"&ROUNDUP(MONTH(H71)/3,0)&"-"&YEAR(H71) -> Q4-2024 | J71: =_xlfn.MINIFS(C:C,M:M,M71) -> 44988 | K71: =TEXT(J71,"MM-YYYY") -> 03-2023 | L71: Asia | M71: Japan | N71: Osaka | O71: =IF(N71="",_xlfn.XLOOKUP(M71,M:M,N:N),N71) -> Osaka | P71: Non-Profit | Q71: Direct | R71: =IF(Q71="",_xlfn.XLOOKUP(M71,M:M,Q:Q),Q71) -> Direct | S71: B. Chen | T71: =IF(S71="",_xlfn.XLOOKUP(L71,L:L,S:S),S71) -> B. Chen | U71: Phones | V71: =IF(AA71<815.0987,"Low",IF(AA71<1640.058,"Medium","High")) -> Medium | W71: PHN-9789 | X71: =IF(AK71<=80%,"A",IF(AK71<=95%,"B","C")) -> A | Y71: 1406.4 | Z71: 1564.76 | AA71: =ABS(Z71) -> 1564.76 | AB71: 0.185 | AC71: =MIN(AB71,30%) -> 0.185 | AD71: =IF(AC71>20%,1,0) -> 0 | AE71: 17 | AF71: =AA71*AE71*(1-AC71) -> 21679.75 | AG71: =Y71*AE71 -> 23908.8 | AH71: =ABS(AF71-AG71) -> 2229.0502 | AI71: =IF(AF71=0,0,AH71/AF71) -> 0.10281716 | AJ71: =AJ70+AF71 -> 3529479 | AK71: =AJ71/SUM(AF:AF) -> 0.32245147 | AL71: =MIN(AC71,'What-If Analysis'!$B$2) -> 0.185 | AM71: =AE71*(1+'What-If Analysis'!$B$3) -> 22.1 | AN71: =Y71*(1+'What-If Analysis'!$B$4) -> 1547.04 | AO71: =AA71*AM71*(1-AL71) -> 28183.675
A72: ORD-2025-874124 | B72: 45791 | C72: =IF(D72<B72,D72,B72) -> 45789 | D72: 45789 | E72: =IF(D72<B72,B72,D72) -> 45791 | F72: =E72-C72 -> 2 | G72: =IF(Data!F32<=7,1,0) -> 1 | H72: =TEXT(C72,"MM-YYYY") -> 05-2025 | I72: ="Q"&ROUNDUP(MONTH(H72)/3,0)&"-"&YEAR(H72) -> Q2-2025 | J72: =_xlfn.MINIFS(C:C,M:M,M72) -> 44928 | K72: =TEXT(J72,"MM-YYYY") -> 01-2023 | L72: Americas | M72: Canada | N72: Vancouver | O72: =IF(N72="",_xlfn.XLOOKUP(M72,M:M,N:N),N72) -> Vancouver | P72: Non-Profit | Q72: Distributor | R72: =IF(Q72="",_xlfn.XLOOKUP(M72,M:M,Q:Q),Q72) -> Distributor | S72: F. Müller | T72: =IF(S72="",_xlfn.XLOOKUP(L72,L:L,S:S),S72) -> F. Müller | U72: Printers | V72: =IF(AA72<815.0987,"Low",IF(AA72<1640.058,"Medium","High")) -> High | W72: PRN-2407 | X72: =IF(AK72<=80%,"A",IF(AK72<=95%,"B","C")) -> A | Y72: 883.5 | Z72: 1978.91 | AA72: =ABS(Z72) -> 1978.91 | AB72: 0.054 | AC72: =MIN(AB72,30%) -> 0.054 | AD72: =IF(AC72>20%,1,0) -> 0 | AE72: 27 | AF72: =AA72*AE72*(1-AC72) -> 50545.319 | AG72: =Y72*AE72 -> 23854.5 | AH72: =ABS(AF72-AG72) -> 26690.819 | AI72: =IF(AF72=0,0,AH72/AF72) -> 0.52805719 | AJ72: =AJ71+AF72 -> 3580024.3 | AK72: =AJ72/SUM(AF:AF) -> 0.32706927 | AL72: =MIN(AC72,'What-If Analysis'!$B$2) -> 0.054 | AM72: =AE72*(1+'What-If Analysis'!$B$3) -> 35.1 | AN72: =Y72*(1+'What-If Analysis'!$B$4) -> 971.85 | AO72: =AA72*AM72*(1-AL72) -> 65708.915
A73: ORD-2024-906395 | B73: 45361 | C73: =IF(D73<B73,D73,B73) -> 45361 | D73: 45391 | E73: =IF(D73<B73,B73,D73) -> 45391 | F73: =E73-C73 -> 30 | G73: =IF(Data!F84<=7,1,0) -> 1 | H73: =TEXT(C73,"MM-YYYY") -> 03-2024 | I73: ="Q"&ROUNDUP(MONTH(H73)/3,0)&"-"&YEAR(H73) -> Q1-2024 | J73: =_xlfn.MINIFS(C:C,M:M,M73) -> 44936 | K73: =TEXT(J73,"MM-YYYY") -> 01-2023 | L73: Europe | M73: France | N73: Lyon | O73: =IF(N73="",_xlfn.XLOOKUP(M73,M:M,N:N),N73) -> Lyon | P73: Corporate | Q73: Direct | R73: =IF(Q73="",_xlfn.XLOOKUP(M73,M:M,Q:Q),Q73) -> Direct | S73: I. Johnson | T73: =IF(S73="",_xlfn.XLOOKUP(L73,L:L,S:S),S73) -> I. Johnson | U73: Components | V73: =IF(AA73<815.0987,"Low",IF(AA73<1640.058,"Medium","High")) -> High | W73: CMP-8002 | X73: =IF(AK73<=80%,"A",IF(AK73<=95%,"B","C")) -> A | Y73: 1176.56 | Z73: 1911.89 | AA73: =ABS(Z73) -> 1911.89 | AB73: 0.119 | AC73: =MIN(AB73,30%) -> 0.119 | AD73: =IF(AC73>20%,1,0) -> 0 | AE73: 20 | AF73: =AA73*AE73*(1-AC73) -> 33687.502 | AG73: =Y73*AE73 -> 23531.2 | AH73: =ABS(AF73-AG73) -> 10156.302 | AI73: =IF(AF73=0,0,AH73/AF73) -> 0.30148575 | AJ73: =AJ72+AF73 -> 3613711.8 | AK73: =AJ73/SUM(AF:AF) -> 0.33014694 | AL73: =MIN(AC73,'What-If Analysis'!$B$2) -> 0.119 | AM73: =AE73*(1+'What-If Analysis'!$B$3) -> 26 | AN73: =Y73*(1+'What-If Analysis'!$B$4) -> 1294.216 | AO73: =AA73*AM73*(1-AL73) -> 43793.752
A74: ORD-2024-640340 | B74: 45587 | C74: =IF(D74<B74,D74,B74) -> 45587 | D74: 45594 | E74: =IF(D74<B74,B74,D74) -> 45594 | F74: =E74-C74 -> 7 | G74: =IF(Data!F136<=7,1,0) -> 0 | H74: =TEXT(C74,"MM-YYYY") -> 10-2024 | I74: ="Q"&ROUNDUP(MONTH(H74)/3,0)&"-"&YEAR(H74) -> Q4-2024 | J74: =_xlfn.MINIFS(C:C,M:M,M74) -> 44939 | K74: =TEXT(J74,"MM-YYYY") -> 01-2023 | L74: Africa | M74: Nigeria | N74: Port Harcourt | O74: =IF(N74="",_xlfn.XLOOKUP(M74,M:M,N:N),N74) -> Port Harcourt | P74: Enterprise | Q74: Distributor | R74: =IF(Q74="",_xlfn.XLOOKUP(M74,M:M,Q:Q),Q74) -> Distributor | S74: M. Rossi | T74: =IF(S74="",_xlfn.XLOOKUP(L74,L:L,S:S),S74) -> M. Rossi | U74: Monitors | V74: =IF(AA74<815.0987,"Low",IF(AA74<1640.058,"Medium","High")) -> Medium | W74: MON-8758 | X74: =IF(AK74<=80%,"A",IF(AK74<=95%,"B","C")) -> A | Y74: 1023.06 | Z74: 1355.61 | AA74: =ABS(Z74) -> 1355.61 | AB74: 0.153 | AC74: =MIN(AB74,30%) -> 0.153 | AD74: =IF(AC74>20%,1,0) -> 0 | AE74: 23 | AF74: =AA74*AE74*(1-AC74) -> 26408.638 | AG74: =Y74*AE74 -> 23530.38 | AH74: =ABS(AF74-AG74) -> 2878.2584 | AI74: =IF(AF74=0,0,AH74/AF74) -> 0.10898928 | AJ74: =AJ73+AF74 -> 3640120.5 | AK74: =AJ74/SUM(AF:AF) -> 0.33255962 | AL74: =MIN(AC74,'What-If Analysis'!$B$2) -> 0.153 | AM74: =AE74*(1+'What-If Analysis'!$B$3) -> 29.9 | AN74: =Y74*(1+'What-If Analysis'!$B$4) -> 1125.366 | AO74: =AA74*AM74*(1-AL74) -> 34331.23
A75: ORD-2024-939873 | B75: 45394 | C75: =IF(D75<B75,D75,B75) -> 45394 | D75: 45419 | E75: =IF(D75<B75,B75,D75) -> 45419 | F75: =E75-C75 -> 25 | G75: =IF(Data!F194<=7,1,0) -> 0 | H75: =TEXT(C75,"MM-YYYY") -> 04-2024 | I75: ="Q"&ROUNDUP(MONTH(H75)/3,0)&"-"&YEAR(H75) -> Q2-2024 | J75: =_xlfn.MINIFS(C:C,M:M,M75) -> 44933 | K75: =TEXT(J75,"MM-YYYY") -> 01-2023 | L75: Africa | M75: South Africa | N75: Johannesburg | O75: =IF(N75="",_xlfn.XLOOKUP(M75,M:M,N:N),N75) -> Johannesburg | P75: Education | Q75: Distributor | R75: =IF(Q75="",_xlfn.XLOOKUP(M75,M:M,Q:Q),Q75) -> Distributor | S75: A. Patel | T75: =IF(S75="",_xlfn.XLOOKUP(L75,L:L,S:S),S75) -> A. Patel | U75: Laptops | V75: =IF(AA75<815.0987,"Low",IF(AA75<1640.058,"Medium","High")) -> Medium | W75: LAP-8489 | X75: =IF(AK75<=80%,"A",IF(AK75<=95%,"B","C")) -> A | Y75: 1376.51 | Z75: 1455.91 | AA75: =ABS(Z75) -> 1455.91 | AB75: 0.185 | AC75: =MIN(AB75,30%) -> 0.185 | AD75: =IF(AC75>20%,1,0) -> 0 | AE75: 17 | AF75: =AA75*AE75*(1-AC75) -> 20171.633 | AG75: =Y75*AE75 -> 23400.67 | AH75: =ABS(AF75-AG75) -> 3229.0369 | AI75: =IF(AF75=0,0,AH75/AF75) -> 0.16007811 | AJ75: =AJ74+AF75 -> 3660292.1 | AK75: =AJ75/SUM(AF:AF) -> 0.33440249 | AL75: =MIN(AC75,'What-If Analysis'!$B$2) -> 0.185 | AM75: =AE75*(1+'What-If Analysis'!$B$3) -> 22.1 | AN75: =Y75*(1+'What-If Analysis'!$B$4) -> 1514.161 | AO75: =AA75*AM75*(1-AL75) -> 26223.123
A76: ORD-2024-438404 | B76: 45558 | C76: =IF(D76<B76,D76,B76) -> 45558 | D76: 45583 | E76: =IF(D76<B76,B76,D76) -> 45583 | F76: =E76-C76 -> 25 | G76: =IF(Data!F45<=7,1,0) -> 1 | H76: =TEXT(C76,"MM-YYYY") -> 09-2024 | I76: ="Q"&ROUNDUP(MONTH(H76)/3,0)&"-"&YEAR(H76) -> Q3-2024 | J76: =_xlfn.MINIFS(C:C,M:M,M76) -> 44928 | K76: =TEXT(J76,"MM-YYYY") -> 01-2023 | L76: Americas | M76: Canada | N76: Vancouver | O76: =IF(N76="",_xlfn.XLOOKUP(M76,M:M,N:N),N76) -> Vancouver | P76: Small Business | Q76: Online | R76: =IF(Q76="",_xlfn.XLOOKUP(M76,M:M,Q:Q),Q76) -> Online | S76: N. Brown | T76: =IF(S76="",_xlfn.XLOOKUP(L76,L:L,S:S),S76) -> N. Brown | U76: Phones | V76: =IF(AA76<815.0987,"Low",IF(AA76<1640.058,"Medium","High")) -> High | W76: PHN-4568 | X76: =IF(AK76<=80%,"A",IF(AK76<=95%,"B","C")) -> A | Y76: 1297 | Z76: 2411.52 | AA76: =ABS(Z76) -> 2411.52 | AB76: 0.021 | AC76: =MIN(AB76,30%) -> 0.021 | AD76: =IF(AC76>20%,1,0) -> 0 | AE76: 18 | AF76: =AA76*AE76*(1-AC76) -> 42495.805 | AG76: =Y76*AE76 -> 23346 | AH76: =ABS(AF76-AG76) -> 19149.805 | AI76: =IF(AF76=0,0,AH76/AF76) -> 0.45062813 | AJ76: =AJ75+AF76 -> 3702787.9 | AK76: =AJ76/SUM(AF:AF) -> 0.33828489 | AL76: =MIN(AC76,'What-If Analysis'!$B$2) -> 0.021 | AM76: =AE76*(1+'What-If Analysis'!$B$3) -> 23.4 | AN76: =Y76*(1+'What-If Analysis'!$B$4) -> 1426.7 | AO76: =AA76*AM76*(1-AL76) -> 55244.547
A77: ORD-2023-378104 | B77: 45217 | C77: =IF(D77<B77,D77,B77) -> 45217 | D77: 45219 | E77: =IF(D77<B77,B77,D77) -> 45219 | F77: =E77-C77 -> 2 | G77: =IF(Data!F130<=7,1,0) -> 1 | H77: =TEXT(C77,"MM-YYYY") -> 10-2023 | I77: ="Q"&ROUNDUP(MONTH(H77)/3,0)&"-"&YEAR(H77) -> Q4-2023 | J77: =_xlfn.MINIFS(C:C,M:M,M77) -> 44946 | K77: =TEXT(J77,"MM-YYYY") -> 01-2023 | L77: Africa | M77: Kenya | N77: Kisumu | O77: =IF(N77="",_xlfn.XLOOKUP(M77,M:M,N:N),N77) -> Kisumu | P77: Consumer | Q77: Retail | R77: =IF(Q77="",_xlfn.XLOOKUP(M77,M:M,Q:Q),Q77) -> Retail | S77: J. Njeri | T77: =IF(S77="",_xlfn.XLOOKUP(L77,L:L,S:S),S77) -> J. Njeri | U77: Phones | V77: =IF(AA77<815.0987,"Low",IF(AA77<1640.058,"Medium","High")) -> Medium | W77: PHN-8891 | X77: =IF(AK77<=80%,"A",IF(AK77<=95%,"B","C")) -> A | Y77: 774.12 | Z77: 908.3 | AA77: =ABS(Z77) -> 908.3 | AB77: 0 | AC77: =MIN(AB77,30%) -> 0 | AD77: =IF(AC77>20%,1,0) -> 0 | AE77: 30 | AF77: =AA77*AE77*(1-AC77) -> 27249 | AG77: =Y77*AE77 -> 23223.6 | AH77: =ABS(AF77-AG77) -> 4025.4 | AI77: =IF(AF77=0,0,AH77/AF77) -> 0.14772652 | AJ77: =AJ76+AF77 -> 3730036.9 | AK77: =AJ77/SUM(AF:AF) -> 0.34077435 | AL77: =MIN(AC77,'What-If Analysis'!$B$2) -> 0 | AM77: =AE77*(1+'What-If Analysis'!$B$3) -> 39 | AN77: =Y77*(1+'What-If Analysis'!$B$4) -> 851.532 | AO77: =AA77*AM77*(1-AL77) -> 35423.7
A78: ORD-2023-308124 | B78: 45035 | C78: =IF(D78<B78,D78,B78) -> 45035 | D78: 45046 | E78: =IF(D78<B78,B78,D78) -> 45046 | F78: =E78-C78 -> 11 | G78: =IF(Data!F93<=7,1,0) -> 0 | H78: =TEXT(C78,"MM-YYYY") -> 04-2023 | I78: ="Q"&ROUNDUP(MONTH(H78)/3,0)&"-"&YEAR(H78) -> Q2-2023 | J78: =_xlfn.MINIFS(C:C,M:M,M78) -> 44955 | K78: =TEXT(J78,"MM-YYYY") -> 01-2023 | L78: Asia | M78: India | N78: Delhi | O78: =IF(N78="",_xlfn.XLOOKUP(M78,M:M,N:N),N78) -> Delhi | P78: Small Business | Q78: Retail | R78: =IF(Q78="",_xlfn.XLOOKUP(M78,M:M,Q:Q),Q78) -> Retail | S78: A. Patel | T78: =IF(S78="",_xlfn.XLOOKUP(L78,L:L,S:S),S78) -> A. Patel | U78: Networking | V78: =IF(AA78<815.0987,"Low",IF(AA78<1640.058,"Medium","High")) -> Medium | W78: NET-2062 | X78: =IF(AK78<=80%,"A",IF(AK78<=95%,"B","C")) -> A | Y78: 826.55 | Z78: 1397.05 | AA78: =ABS(Z78) -> 1397.05 | AB78: 0.169 | AC78: =MIN(AB78,30%) -> 0.169 | AD78: =IF(AC78>20%,1,0) -> 0 | AE78: 28 | AF78: =AA78*AE78*(1-AC78) -> 32506.559 | AG78: =Y78*AE78 -> 23143.4 | AH78: =ABS(AF78-AG78) -> 9363.1594 | AI78: =IF(AF78=0,0,AH78/AF78) -> 0.28803908 | AJ78: =AJ77+AF78 -> 3762543.5 | AK78: =AJ78/SUM(AF:AF) -> 0.34374413 | AL78: =MIN(AC78,'What-If Analysis'!$B$2) -> 0.169 | AM78: =AE78*(1+'What-If Analysis'!$B$3) -> 36.4 | AN78: =Y78*(1+'What-If Analysis'!$B$4) -> 909.205 | AO78: =AA78*AM78*(1-AL78) -> 42258.527
A79: ORD-2024-129345 | B79: 45340 | C79: =IF(D79<B79,D79,B79) -> 45340 | D79: 45354 | E79: =IF(D79<B79,B79,D79) -> 45354 | F79: =E79-C79 -> 14 | G79: =IF(Data!F63<=7,1,0) -> 0 | H79: =TEXT(C79,"MM-YYYY") -> 02-2024 | I79: ="Q"&ROUNDUP(MONTH(H79)/3,0)&"-"&YEAR(H79) -> Q1-2024 | J79: =_xlfn.MINIFS(C:C,M:M,M79) -> 44955 | K79: =TEXT(J79,"MM-YYYY") -> 01-2023 | L79: Americas | M79: Brazil | O79: =IF(N79="",_xlfn.XLOOKUP(M79,M:M,N:N),N79) -> São Paulo | P79: Enterprise | Q79: Distributor | R79: =IF(Q79="",_xlfn.XLOOKUP(M79,M:M,Q:Q),Q79) -> Distributor | S79: A. Patel | T79: =IF(S79="",_xlfn.XLOOKUP(L79,L:L,S:S),S79) -> A. Patel | U79: Printers | V79: =IF(AA79<815.0987,"Low",IF(AA79<1640.058,"Medium","High")) -> Medium | W79: PRN-5384 | X79: =IF(AK79<=80%,"A",IF(AK79<=95%,"B","C")) -> A | Y79: 624.23 | Z79: 1318.37 | AA79: =ABS(Z79) -> 1318.37 | AB79: 0.21 | AC79: =MIN(AB79,30%) -> 0.21 | AD79: =IF(AC79>20%,1,0) -> 1 | AE79: 37 | AF79: =AA79*AE79*(1-AC79) -> 38535.955 | AG79: =Y79*AE79 -> 23096.51 | AH79: =ABS(AF79-AG79) -> 15439.445 | AI79: =IF(AF79=0,0,AH79/AF79) -> 0.40065038 | AJ79: =AJ78+AF79 -> 3801079.4 | AK79: =AJ79/SUM(AF:AF) -> 0.34726475 | AL79: =MIN(AC79,'What-If Analysis'!$B$2) -> 0.2 | AM79: =AE79*(1+'What-If Analysis'!$B$3) -> 48.1 | AN79: =Y79*(1+'What-If Analysis'!$B$4) -> 686.653 | AO79: =AA79*AM79*(1-AL79) -> 50730.878
A80: ORD-2025-312803 | B80: 45832 | C80: =IF(D80<B80,D80,B80) -> 45832 | D80: 45852 | E80: =IF(D80<B80,B80,D80) -> 45852 | F80: =E80-C80 -> 20 | G80: =IF(Data!F46<=7,1,0) -> 1 | H80: =TEXT(C80,"MM-YYYY") -> 06-2025 | I80: ="Q"&ROUNDUP(MONTH(H80)/3,0)&"-"&YEAR(H80) -> Q2-2025 | J80: =_xlfn.MINIFS(C:C,M:M,M80) -> 44933 | K80: =TEXT(J80,"MM-YYYY") -> 01-2023 | L80: Africa | M80: South Africa | N80: Johannesburg | O80: =IF(N80="",_xlfn.XLOOKUP(M80,M:M,N:N),N80) -> Johannesburg | P80: Enterprise | Q80: Marketplace | R80: =IF(Q80="",_xlfn.XLOOKUP(M80,M:M,Q:Q),Q80) -> Marketplace | S80: J. Njeri | T80: =IF(S80="",_xlfn.XLOOKUP(L80,L:L,S:S),S80) -> J. Njeri | U80: Laptops | V80: =IF(AA80<815.0987,"Low",IF(AA80<1640.058,"Medium","High")) -> High | W80: LAP-1308 | X80: =IF(AK80<=80%,"A",IF(AK80<=95%,"B","C")) -> A | Y80: 1151.06 | Z80: 2821.36 | AA80: =ABS(Z80) -> 2821.36 | AB80: 0.248 | AC80: =MIN(AB80,30%) -> 0.248 | AD80: =IF(AC80>20%,1,0) -> 1 | AE80: 20 | AF80: =AA80*AE80*(1-AC80) -> 42433.254 | AG80: =Y80*AE80 -> 23021.2 | AH80: =ABS(AF80-AG80) -> 19412.054 | AI80: =IF(AF80=0,0,AH80/AF80) -> 0.45747268 | AJ80: =AJ79+AF80 -> 3843512.7 | AK80: =AJ80/SUM(AF:AF) -> 0.35114144 | AL80: =MIN(AC80,'What-If Analysis'!$B$2) -> 0.2 | AM80: =AE80*(1+'What-If Analysis'!$B$3) -> 26 | AN80: =Y80*(1+'What-If Analysis'!$B$4) -> 1266.166 | AO80: =AA80*AM80*(1-AL80) -> 58684.288
A81: ORD-2023-249805 | B81: 45282 | C81: =IF(D81<B81,D81,B81) -> 45282 | D81: 45307 | E81: =IF(D81<B81,B81,D81) -> 45307 | F81: =E81-C81 -> 25 | G81: =IF(Data!F281<=7,1,0) -> 0 | H81: =TEXT(C81,"MM-YYYY") -> 12-2023 | I81: ="Q"&ROUNDUP(MONTH(H81)/3,0)&"-"&YEAR(H81) -> Q4-2023 | J81: =_xlfn.MINIFS(C:C,M:M,M81) -> 44955 | K81: =TEXT(J81,"MM-YYYY") -> 01-2023 | L81: Asia | M81: India | N81: Hyderabad | O81: =IF(N81="",_xlfn.XLOOKUP(M81,M:M,N:N),N81) -> Hyderabad | P81: Small Business | Q81: Retail | R81: =IF(Q81="",_xlfn.XLOOKUP(M81,M:M,Q:Q),Q81) -> Retail | S81: A. Patel | T81: =IF(S81="",_xlfn.XLOOKUP(L81,L:L,S:S),S81) -> A. Patel | U81: Components | V81: =IF(AA81<815.0987,"Low",IF(AA81<1640.058,"Medium","High")) -> Medium | W81: CMP-1555 | X81: =IF(AK81<=80%,"A",IF(AK81<=95%,"B","C")) -> A | Y81: 1346.81 | Z81: 978.09 | AA81: =ABS(Z81) -> 978.09 | AB81: 0.159 | AC81: =MIN(AB81,30%) -> 0.159 | AD81: =IF(AC81>20%,1,0) -> 0 | AE81: 17 | AF81: =AA81*AE81*(1-AC81) -> 13983.753 | AG81: =Y81*AE81 -> 22895.77 | AH81: =ABS(AF81-AG81) -> 8912.0173 | AI81: =IF(AF81=0,0,AH81/AF81) -> 0.63731228 | AJ81: =AJ80+AF81 -> 3857496.4 | AK81: =AJ81/SUM(AF:AF) -> 0.35241898 | AL81: =MIN(AC81,'What-If Analysis'!$B$2) -> 0.159 | AM81: =AE81*(1+'What-If Analysis'!$B$3) -> 22.1 | AN81: =Y81*(1+'What-If Analysis'!$B$4) -> 1481.491 | AO81: =AA81*AM81*(1-AL81) -> 18178.879
A82: ORD-2024-704056 | B82: 45466 | C82: =IF(D82<B82,D82,B82) -> 45466 | D82: 45468 | E82: =IF(D82<B82,B82,D82) -> 45468 | F82: =E82-C82 -> 2 | G82: =IF(Data!F74<=7,1,0) -> 1 | H82: =TEXT(C82,"MM-YYYY") -> 06-2024 | I82: ="Q"&ROUNDUP(MONTH(H82)/3,0)&"-"&YEAR(H82) -> Q2-2024 | J82: =_xlfn.MINIFS(C:C,M:M,M82) -> 44945 | K82: =TEXT(J82,"MM-YYYY") -> 01-2023 | L82: Europe | M82: United Kingdom | N82: Birmingham | O82: =IF(N82="",_xlfn.XLOOKUP(M82,M:M,N:N),N82) -> Birmingham | P82: Small Business | Q82: Marketplace | R82: =IF(Q82="",_xlfn.XLOOKUP(M82,M:M,Q:Q),Q82) -> Marketplace | S82: L. Okafor | T82: =IF(S82="",_xlfn.XLOOKUP(L82,L:L,S:S),S82) -> L. Okafor | U82: Accessories | V82: =IF(AA82<815.0987,"Low",IF(AA82<1640.058,"Medium","High")) -> High | W82: ACC-7838 | X82: =IF(AK82<=80%,"A",IF(AK82<=95%,"B","C")) -> A | Y82: 951.44 | Z82: 1646.43 | AA82: =ABS(Z82) -> 1646.43 | AB82: 0.11 | AC82: =MIN(AB82,30%) -> 0.11 | AD82: =IF(AC82>20%,1,0) -> 0 | AE82: 24 | AF82: =AA82*AE82*(1-AC82) -> 35167.745 | AG82: =Y82*AE82 -> 22834.56 | AH82: =ABS(AF82-AG82) -> 12333.185 | AI82: =IF(AF82=0,0,AH82/AF82) -> 0.35069593 | AJ82: =AJ81+AF82 -> 3892664.2 | AK82: =AJ82/SUM(AF:AF) -> 0.35563189 | AL82: =MIN(AC82,'What-If Analysis'!$B$2) -> 0.11 | AM82: =AE82*(1+'What-If Analysis'!$B$3) -> 31.2 | AN82: =Y82*(1+'What-If Analysis'!$B$4) -> 1046.584 | AO82: =AA82*AM82*(1-AL82) -> 45718.068
A83: ORD-2024-331226 | B83: 45626 | C83: =IF(D83<B83,D83,B83) -> 45626 | D83: 45645 | E83: =IF(D83<B83,B83,D83) -> 45645 | F83: =E83-C83 -> 19 | G83: =IF(Data!F89<=7,1,0) -> 0 | H83: =TEXT(C83,"MM-YYYY") -> 11-2024 | I83: ="Q"&ROUNDUP(MONTH(H83)/3,0)&"-"&YEAR(H83) -> Q4-2024 | J83: =_xlfn.MINIFS(C:C,M:M,M83) -> 44946 | K83: =TEXT(J83,"MM-YYYY") -> 01-2023 | L83: Africa | M83: Kenya | N83: Kisumu | O83: =IF(N83="",_xlfn.XLOOKUP(M83,M:M,N:N),N83) -> Kisumu | P83: Corporate | Q83: Online | R83: =IF(Q83="",_xlfn.XLOOKUP(M83,M:M,Q:Q),Q83) -> Online | S83: L. Okafor | T83: =IF(S83="",_xlfn.XLOOKUP(L83,L:L,S:S),S83) -> L. Okafor | U83: Phones | V83: =IF(AA83<815.0987,"Low",IF(AA83<1640.058,"Medium","High")) -> High | W83: PHN-1919 | X83: =IF(AK83<=80%,"A",IF(AK83<=95%,"B","C")) -> A | Y83: 1195.98 | Z83: 1841.9 | AA83: =ABS(Z83) -> 1841.9 | AB83: 0.055 | AC83: =MIN(AB83,30%) -> 0.055 | AD83: =IF(AC83>20%,1,0) -> 0 | AE83: 19 | AF83: =AA83*AE83*(1-AC83) -> 33071.315 | AG83: =Y83*AE83 -> 22723.62 | AH83: =ABS(AF83-AG83) -> 10347.695 | AI83: =IF(AF83=0,0,AH83/AF83) -> 0.31289033 | AJ83: =AJ82+AF83 -> 3925735.5 | AK83: =AJ83/SUM(AF:AF) -> 0.35865327 | AL83: =MIN(AC83,'What-If Analysis'!$B$2) -> 0.055 | AM83: =AE83*(1+'What-If Analysis'!$B$3) -> 24.7 | AN83: =Y83*(1+'What-If Analysis'!$B$4) -> 1315.578 | AO83: =AA83*AM83*(1-AL83) -> 42992.709
A84: ORD-2024-925626 | B84: 45600 | C84: =IF(D84<B84,D84,B84) -> 45600 | D84: 45601 | E84: =IF(D84<B84,B84,D84) -> 45601 | F84: =E84-C84 -> 1 | G84: =IF(Data!F55<=7,1,0) -> 0 | H84: =TEXT(C84,"MM-YYYY") -> 11-2024 | I84: ="Q"&ROUNDUP(MONTH(H84)/3,0)&"-"&YEAR(H84) -> Q4-2024 | J84: =_xlfn.MINIFS(C:C,M:M,M84) -> 44945 | K84: =TEXT(J84,"MM-YYYY") -> 01-2023 | L84: Europe | M84: United Kingdom | N84: London | O84: =IF(N84="",_xlfn.XLOOKUP(M84,M:M,N:N),N84) -> London | P84: Corporate | Q84: Retail | R84: =IF(Q84="",_xlfn.XLOOKUP(M84,M:M,Q:Q),Q84) -> Retail | S84: M. Rossi | T84: =IF(S84="",_xlfn.XLOOKUP(L84,L:L,S:S),S84) -> M. Rossi | U84: Printers | V84: =IF(AA84<815.0987,"Low",IF(AA84<1640.058,"Medium","High")) -> Medium | W84: PRN-2293 | X84: =IF(AK84<=80%,"A",IF(AK84<=95%,"B","C")) -> A | Y84: 840.68 | Z84: 1493.53 | AA84: =ABS(Z84) -> 1493.53 | AB84: 0 | AC84: =MIN(AB84,30%) -> 0 | AD84: =IF(AC84>20%,1,0) -> 0 | AE84: 27 | AF84: =AA84*AE84*(1-AC84) -> 40325.31 | AG84: =Y84*AE84 -> 22698.36 | AH84: =ABS(AF84-AG84) -> 17626.95 | AI84: =IF(AF84=0,0,AH84/AF84) -> 0.43711877 | AJ84: =AJ83+AF84 -> 3966060.8 | AK84: =AJ84/SUM(AF:AF) -> 0.36233737 | AL84: =MIN(AC84,'What-If Analysis'!$B$2) -> 0 | AM84: =AE84*(1+'What-If Analysis'!$B$3) -> 35.1 | AN84: =Y84*(1+'What-If Analysis'!$B$4) -> 924.748 | AO84: =AA84*AM84*(1-AL84) -> 52422.903
A85: ORD-2024-237478 | B85: 45568 | C85: =IF(D85<B85,D85,B85) -> 45568 | D85: 45576 | E85: =IF(D85<B85,B85,D85) -> 45576 | F85: =E85-C85 -> 8 | G85: =IF(Data!F49<=7,1,0) -> 0 | H85: =TEXT(C85,"MM-YYYY") -> 10-2024 | I85: ="Q"&ROUNDUP(MONTH(H85)/3,0)&"-"&YEAR(H85) -> Q4-2024 | J85: =_xlfn.MINIFS(C:C,M:M,M85) -> 44938 | K85: =TEXT(J85,"MM-YYYY") -> 01-2023 | L85: Asia | M85: China | N85: Beijing | O85: =IF(N85="",_xlfn.XLOOKUP(M85,M:M,N:N),N85) -> Beijing | P85: Enterprise | Q85: Direct | R85: =IF(Q85="",_xlfn.XLOOKUP(M85,M:M,Q:Q),Q85) -> Direct | S85: B. Chen | T85: =IF(S85="",_xlfn.XLOOKUP(L85,L:L,S:S),S85) -> B. Chen | U85: Phones | V85: =IF(AA85<815.0987,"Low",IF(AA85<1640.058,"Medium","High")) -> High | W85: PHN-7488 | X85: =IF(AK85<=80%,"A",IF(AK85<=95%,"B","C")) -> A | Y85: 1132.61 | Z85: 2206.63 | AA85: =ABS(Z85) -> 2206.63 | AB85: 0.063 | AC85: =MIN(AB85,30%) -> 0.063 | AD85: =IF(AC85>20%,1,0) -> 0 | AE85: 20 | AF85: =AA85*AE85*(1-AC85) -> 41352.246 | AG85: =Y85*AE85 -> 22652.2 | AH85: =ABS(AF85-AG85) -> 18700.046 | AI85: =IF(AF85=0,0,AH85/AF85) -> 0.45221355 | AJ85: =AJ84+AF85 -> 4007413 | AK85: =AJ85/SUM(AF:AF) -> 0.36611529 | AL85: =MIN(AC85,'What-If Analysis'!$B$2) -> 0.063 | AM85: =AE85*(1+'What-If Analysis'!$B$3) -> 26 | AN85: =Y85*(1+'What-If Analysis'!$B$4) -> 1245.871 | AO85: =AA85*AM85*(1-AL85) -> 53757.92
A86: ORD-2025-673091 | B86: 45784 | C86: =IF(D86<B86,D86,B86) -> 45784 | D86: 45790 | E86: =IF(D86<B86,B86,D86) -> 45790 | F86: =E86-C86 -> 6 | G86: =IF(Data!F50<=7,1,0) -> 0 | H86: =TEXT(C86,"MM-YYYY") -> 05-2025 | I86: ="Q"&ROUNDUP(MONTH(H86)/3,0)&"-"&YEAR(H86) -> Q2-2025 | J86: =_xlfn.MINIFS(C:C,M:M,M86) -> 44955 | K86: =TEXT(J86,"MM-YYYY") -> 01-2023 | L86: Asia | M86: India | N86: Bengaluru | O86: =IF(N86="",_xlfn.XLOOKUP(M86,M:M,N:N),N86) -> Bengaluru | P86: Enterprise | Q86: Direct | R86: =IF(Q86="",_xlfn.XLOOKUP(M86,M:M,Q:Q),Q86) -> Direct | S86: J. Njeri | T86: =IF(S86="",_xlfn.XLOOKUP(L86,L:L,S:S),S86) -> J. Njeri | U86: Phones | V86: =IF(AA86<815.0987,"Low",IF(AA86<1640.058,"Medium","High")) -> High | W86: PHN-5683 | X86: =IF(AK86<=80%,"A",IF(AK86<=95%,"B","C")) -> A | Y86: 935.98 | Z86: 2077.69 | AA86: =ABS(Z86) -> 2077.69 | AB86: 0.175 | AC86: =MIN(AB86,30%) -> 0.175 | AD86: =IF(AC86>20%,1,0) -> 0 | AE86: 24 | AF86: =AA86*AE86*(1-AC86) -> 41138.262 | AG86: =Y86*AE86 -> 22463.52 | AH86: =ABS(AF86-AG86) -> 18674.742 | AI86: =IF(AF86=0,0,AH86/AF86) -> 0.45395068 | AJ86: =AJ85+AF86 -> 4048551.3 | AK86: =AJ86/SUM(AF:AF) -> 0.36987366 | AL86: =MIN(AC86,'What-If Analysis'!$B$2) -> 0.175 | AM86: =AE86*(1+'What-If Analysis'!$B$3) -> 31.2 | AN86: =Y86*(1+'What-If Analysis'!$B$4) -> 1029.578 | AO86: =AA86*AM86*(1-AL86) -> 53479.741
A87: ORD-2024-638884 | B87: 45440 | C87: =IF(D87<B87,D87,B87) -> 45438 | D87: 45438 | E87: =IF(D87<B87,B87,D87) -> 45440 | F87: =E87-C87 -> 2 | G87: =IF(Data!F81<=7,1,0) -> 0 | H87: =TEXT(C87,"MM-YYYY") -> 05-2024 | I87: ="Q"&ROUNDUP(MONTH(H87)/3,0)&"-"&YEAR(H87) -> Q2-2024 | J87: =_xlfn.MINIFS(C:C,M:M,M87) -> 44939 | K87: =TEXT(J87,"MM-YYYY") -> 01-2023 | L87: Africa | M87: Nigeria | N87: Abuja | O87: =IF(N87="",_xlfn.XLOOKUP(M87,M:M,N:N),N87) -> Abuja | P87: Enterprise | Q87: Online | R87: =IF(Q87="",_xlfn.XLOOKUP(M87,M:M,Q:Q),Q87) -> Online | S87: F. Müller | T87: =IF(S87="",_xlfn.XLOOKUP(L87,L:L,S:S),S87) -> F. Müller | U87: Accessories | V87: =IF(AA87<815.0987,"Low",IF(AA87<1640.058,"Medium","High")) -> High | W87: ACC-5177 | X87: =IF(AK87<=80%,"A",IF(AK87<=95%,"B","C")) -> A | Y87: 1227.08 | Z87: 1896.62 | AA87: =ABS(Z87) -> 1896.62 | AB87: 0 | AC87: =MIN(AB87,30%) -> 0 | AD87: =IF(AC87>20%,1,0) -> 0 | AE87: 18 | AF87: =AA87*AE87*(1-AC87) -> 34139.16 | AG87: =Y87*AE87 -> 22087.44 | AH87: =ABS(AF87-AG87) -> 12051.72 | AI87: =IF(AF87=0,0,AH87/AF87) -> 0.35301747 | AJ87: =AJ86+AF87 -> 4082690.5 | AK87: =AJ87/SUM(AF:AF) -> 0.3729926 | AL87: =MIN(AC87,'What-If Analysis'!$B$2) -> 0 | AM87: =AE87*(1+'What-If Analysis'!$B$3) -> 23.4 | AN87: =Y87*(1+'What-If Analysis'!$B$4) -> 1349.788 | AO87: =AA87*AM87*(1-AL87) -> 44380.908
A88: ORD-2024-626925 | B88: 45450 | C88: =IF(D88<B88,D88,B88) -> 45450 | D88: 45452 | E88: =IF(D88<B88,B88,D88) -> 45452 | F88: =E88-C88 -> 2 | G88: =IF(Data!F107<=7,1,0) -> 0 | H88: =TEXT(C88,"MM-YYYY") -> 06-2024 | I88: ="Q"&ROUNDUP(MONTH(H88)/3,0)&"-"&YEAR(H88) -> Q2-2024 | J88: =_xlfn.MINIFS(C:C,M:M,M88) -> 44938 | K88: =TEXT(J88,"MM-YYYY") -> 01-2023 | L88: Asia | M88: China | N88: Shanghai | O88: =IF(N88="",_xlfn.XLOOKUP(M88,M:M,N:N),N88) -> Shanghai | P88: Corporate | Q88: Retail | R88: =IF(Q88="",_xlfn.XLOOKUP(M88,M:M,Q:Q),Q88) -> Retail | S88: O. Wang | T88: =IF(S88="",_xlfn.XLOOKUP(L88,L:L,S:S),S88) -> O. Wang | U88: Monitors | V88: =IF(AA88<815.0987,"Low",IF(AA88<1640.058,"Medium","High")) -> High | W88: MON-8688 | X88: =IF(AK88<=80%,"A",IF(AK88<=95%,"B","C")) -> A | Y88: 1370.28 | Z88: 2209.66 | AA88: =ABS(Z88) -> 2209.66 | AB88: 0.133 | AC88: =MIN(AB88,30%) -> 0.133 | AD88: =IF(AC88>20%,1,0) -> 0 | AE88: 16 | AF88: =AA88*AE88*(1-AC88) -> 30652.404 | AG88: =Y88*AE88 -> 21924.48 | AH88: =ABS(AF88-AG88) -> 8727.9235 | AI88: =IF(AF88=0,0,AH88/AF88) -> 0.28473863 | AJ88: =AJ87+AF88 -> 4113342.9 | AK88: =AJ88/SUM(AF:AF) -> 0.37579299 | AL88: =MIN(AC88,'What-If Analysis'!$B$2) -> 0.133 | AM88: =AE88*(1+'What-If Analysis'!$B$3) -> 20.8 | AN88: =Y88*(1+'What-If Analysis'!$B$4) -> 1507.308 | AO88: =AA88*AM88*(1-AL88) -> 39848.125
A89: ORD-2023-569862 | B89: 45123 | C89: =IF(D89<B89,D89,B89) -> 45123 | D89: 45151 | E89: =IF(D89<B89,B89,D89) -> 45151 | F89: =E89-C89 -> 28 | G89: =IF(Data!F47<=7,1,0) -> 0 | H89: =TEXT(C89,"MM-YYYY") -> 07-2023 | I89: ="Q"&ROUNDUP(MONTH(H89)/3,0)&"-"&YEAR(H89) -> Q3-2023 | J89: =_xlfn.MINIFS(C:C,M:M,M89) -> 44945 | K89: =TEXT(J89,"MM-YYYY") -> 01-2023 | L89: Europe | M89: United Kingdom | N89: Manchester | O89: =IF(N89="",_xlfn.XLOOKUP(M89,M:M,N:N),N89) -> Manchester | P89: Non-Profit | Q89: Online | R89: =IF(Q89="",_xlfn.XLOOKUP(M89,M:M,Q:Q),Q89) -> Online | S89: J. Njeri | T89: =IF(S89="",_xlfn.XLOOKUP(L89,L:L,S:S),S89) -> J. Njeri | U89: Laptops | V89: =IF(AA89<815.0987,"Low",IF(AA89<1640.058,"Medium","High")) -> High | W89: LAP-1178 | X89: =IF(AK89<=80%,"A",IF(AK89<=95%,"B","C")) -> A | Y89: 1039.03 | Z89: 2545.81 | AA89: =ABS(Z89) -> 2545.81 | AB89: 0.216 | AC89: =MIN(AB89,30%) -> 0.216 | AD89: =IF(AC89>20%,1,0) -> 1 | AE89: 21 | AF89: =AA89*AE89*(1-AC89) -> 41914.216 | AG89: =Y89*AE89 -> 21819.63 | AH89: =ABS(AF89-AG89) -> 20094.586 | AI89: =IF(AF89=0,0,AH89/AF89) -> 0.47942173 | AJ89: =AJ88+AF89 -> 4155257.1 | AK89: =AJ89/SUM(AF:AF) -> 0.37962225 | AL89: =MIN(AC89,'What-If Analysis'!$B$2) -> 0.2 | AM89: =AE89*(1+'What-If Analysis'!$B$3) -> 27.3 | AN89: =Y89*(1+'What-If Analysis'!$B$4) -> 1142.933 | AO89: =AA89*AM89*(1-AL89) -> 55600.49
A90: ORD-2025-949776 | B90: 45883 | C90: =IF(D90<B90,D90,B90) -> 45883 | D90: 45911 | E90: =IF(D90<B90,B90,D90) -> 45911 | F90: =E90-C90 -> 28 | G90: =IF(Data!F41<=7,1,0) -> 0 | H90: =TEXT(C90,"MM-YYYY") -> 08-2025 | I90: ="Q"&ROUNDUP(MONTH(H90)/3,0)&"-"&YEAR(H90) -> Q3-2025 | J90: =_xlfn.MINIFS(C:C,M:M,M90) -> 44955 | K90: =TEXT(J90,"MM-YYYY") -> 01-2023 | L90: Americas | M90: Brazil | N90: São Paulo | O90: =IF(N90="",_xlfn.XLOOKUP(M90,M:M,N:N),N90) -> São Paulo | P90: Non-Profit | Q90: Direct | R90: =IF(Q90="",_xlfn.XLOOKUP(M90,M:M,Q:Q),Q90) -> Direct | S90: F. Müller | T90: =IF(S90="",_xlfn.XLOOKUP(L90,L:L,S:S),S90) -> F. Müller | U90: Printers | V90: =IF(AA90<815.0987,"Low",IF(AA90<1640.058,"Medium","High")) -> High | W90: PRN-9490 | X90: =IF(AK90<=80%,"A",IF(AK90<=95%,"B","C")) -> A | Y90: 1203.02 | Z90: 2439.33 | AA90: =ABS(Z90) -> 2439.33 | AB90: 0 | AC90: =MIN(AB90,30%) -> 0 | AD90: =IF(AC90>20%,1,0) -> 0 | AE90: 18 | AF90: =AA90*AE90*(1-AC90) -> 43907.94 | AG90: =Y90*AE90 -> 21654.36 | AH90: =ABS(AF90-AG90) -> 22253.58 | AI90: =IF(AF90=0,0,AH90/AF90) -> 0.5068236 | AJ90: =AJ89+AF90 -> 4199165 | AK90: =AJ90/SUM(AF:AF) -> 0.38363366 | AL90: =MIN(AC90,'What-If Analysis'!$B$2) -> 0 | AM90: =AE90*(1+'What-If Analysis'!$B$3) -> 23.4 | AN90: =Y90*(1+'What-If Analysis'!$B$4) -> 1323.322 | AO90: =AA90*AM90*(1-AL90) -> 57080.322
A91: ORD-2023-369160 | B91: 45131 | C91: =IF(D91<B91,D91,B91) -> 45131 | D91: 45151 | E91: =IF(D91<B91,B91,D91) -> 45151 | F91: =E91-C91 -> 20 | G91: =IF(Data!F116<=7,1,0) -> 0 | H91: =TEXT(C91,"MM-YYYY") -> 07-2023 | I91: ="Q"&ROUNDUP(MONTH(H91)/3,0)&"-"&YEAR(H91) -> Q3-2023 | J91: =_xlfn.MINIFS(C:C,M:M,M91) -> 44928 | K91: =TEXT(J91,"MM-YYYY") -> 01-2023 | L91: Americas | M91: Canada | N91: Montreal | O91: =IF(N91="",_xlfn.XLOOKUP(M91,M:M,N:N),N91) -> Montreal | P91: Education | Q91: Direct | R91: =IF(Q91="",_xlfn.XLOOKUP(M91,M:M,Q:Q),Q91) -> Direct | S91: C. Otieno | T91: =IF(S91="",_xlfn.XLOOKUP(L91,L:L,S:S),S91) -> C. Otieno | U91: Monitors | V91: =IF(AA91<815.0987,"Low",IF(AA91<1640.058,"Medium","High")) -> High | W91: MON-3307 | X91: =IF(AK91<=80%,"A",IF(AK91<=95%,"B","C")) -> A | Y91: 1082.38 | Z91: 1766.55 | AA91: =ABS(Z91) -> 1766.55 | AB91: 0.164 | AC91: =MIN(AB91,30%) -> 0.164 | AD91: =IF(AC91>20%,1,0) -> 0 | AE91: 20 | AF91: =AA91*AE91*(1-AC91) -> 29536.716 | AG91: =Y91*AE91 -> 21647.6 | AH91: =ABS(AF91-AG91) -> 7889.116 | AI91: =IF(AF91=0,0,AH91/AF91) -> 0.26709523 | AJ91: =AJ90+AF91 -> 4228701.7 | AK91: =AJ91/SUM(AF:AF) -> 0.38633212 | AL91: =MIN(AC91,'What-If Analysis'!$B$2) -> 0.164 | AM91: =AE91*(1+'What-If Analysis'!$B$3) -> 26 | AN91: =Y91*(1+'What-If Analysis'!$B$4) -> 1190.618 | AO91: =AA91*AM91*(1-AL91) -> 38397.731
A92: ORD-2023-422918 | B92: 44985 | C92: =IF(D92<B92,D92,B92) -> 44985 | D92: 45005 | E92: =IF(D92<B92,B92,D92) -> 45005 | F92: =E92-C92 -> 20 | G92: =IF(Data!F146<=7,1,0) -> 0 | H92: =TEXT(C92,"MM-YYYY") -> 02-2023 | I92: ="Q"&ROUNDUP(MONTH(H92)/3,0)&"-"&YEAR(H92) -> Q1-2023 | J92: =_xlfn.MINIFS(C:C,M:M,M92) -> 44947 | K92: =TEXT(J92,"MM-YYYY") -> 01-2023 | L92: Europe | M92: Germany | N92: Berlin | O92: =IF(N92="",_xlfn.XLOOKUP(M92,M:M,N:N),N92) -> Berlin | P92: Small Business | Q92: Direct | R92: =IF(Q92="",_xlfn.XLOOKUP(M92,M:M,Q:Q),Q92) -> Direct | S92: H. Kim | T92: =IF(S92="",_xlfn.XLOOKUP(L92,L:L,S:S),S92) -> H. Kim | U92: Laptops | V92: =IF(AA92<815.0987,"Low",IF(AA92<1640.058,"Medium","High")) -> High | W92: LAP-3679 | X92: =IF(AK92<=80%,"A",IF(AK92<=95%,"B","C")) -> A | Y92: 1200.78 | Z92: 2001.17 | AA92: =ABS(Z92) -> 2001.17 | AB92: 0.292 | AC92: =MIN(AB92,30%) -> 0.292 | AD92: =IF(AC92>20%,1,0) -> 1 | AE92: 18 | AF92: =AA92*AE92*(1-AC92) -> 25502.91 | AG92: =Y92*AE92 -> 21614.04 | AH92: =ABS(AF92-AG92) -> 3888.8705 | AI92: =IF(AF92=0,0,AH92/AF92) -> 0.15248732 | AJ92: =AJ91+AF92 -> 4254204.6 | AK92: =AJ92/SUM(AF:AF) -> 0.38866205 | AL92: =MIN(AC92,'What-If Analysis'!$B$2) -> 0.2 | AM92: =AE92*(1+'What-If Analysis'!$B$3) -> 23.4 | AN92: =Y92*(1+'What-If Analysis'!$B$4) -> 1320.858 | AO92: =AA92*AM92*(1-AL92) -> 37461.902
A93: ORD-2025-328504 | B93: 45684 | C93: =IF(D93<B93,D93,B93) -> 45684 | D93: 45703 | E93: =IF(D93<B93,B93,D93) -> 45703 | F93: =E93-C93 -> 19 | G93: =IF(Data!F28<=7,1,0) -> 1 | H93: =TEXT(C93,"MM-YYYY") -> 01-2025 | I93: ="Q"&ROUNDUP(MONTH(H93)/3,0)&"-"&YEAR(H93) -> Q1-2025 | J93: =_xlfn.MINIFS(C:C,M:M,M93) -> 44938 | K93: =TEXT(J93,"MM-YYYY") -> 01-2023 | L93: Asia | M93: China | N93: Shenzhen | O93: =IF(N93="",_xlfn.XLOOKUP(M93,M:M,N:N),N93) -> Shenzhen | P93: Non-Profit | Q93: Direct | R93: =IF(Q93="",_xlfn.XLOOKUP(M93,M:M,Q:Q),Q93) -> Direct | S93: L. Okafor | T93: =IF(S93="",_xlfn.XLOOKUP(L93,L:L,S:S),S93) -> L. Okafor | U93: Phones | V93: =IF(AA93<815.0987,"Low",IF(AA93<1640.058,"Medium","High")) -> High | W93: PHN-8368 | X93: =IF(AK93<=80%,"A",IF(AK93<=95%,"B","C")) -> A | Y93: 1253.22 | Z93: 3104.71 | AA93: =ABS(Z93) -> 3104.71 | AB93: 0 | AC93: =MIN(AB93,30%) -> 0 | AD93: =IF(AC93>20%,1,0) -> 0 | AE93: 17 | AF93: =AA93*AE93*(1-AC93) -> 52780.07 | AG93: =Y93*AE93 -> 21304.74 | AH93: =ABS(AF93-AG93) -> 31475.33 | AI93: =IF(AF93=0,0,AH93/AF93) -> 0.59634877 | AJ93: =AJ92+AF93 -> 4306984.7 | AK93: =AJ93/SUM(AF:AF) -> 0.39348402 | AL93: =MIN(AC93,'What-If Analysis'!$B$2) -> 0 | AM93: =AE93*(1+'What-If Analysis'!$B$3) -> 22.1 | AN93: =Y93*(1+'What-If Analysis'!$B$4) -> 1378.542 | AO93: =AA93*AM93*(1-AL93) -> 68614.091
A94: ORD-2024-500511 | B94: 45573 | C94: =IF(D94<B94,D94,B94) -> 45573 | D94: 45573 | E94: =IF(D94<B94,B94,D94) -> 45573 | F94: =E94-C94 -> 0 | G94: =IF(Data!F62<=7,1,0) -> 0 | H94: =TEXT(C94,"MM-YYYY") -> 10-2024 | I94: ="Q"&ROUNDUP(MONTH(H94)/3,0)&"-"&YEAR(H94) -> Q4-2024 | J94: =_xlfn.MINIFS(C:C,M:M,M94) -> 44945 | K94: =TEXT(J94,"MM-YYYY") -> 01-2023 | L94: Europe | M94: United Kingdom | N94: London | O94: =IF(N94="",_xlfn.XLOOKUP(M94,M:M,N:N),N94) -> London | P94: Corporate | Q94: Online | R94: =IF(Q94="",_xlfn.XLOOKUP(M94,M:M,Q:Q),Q94) -> Online | S94: E. Garcia | T94: =IF(S94="",_xlfn.XLOOKUP(L94,L:L,S:S),S94) -> E. Garcia | U94: Monitors | V94: =IF(AA94<815.0987,"Low",IF(AA94<1640.058,"Medium","High")) -> High | W94: MON-9733 | X94: =IF(AK94<=80%,"A",IF(AK94<=95%,"B","C")) -> A | Y94: 1108.11 | Z94: 2503.79 | AA94: =ABS(Z94) -> 2503.79 | AB94: 0.184 | AC94: =MIN(AB94,30%) -> 0.184 | AD94: =IF(AC94>20%,1,0) -> 0 | AE94: 19 | AF94: =AA94*AE94*(1-AC94) -> 38818.76 | AG94: =Y94*AE94 -> 21054.09 | AH94: =ABS(AF94-AG94) -> 17764.67 | AI94: =IF(AF94=0,0,AH94/AF94) -> 0.45763105 | AJ94: =AJ93+AF94 -> 4345803.5 | AK94: =AJ94/SUM(AF:AF) -> 0.39703048 | AL94: =MIN(AC94,'What-If Analysis'!$B$2) -> 0.184 | AM94: =AE94*(1+'What-If Analysis'!$B$3) -> 24.7 | AN94: =Y94*(1+'What-If Analysis'!$B$4) -> 1218.921 | AO94: =AA94*AM94*(1-AL94) -> 50464.388
A95: ORD-2024-993481 | B95: 45522 | C95: =IF(D95<B95,D95,B95) -> 45522 | D95: 45547 | E95: =IF(D95<B95,B95,D95) -> 45547 | F95: =E95-C95 -> 25 | G95: =IF(Data!F199<=7,1,0) -> 0 | H95: =TEXT(C95,"MM-YYYY") -> 08-2024 | I95: ="Q"&ROUNDUP(MONTH(H95)/3,0)&"-"&YEAR(H95) -> Q3-2024 | J95: =_xlfn.MINIFS(C:C,M:M,M95) -> 44955 | K95: =TEXT(J95,"MM-YYYY") -> 01-2023 | L95: Asia | M95: India | N95: Mumbai | O95: =IF(N95="",_xlfn.XLOOKUP(M95,M:M,N:N),N95) -> Mumbai | P95: Consumer | Q95: Marketplace | R95: =IF(Q95="",_xlfn.XLOOKUP(M95,M:M,Q:Q),Q95) -> Marketplace | S95: C. Otieno | T95: =IF(S95="",_xlfn.XLOOKUP(L95,L:L,S:S),S95) -> C. Otieno | U95: Phones | V95: =IF(AA95<815.0987,"Low",IF(AA95<1640.058,"Medium","High")) -> Medium | W95: PHN-3077 | X95: =IF(AK95<=80%,"A",IF(AK95<=95%,"B","C")) -> A | Y95: 1154.03 | Z95: 1590.36 | AA95: =ABS(Z95) -> 1590.36 | AB95: 0.314 | AC95: =MIN(AB95,30%) -> 0.3 | AD95: =IF(AC95>20%,1,0) -> 1 | AE95: 18 | AF95: =AA95*AE95*(1-AC95) -> 20038.536 | AG95: =Y95*AE95 -> 20772.54 | AH95: =ABS(AF95-AG95) -> 734.004 | AI95: =IF(AF95=0,0,AH95/AF95) -> 0.036629622 | AJ95: =AJ94+AF95 -> 4365842 | AK95: =AJ95/SUM(AF:AF) -> 0.39886119 | AL95: =MIN(AC95,'What-If Analysis'!$B$2) -> 0.2 | AM95: =AE95*(1+'What-If Analysis'!$B$3) -> 23.4 | AN95: =Y95*(1+'What-If Analysis'!$B$4) -> 1269.433 | AO95: =AA95*AM95*(1-AL95) -> 29771.539
A96: ORD-2023-808024 | B96: 45290 | C96: =IF(D96<B96,D96,B96) -> 45290 | D96: 45299 | E96: =IF(D96<B96,B96,D96) -> 45299 | F96: =E96-C96 -> 9 | G96: =IF(Data!F158<=7,1,0) -> 0 | H96: =TEXT(C96,"MM-YYYY") -> 12-2023 | I96: ="Q"&ROUNDUP(MONTH(H96)/3,0)&"-"&YEAR(H96) -> Q4-2023 | J96: =_xlfn.MINIFS(C:C,M:M,M96) -> 44936 | K96: =TEXT(J96,"MM-YYYY") -> 01-2023 | L96: Europe | M96: France | N96: Marseille | O96: =IF(N96="",_xlfn.XLOOKUP(M96,M:M,N:N),N96) -> Marseille | P96: Consumer | Q96: Marketplace | R96: =IF(Q96="",_xlfn.XLOOKUP(M96,M:M,Q:Q),Q96) -> Marketplace | S96: L. Okafor | T96: =IF(S96="",_xlfn.XLOOKUP(L96,L:L,S:S),S96) -> L. Okafor | U96: Accessories | V96: =IF(AA96<815.0987,"Low",IF(AA96<1640.058,"Medium","High")) -> Medium | W96: ACC-6594 | X96: =IF(AK96<=80%,"A",IF(AK96<=95%,"B","C")) -> A | Y96: 861.1 | Z96: 1224.72 | AA96: =ABS(Z96) -> 1224.72 | AB96: 0.174 | AC96: =MIN(AB96,30%) -> 0.174 | AD96: =IF(AC96>20%,1,0) -> 0 | AE96: 24 | AF96: =AA96*AE96*(1-AC96) -> 24278.849 | AG96: =Y96*AE96 -> 20666.4 | AH96: =ABS(AF96-AG96) -> 3612.4493 | AI96: =IF(AF96=0,0,AH96/AF96) -> 0.14878997 | AJ96: =AJ95+AF96 -> 4390120.9 | AK96: =AJ96/SUM(AF:AF) -> 0.40107929 | AL96: =MIN(AC96,'What-If Analysis'!$B$2) -> 0.174 | AM96: =AE96*(1+'What-If Analysis'!$B$3) -> 31.2 | AN96: =Y96*(1+'What-If Analysis'!$B$4) -> 947.21 | AO96: =AA96*AM96*(1-AL96) -> 31562.504
A97: ORD-2024-966651 | B97: 45579 | C97: =IF(D97<B97,D97,B97) -> 45579 | D97: 45604 | E97: =IF(D97<B97,B97,D97) -> 45604 | F97: =E97-C97 -> 25 | G97: =IF(Data!F70<=7,1,0) -> 1 | H97: =TEXT(C97,"MM-YYYY") -> 10-2024 | I97: ="Q"&ROUNDUP(MONTH(H97)/3,0)&"-"&YEAR(H97) -> Q4-2024 | J97: =_xlfn.MINIFS(C:C,M:M,M97) -> 44939 | K97: =TEXT(J97,"MM-YYYY") -> 01-2023 | L97: Africa | M97: Nigeria | N97: Lagos | O97: =IF(N97="",_xlfn.XLOOKUP(M97,M:M,N:N),N97) -> Lagos | P97: Enterprise | Q97: Online | R97: =IF(Q97="",_xlfn.XLOOKUP(M97,M:M,Q:Q),Q97) -> Online | S97: O. Wang | T97: =IF(S97="",_xlfn.XLOOKUP(L97,L:L,S:S),S97) -> O. Wang | U97: Networking | V97: =IF(AA97<815.0987,"Low",IF(AA97<1640.058,"Medium","High")) -> High | W97: NET-5268 | X97: =IF(AK97<=80%,"A",IF(AK97<=95%,"B","C")) -> A | Y97: 859.35 | Z97: 1825.61 | AA97: =ABS(Z97) -> 1825.61 | AB97: 0.187 | AC97: =MIN(AB97,30%) -> 0.187 | AD97: =IF(AC97>20%,1,0) -> 0 | AE97: 24 | AF97: =AA97*AE97*(1-AC97) -> 35621.302 | AG97: =Y97*AE97 -> 20624.4 | AH97: =ABS(AF97-AG97) -> 14996.902 | AI97: =IF(AF97=0,0,AH97/AF97) -> 0.42100938 | AJ97: =AJ96+AF97 -> 4425742.2 | AK97: =AJ97/SUM(AF:AF) -> 0.40433364 | AL97: =MIN(AC97,'What-If Analysis'!$B$2) -> 0.187 | AM97: =AE97*(1+'What-If Analysis'!$B$3) -> 31.2 | AN97: =Y97*(1+'What-If Analysis'!$B$4) -> 945.285 | AO97: =AA97*AM97*(1-AL97) -> 46307.693
A98: ORD-2025-898022 | B98: 45902 | C98: =IF(D98<B98,D98,B98) -> 45902 | D98: 45911 | E98: =IF(D98<B98,B98,D98) -> 45911 | F98: =E98-C98 -> 9 | G98: =IF(Data!F306<=7,1,0) -> 0 | H98: =TEXT(C98,"MM-YYYY") -> 09-2025 | I98: ="Q"&ROUNDUP(MONTH(H98)/3,0)&"-"&YEAR(H98) -> Q3-2025 | J98: =_xlfn.MINIFS(C:C,M:M,M98) -> 44928 | K98: =TEXT(J98,"MM-YYYY") -> 01-2023 | L98: Americas | M98: Canada | N98: Toronto | O98: =IF(N98="",_xlfn.XLOOKUP(M98,M:M,N:N),N98) -> Toronto | P98: Corporate | Q98: Distributor | R98: =IF(Q98="",_xlfn.XLOOKUP(M98,M:M,Q:Q),Q98) -> Distributor | S98: M. Rossi | T98: =IF(S98="",_xlfn.XLOOKUP(L98,L:L,S:S),S98) -> M. Rossi | U98: Printers | V98: =IF(AA98<815.0987,"Low",IF(AA98<1640.058,"Medium","High")) -> Medium | W98: PRN-1276 | X98: =IF(AK98<=80%,"A",IF(AK98<=95%,"B","C")) -> A | Y98: 1207.63 | Z98: 921.68 | AA98: =ABS(Z98) -> 921.68 | AB98: 0.196 | AC98: =MIN(AB98,30%) -> 0.196 | AD98: =IF(AC98>20%,1,0) -> 0 | AE98: 17 | AF98: =AA98*AE98*(1-AC98) -> 12597.522 | AG98: =Y98*AE98 -> 20529.71 | AH98: =ABS(AF98-AG98) -> 7932.1878 | AI98: =IF(AF98=0,0,AH98/AF98) -> 0.62966253 | AJ98: =AJ97+AF98 -> 4438339.7 | AK98: =AJ98/SUM(AF:AF) -> 0.40548454 | AL98: =MIN(AC98,'What-If Analysis'!$B$2) -> 0.196 | AM98: =AE98*(1+'What-If Analysis'!$B$3) -> 22.1 | AN98: =Y98*(1+'What-If Analysis'!$B$4) -> 1328.393 | AO98: =AA98*AM98*(1-AL98) -> 16376.779
A99: ORD-2024-102866 | B99: 45638 | C99: =IF(D99<B99,D99,B99) -> 45638 | D99: 45646 | E99: =IF(D99<B99,B99,D99) -> 45646 | F99: =E99-C99 -> 8 | G99: =IF(Data!F215<=7,1,0) -> 0 | H99: =TEXT(C99,"MM-YYYY") -> 12-2024 | I99: ="Q"&ROUNDUP(MONTH(H99)/3,0)&"-"&YEAR(H99) -> Q4-2024 | J99: =_xlfn.MINIFS(C:C,M:M,M99) -> 44988 | K99: =TEXT(J99,"MM-YYYY") -> 03-2023 | L99: Asia | M99: Japan | N99: Tokyo | O99: =IF(N99="",_xlfn.XLOOKUP(M99,M:M,N:N),N99) -> Tokyo | P99: Corporate | Q99: Retail | R99: =IF(Q99="",_xlfn.XLOOKUP(M99,M:M,Q:Q),Q99) -> Retail | S99: B. Chen | T99: =IF(S99="",_xlfn.XLOOKUP(L99,L:L,S:S),S99) -> B. Chen | U99: Laptops | V99: =IF(AA99<815.0987,"Low",IF(AA99<1640.058,"Medium","High")) -> Medium | W99: LAP-8347 | X99: =IF(AK99<=80%,"A",IF(AK99<=95%,"B","C")) -> A | Y99: 1202.47 | Z99: 1444.72 | AA99: =ABS(Z99) -> 1444.72 | AB99: 0.241 | AC99: =MIN(AB99,30%) -> 0.241 | AD99: =IF(AC99>20%,1,0) -> 1 | AE99: 17 | AF99: =AA99*AE99*(1-AC99) -> 18641.222 | AG99: =Y99*AE99 -> 20441.99 | AH99: =ABS(AF99-AG99) -> 1800.7678 | AI99: =IF(AF99=0,0,AH99/AF99) -> 0.096601383 | AJ99: =AJ98+AF99 -> 4456980.9 | AK99: =AJ99/SUM(AF:AF) -> 0.40718759 | AL99: =MIN(AC99,'What-If Analysis'!$B$2) -> 0.2 | AM99: =AE99*(1+'What-If Analysis'!$B$3) -> 22.1 | AN99: =Y99*(1+'What-If Analysis'!$B$4) -> 1322.717 | AO99: =AA99*AM99*(1-AL99) -> 25542.65
A100: ORD-2024-930679 | B100: 45643 | C100: =IF(D100<B100,D100,B100) -> 45643 | D100: 45673 | E100: =IF(D100<B100,B100,D100) -> 45673 | F100: =E100-C100 -> 30 | G100: =IF(Data!F600<=7,1,0) -> 1 | H100: =TEXT(C100,"MM-YYYY") -> 12-2024 | I100: ="Q"&ROUNDUP(MONTH(H100)/3,0)&"-"&YEAR(H100) -> Q4-2024 | J100: =_xlfn.MINIFS(C:C,M:M,M100) -> 44945 | K100: =TEXT(J100,"MM-YYYY") -> 01-2023 | L100: Europe | M100: United Kingdom | N100: Manchester | O100: =IF(N100="",_xlfn.XLOOKUP(M100,M:M,N:N),N100) -> Manchester | P100: Corporate | Q100: Retail | R100: =IF(Q100="",_xlfn.XLOOKUP(M100,M:M,Q:Q),Q100) -> Retail | S100: D. Smith | T100: =IF(S100="",_xlfn.XLOOKUP(L100,L:L,S:S),S100) -> D. Smith | U100: Monitors | V100: =IF(AA100<815.0987,"Low",IF(AA100<1640.058,"Medium","High")) -> Low | W100: MON-4215 | X100: =IF(AK100<=80%,"A",IF(AK100<=95%,"B","C")) -> A | Y100: 722.87 | Z100: -33.66 | AA100: =ABS(Z100) -> 33.66 | AB100: 0.102 | AC100: =MIN(AB100,30%) -> 0.102 | AD100: =IF(AC100>20%,1,0) -> 0 | AE100: 28 | AF100: =AA100*AE100*(1-AC100) -> 846.34704 | AG100: =Y100*AE100 -> 20240.36 | AH100: =ABS(AF100-AG100) -> 19394.013 | AI100: =IF(AF100=0,0,AH100/AF100) -> 22.914965 | AJ100: =AJ99+AF100 -> 4457827.2 | AK100: =AJ100/SUM(AF:AF) -> 0.40726492 | AL100: =MIN(AC100,'What-If Analysis'!$B$2) -> 0.102 | AM100: =AE100*(1+'What-If Analysis'!$B$3) -> 36.4 | AN100: =Y100*(1+'What-If Analysis'!$B$4) -> 795.157 | AO100: =AA100*AM100*(1-AL100) -> 1100.2512
...

Sheet What-If Analysis
A2: Global Discount Cap | B2: 0.2
A3: Quantity Uplift | B3: 0.3
A4: UnitCost inflation factor | B4: 0.1
A7: Baseline Revenue | B7: =SUM(Data!AF:AF) -> 10945768
A8: Scenario Revenue | B8: =SUM(Data!AO:AO) -> 14344693

Sheet Brief
A1: Assignment
A2: Excel Mastery Assignment: Sales Operations & Analytics
A4: Overview:
A5: You are an analyst for a multi-regional electronics distributor. The 'Data' sheet contains 632 rows and 15 columns of transactional data with intentional data-quality issues.
A6: Your job is to clean, enrich, analyze, and present insights via a dynamic dashboard.
A8: Part A — Data Cleaning & Preparation:
A9: 1) Create a staging table where you:
A10: • Remove exact duplicate rows (define and document your duplicate criteria).
A11: • Fix data types (dates as Dates, numeric fields as numbers).
A12: • Handle missing values for City, Salesperson, and Channel using reasonable business logic (document your approach).
A13: • Flag and correct suspicious UnitPrice values (e.g., negative prices) and discounts (e.g., > 30%).
A14: • Ensure RequiredDate is not earlier than OrderDate; where it is, impute a corrected RequiredDate (explain your rule).
... A67: 15) Ensure your dashboard responds to slicers without broken references.

Sheet Dashboard

Sheet Dashboard Report
